<?xml version="1.0" encoding="UTF-8"?><results filename="2"><w>319997</w><o>80</o><u>http://www.microsoft.com/about/en/us/default.aspx</u><r>45</r><i>sitespeed.io</i><lt>3805</lt><g><ynumreq><score>11</score><message>This page has 10 external Javascript scripts.  Try combining them into one.
This page has 8 external stylesheets.  Try combining them into one.
This page has 13 external background images.  Try combining them with CSS sprites.</message><components></components></ynumreq><yemptysrc><score>100</score><message></message><components></components></yemptysrc><ycompress><score>100</score><message></message><components></components></ycompress><ycsstop><score>100</score><message></message><components></components></ycsstop><yjsbottom><score>100</score><message></message><components></components></yjsbottom><yexpressions><score>86</score><message>There is a total of 2 expressions</message><components><item><![CDATA[http://www.microsoft.com/about/shared/core/2/css/css.ashx?sc=/about/en/us/site.config&pc=/about/en/us/PageConfig/default.xml&c=alVertNav;cspAdControl]]></item></components></yexpressions><yexternal><message>Only consider this if your property is a common user home page.</message><components><item>There is a total of 2 inline css</item><item>There is a total of 6 inline scripts</item></components></yexternal><ydns><score>80</score><message>The components are split over more than 4 domains</message><components><item>www.microsoft.com: 19 components, 94.2K (85.0K GZip)</item><item>ajax.microsoft.com: 1 component, 70.8K (38.2K GZip)</item><item>i3.microsoft.com: 10 components, 158.7K (68.1K GZip)</item><item>m.webtrends.com: 1 component, 0.06K</item><item>c.microsoft.com: 1 component, 13.4K (13.4K GZip)</item><item>i2.microsoft.com: 3 components, 8.7K</item><item>i.microsoft.com: 8 components, 55.8K</item><item>c1.microsoft.com: 2 components, 0.08K</item></components></ydns><yminify><score>60</score><message>There are 4 components that can be minified</message><components><item>http://www.microsoft.com/global/about/en/us/RenderingAssets/default.css</item><item>http://i3.microsoft.com/global/en/us/renderingassets/webtrends_15_1.js</item><item><![CDATA[inline &lt;script&gt; tag #2]]></item><item><![CDATA[inline &lt;script&gt; tag #5]]></item></components></yminify><yredirects><score>100</score><message></message><components></components></yredirects><ydupes><score>100</score><message></message><components></components></ydupes><yetags><score>0</score><message>There are 29 components with misconfigured ETags</message><components><item>http://www.microsoft.com/global/about/en/us/RenderingAssets/default.css</item><item>http://ajax.microsoft.com/ajax/jquery/jquery-1.4.1.min.js</item><item>http://i3.microsoft.com/shared/core/2/swe/3.5.0.0/3.5.30729.1/MicrosoftAjax.js</item><item>http://i3.microsoft.com/global/en/us/renderingassets/webtrends_15_1.js</item><item>http://c.microsoft.com/ms.js</item><item>http://i3.microsoft.com/about/shared/templates/master/AboutLegal/Stage_BG_btm.png</item><item>http://i3.microsoft.com/about/shared/templates/master/AboutLegal/bg.jpg</item><item>http://i3.microsoft.com/about/shared/templates/components/mscomSearch/glass.png</item><item>http://i3.microsoft.com/about/shared/templates/components/mscomSearch/search.gif</item><item>http://www.microsoft.com/global/about/twc/en/us/PublishingImages/ImportedContent/about/legal/en/us/en-US.gif</item><item>http://i3.microsoft.com/about/shared/templates/components/mscomHorizNav/a.png</item><item>http://i2.microsoft.com/about/shared/templates/components/mscomHorizNav/b.png</item><item>http://i3.microsoft.com/about/shared/templates/components/mscomHorizNav/bullet.png</item><item>http://i3.microsoft.com/about/shared/templates/components/mscomHorizNav/b.png</item><item>http://i2.microsoft.com/about/shared/templates/components/mscomHorizNav/a.png</item><item>http://i2.microsoft.com/about/shared/templates/master/AboutLegal/bg.jpg</item><item>http://www.microsoft.com/global/about/twc/en/us/PublishingImages/Ip_Right_Rail.png</item><item>http://i3.microsoft.com/about/shared/templates/master/mscomSuiteMaster/bg.png</item><item>http://www.microsoft.com/global/en/publishingimages/sitebrand/microsoft.gif</item><item>http://i.microsoft.com/global/about/en/us/PublishingImages/gptw.jpg</item><item>http://i.microsoft.com/global/about/en/us/PublishingImages/ImportedContent/about/twc/en/us/About_Home_Hero.jpg</item><item>http://i.microsoft.com/global/about/en/us/PublishingImages/70043_55x55_info.jpg</item><item>http://i.microsoft.com/global/about/en/us/PublishingImages/70043_55x55_corp.jpg</item><item>http://i.microsoft.com/global/about/en/us/PublishingImages/CPE_About_55x55.jpg</item><item>http://i.microsoft.com/global/about/en/us/PublishingImages/70043_55x55_legal.jpg</item><item>http://i.microsoft.com/global/about/en/us/PublishingImages/d_inc_about_hp.png</item><item>http://www.microsoft.com/about/shared/Templates/Components/cueRSSConsumer/synd.gif</item><item>http://i.microsoft.com/about/shared/templates/components/mscomfooter/logo.png</item><item><![CDATA[http://c1.microsoft.com/c.gif?DI=4050&did=1&t=&MUID=3B7B8ECF7E2566272C918D367A256663&cb=1cda9d229093cf0]]></item></components></yetags><yxhr><score>100</score><message></message><components></components></yxhr><yxhrmethod><score>100</score><message></message><components></components></yxhrmethod><ymindom><score>100</score><message></message><components></components></ymindom><yno404><score>100</score><message></message><components></components></yno404><ymincookie><score>100</score><message></message><components></components></ymincookie><ycookiefree><score>95</score><message>There is 1 component that is not cookie-free</message><components><item><![CDATA[http://c1.microsoft.com/c.gif?DI=4050&did=1&t=&MUID=3B7B8ECF7E2566272C918D367A256663&cb=1cda9d229093cf0]]></item></components></ycookiefree><ynofilter><score>100</score><message></message><components></components></ynofilter><yimgnoscale><score>100</score><message></message><components></components></yimgnoscale><_3po_asyncjs><score>100</score><message></message><components></components></_3po_asyncjs><_3po_jsonce><score>100</score><message></message><components></components></_3po_jsonce><cssprint><score>100</score><message></message><components></components></cssprint><cssinheaddomain><score>100</score><message></message><components></components></cssinheaddomain><syncjsinhead><score>40</score><message>There are 6 scripts that are not loaded asynchronously in head, that will block the rendering.</message><components><item>http://www.microsoft.com/about/shared/core/2/js/js.ashx?s=Csp;shared</item><item>http://www.microsoft.com/about/shared/core/2/js/js.ashx?c=mscomSearch</item><item>http://www.microsoft.com/about/shared/core/2/js/js.ashx?c=mscomHorizNav</item><item><![CDATA[http://www.microsoft.com/about/shared/core/2/js/js.ashx?&]]></item><item>http://ajax.microsoft.com/ajax/jquery/jquery-1.4.1.min.js</item><item>http://www.microsoft.com/about/shared/core/2/js/js.ashx?c=alVertNav</item></components></syncjsinhead><avoidfont><score>100</score><message></message><components></components></avoidfont><totalrequests><score>81</score><message>The page uses 45 requests, that is too many to make the page load fast.</message><components><item>http://www.microsoft.com/about/en/us/default.aspx</item><item><![CDATA[http://www.microsoft.com/about/shared/core/2/css/css.ashx?sc=/about/en/us/site.config&pc=/about/en/us/PageConfig/default.xml&m=AboutLegal]]></item><item><![CDATA[http://www.microsoft.com/about/shared/core/2/css/css.ashx?sc=/about/en/us/site.config&pc=/about/en/us/PageConfig/default.xml&c=mscomHeader]]></item><item><![CDATA[http://www.microsoft.com/about/shared/core/2/css/css.ashx?sc=/about/en/us/site.config&pc=/about/en/us/PageConfig/default.xml&c=mscomSearch]]></item><item><![CDATA[http://www.microsoft.com/about/shared/core/2/css/css.ashx?sc=/about/en/us/site.config&pc=/about/en/us/PageConfig/default.xml&c=mscomHorizNav]]></item><item><![CDATA[http://www.microsoft.com/about/shared/core/2/css/css.ashx?sc=/about/en/us/site.config&pc=/about/en/us/PageConfig/default.xml&pt=alHome&c=cspAdControl;alGenericComplexContent;alTable]]></item><item>http://www.microsoft.com/global/about/en/us/RenderingAssets/default.css</item><item><![CDATA[http://www.microsoft.com/about/shared/core/2/css/css.ashx?sc=/about/en/us/site.config&pc=/about/en/us/PageConfig/default.xml&c=alVertNav;cspAdControl]]></item><item><![CDATA[http://www.microsoft.com/about/shared/core/2/css/css.ashx?sc=/about/en/us/site.config&pc=/about/en/us/PageConfig/default.xml&c=mscomFooter]]></item><item>http://www.microsoft.com/about/shared/core/2/js/js.ashx?s=Csp;shared</item><item>http://www.microsoft.com/about/shared/core/2/js/js.ashx?c=mscomSearch</item><item>http://www.microsoft.com/about/shared/core/2/js/js.ashx?c=mscomHorizNav</item><item><![CDATA[http://www.microsoft.com/about/shared/core/2/js/js.ashx?&]]></item><item>http://ajax.microsoft.com/ajax/jquery/jquery-1.4.1.min.js</item><item>http://www.microsoft.com/about/shared/core/2/js/js.ashx?c=alVertNav</item><item>http://i3.microsoft.com/shared/core/2/swe/3.5.0.0/3.5.30729.1/MicrosoftAjax.js</item><item>http://m.webtrends.com/dcsjwb9vb00000c932fd0rjc7_5p3t/wtid.js</item><item>http://i3.microsoft.com/global/en/us/renderingassets/webtrends_15_1.js</item><item>http://c.microsoft.com/ms.js</item><item>http://i3.microsoft.com/about/shared/templates/master/AboutLegal/Stage_BG_btm.png</item><item>http://i3.microsoft.com/about/shared/templates/master/AboutLegal/bg.jpg</item><item>http://i3.microsoft.com/about/shared/templates/components/mscomSearch/glass.png</item><item>http://i3.microsoft.com/about/shared/templates/components/mscomSearch/search.gif</item><item>http://www.microsoft.com/global/about/twc/en/us/PublishingImages/ImportedContent/about/legal/en/us/en-US.gif</item><item>http://i3.microsoft.com/about/shared/templates/components/mscomHorizNav/a.png</item><item>http://i2.microsoft.com/about/shared/templates/components/mscomHorizNav/b.png</item><item>http://i3.microsoft.com/about/shared/templates/components/mscomHorizNav/bullet.png</item><item>http://i3.microsoft.com/about/shared/templates/components/mscomHorizNav/b.png</item><item>http://i2.microsoft.com/about/shared/templates/components/mscomHorizNav/a.png</item><item>http://i2.microsoft.com/about/shared/templates/master/AboutLegal/bg.jpg</item><item>http://www.microsoft.com/global/about/twc/en/us/PublishingImages/Ip_Right_Rail.png</item><item>http://i3.microsoft.com/about/shared/templates/master/mscomSuiteMaster/bg.png</item><item>http://www.microsoft.com/global/en/publishingimages/sitebrand/microsoft.gif</item><item>http://i.microsoft.com/global/about/en/us/PublishingImages/gptw.jpg</item><item>http://i.microsoft.com/global/about/en/us/PublishingImages/ImportedContent/about/twc/en/us/About_Home_Hero.jpg</item><item>http://i.microsoft.com/global/about/en/us/PublishingImages/70043_55x55_info.jpg</item><item>http://i.microsoft.com/global/about/en/us/PublishingImages/70043_55x55_corp.jpg</item><item>http://i.microsoft.com/global/about/en/us/PublishingImages/CPE_About_55x55.jpg</item><item>http://i.microsoft.com/global/about/en/us/PublishingImages/70043_55x55_legal.jpg</item><item>http://i.microsoft.com/global/about/en/us/PublishingImages/d_inc_about_hp.png</item><item>http://www.microsoft.com/about/shared/Templates/Components/cueRSSConsumer/synd.gif</item><item>http://i.microsoft.com/about/shared/templates/components/mscomfooter/logo.png</item><item>http://www.microsoft.com/favicon.ico</item><item><![CDATA[http://c1.microsoft.com/c.gif?DI=4050&did=1&t=]]></item><item><![CDATA[http://c1.microsoft.com/c.gif?DI=4050&did=1&t=&MUID=3B7B8ECF7E2566272C918D367A256663&cb=1cda9d229093cf0]]></item></components></totalrequests><expiresmod><score>0</score><message>There are 28 static components without a far-future expiration date.</message><components><item><![CDATA[http://www.microsoft.com/about/shared/core/2/css/css.ashx?sc=/about/en/us/site.config&pc=/about/en/us/PageConfig/default.xml&m=AboutLegal]]></item><item><![CDATA[http://www.microsoft.com/about/shared/core/2/css/css.ashx?sc=/about/en/us/site.config&pc=/about/en/us/PageConfig/default.xml&c=mscomHeader]]></item><item><![CDATA[http://www.microsoft.com/about/shared/core/2/css/css.ashx?sc=/about/en/us/site.config&pc=/about/en/us/PageConfig/default.xml&c=mscomSearch]]></item><item><![CDATA[http://www.microsoft.com/about/shared/core/2/css/css.ashx?sc=/about/en/us/site.config&pc=/about/en/us/PageConfig/default.xml&c=mscomHorizNav]]></item><item><![CDATA[http://www.microsoft.com/about/shared/core/2/css/css.ashx?sc=/about/en/us/site.config&pc=/about/en/us/PageConfig/default.xml&pt=alHome&c=cspAdControl;alGenericComplexContent;alTable]]></item><item>http://www.microsoft.com/global/about/en/us/RenderingAssets/default.css</item><item><![CDATA[http://www.microsoft.com/about/shared/core/2/css/css.ashx?sc=/about/en/us/site.config&pc=/about/en/us/PageConfig/default.xml&c=alVertNav;cspAdControl]]></item><item><![CDATA[http://www.microsoft.com/about/shared/core/2/css/css.ashx?sc=/about/en/us/site.config&pc=/about/en/us/PageConfig/default.xml&c=mscomFooter]]></item><item>http://www.microsoft.com/about/shared/core/2/js/js.ashx?s=Csp;shared</item><item>http://www.microsoft.com/about/shared/core/2/js/js.ashx?c=mscomSearch</item><item>http://www.microsoft.com/about/shared/core/2/js/js.ashx?c=mscomHorizNav</item><item><![CDATA[http://www.microsoft.com/about/shared/core/2/js/js.ashx?&]]></item><item>http://www.microsoft.com/about/shared/core/2/js/js.ashx?c=alVertNav</item><item>http://i3.microsoft.com/shared/core/2/swe/3.5.0.0/3.5.30729.1/MicrosoftAjax.js</item><item>http://m.webtrends.com/dcsjwb9vb00000c932fd0rjc7_5p3t/wtid.js</item><item>http://i3.microsoft.com/global/en/us/renderingassets/webtrends_15_1.js</item><item>http://c.microsoft.com/ms.js</item><item>http://www.microsoft.com/global/about/twc/en/us/PublishingImages/ImportedContent/about/legal/en/us/en-US.gif</item><item>http://www.microsoft.com/global/about/twc/en/us/PublishingImages/Ip_Right_Rail.png</item><item>http://www.microsoft.com/global/en/publishingimages/sitebrand/microsoft.gif</item><item>http://i.microsoft.com/global/about/en/us/PublishingImages/gptw.jpg</item><item>http://i.microsoft.com/global/about/en/us/PublishingImages/ImportedContent/about/twc/en/us/About_Home_Hero.jpg</item><item>http://i.microsoft.com/global/about/en/us/PublishingImages/70043_55x55_info.jpg</item><item>http://i.microsoft.com/global/about/en/us/PublishingImages/70043_55x55_corp.jpg</item><item>http://i.microsoft.com/global/about/en/us/PublishingImages/CPE_About_55x55.jpg</item><item>http://i.microsoft.com/global/about/en/us/PublishingImages/70043_55x55_legal.jpg</item><item>http://i.microsoft.com/global/about/en/us/PublishingImages/d_inc_about_hp.png</item><item><![CDATA[http://c1.microsoft.com/c.gif?DI=4050&did=1&t=&MUID=3B7B8ECF7E2566272C918D367A256663&cb=1cda9d229093cf0]]></item></components></expiresmod><spof><score>100</score><message></message><components></components></spof></g><w_c>110</w_c><r_c>31</r_c><stats><doc><r>1</r><w>49865</w></doc><css><r>8</r><w>16367</w></css><js><r>10</r><w>138614</w></js><cssimage><r>13</r><w>57155</w></cssimage><image><r>11</r><w>57954</w></image><favicon><r>1</r><w>0</w></favicon><iframe><r>1</r><w>42</w></iframe></stats><stats_c><doc><r>1</r><w>0</w></doc><css><r>8</r><w>0</w></css><js><r>9</r><w>68</w></js><cssimage><r>2</r><w>0</w></cssimage><image><r>9</r><w>0</w></image><favicon><r>1</r><w>0</w></favicon><iframe><r>1</r><w>42</w></iframe></stats_c><comps><item><type>doc</type><url>http://www.microsoft.com/about/en/us/default.aspx</url><size>49850</size><resp>843</resp><gzip>49865</gzip><expires>2012/10/14</expires><etag>634843561230000000</etag><headers><request><User-Agent>Mozilla/5.0 (Macintosh; Intel Mac OS X) AppleWebKit/534.34 (KHTML, like Gecko) PhantomJS/1.7.0 Safari/534.34</User-Agent><Accept>text/html,application/xhtml+xml,application/xml;q=0.9,*/*;q=0.8</Accept></request><response><Cache-Control>public</Cache-Control><Content-Type>text/html; charset=utf-8</Content-Type><Content-Encoding>gzip</Content-Encoding><Expires>Sun, 14 Oct 2012 06:17:13 GMT</Expires><Last-Modified>Thu, 27 Sep 2012 22:22:03 GMT</Last-Modified><ETag>634843561230000000</ETag><Vary>Accept-Encoding</Vary><Server>Microsoft-IIS/8.0</Server><P3P>CP="ALL IND DSP COR ADM CONo CUR CUSo IVAo IVDo PSA PSD TAI TELo OUR SAMo CNT COM INT NAV ONL PHY PRE PUR UNI"</P3P><X-Aspnet-Version>2.0.50727</X-Aspnet-Version><Vtag>438936931900000000</Vtag><X-Powered-By>ASP.NET, ARR/2.5, ASP.NET</X-Powered-By><Date>Sun, 14 Oct 2012 06:07:13 GMT</Date></response></headers></item><item><type>css</type><url><![CDATA[http://www.microsoft.com/about/shared/core/2/css/css.ashx?sc=/about/en/us/site.config&pc=/about/en/us/PageConfig/default.xml&m=AboutLegal]]></url><size>2631</size><resp>1215</resp><gzip>2634</gzip><expires>2012/10/14</expires><etag>634121599210000000</etag><headers><request><User-Agent>Mozilla/5.0 (Macintosh; Intel Mac OS X) AppleWebKit/534.34 (KHTML, like Gecko) PhantomJS/1.7.0 Safari/534.34</User-Agent><Accept>text/css,*/*;q=0.1</Accept><Referer>http://www.microsoft.com/about/en/us/default.aspx</Referer></request><response><Cache-Control>public</Cache-Control><Content-Type>text/css; charset=utf-8</Content-Type><Content-Encoding>gzip</Content-Encoding><Expires>Sun, 14 Oct 2012 06:17:14 GMT</Expires><Last-Modified>Tue, 15 Jun 2010 07:52:01 GMT</Last-Modified><ETag>634121599210000000</ETag><Vary>Accept-Encoding</Vary><Server>Microsoft-IIS/8.0</Server><P3P>CP="ALL IND DSP COR ADM CONo CUR CUSo IVAo IVDo PSA PSD TAI TELo OUR SAMo CNT COM INT NAV ONL PHY PRE PUR UNI"</P3P><X-Aspnet-Version>2.0.50727</X-Aspnet-Version><Vtag>279190431200000000</Vtag><X-Powered-By>ASP.NET, ARR/2.5, ASP.NET</X-Powered-By><Date>Sun, 14 Oct 2012 06:07:13 GMT</Date></response></headers></item><item><type>css</type><url><![CDATA[http://www.microsoft.com/about/shared/core/2/css/css.ashx?sc=/about/en/us/site.config&pc=/about/en/us/PageConfig/default.xml&c=mscomHeader]]></url><size>447</size><resp>1214</resp><gzip>450</gzip><expires>2012/10/14</expires><etag>634121599210000000</etag><headers><request><User-Agent>Mozilla/5.0 (Macintosh; Intel Mac OS X) AppleWebKit/534.34 (KHTML, like Gecko) PhantomJS/1.7.0 Safari/534.34</User-Agent><Accept>text/css,*/*;q=0.1</Accept><Referer>http://www.microsoft.com/about/en/us/default.aspx</Referer></request><response><Cache-Control>public</Cache-Control><Content-Type>text/css; charset=utf-8</Content-Type><Content-Encoding>gzip</Content-Encoding><Expires>Sun, 14 Oct 2012 06:17:14 GMT</Expires><Last-Modified>Tue, 15 Jun 2010 07:52:01 GMT</Last-Modified><ETag>634121599210000000</ETag><Vary>Accept-Encoding</Vary><Server>Microsoft-IIS/7.5</Server><P3P>CP="ALL IND DSP COR ADM CONo CUR CUSo IVAo IVDo PSA PSD TAI TELo OUR SAMo CNT COM INT NAV ONL PHY PRE PUR UNI"</P3P><X-Aspnet-Version>2.0.50727</X-Aspnet-Version><Vtag>43882931700000000</Vtag><X-Powered-By>ASP.NET, ARR/2.5, ASP.NET</X-Powered-By><Date>Sun, 14 Oct 2012 06:07:14 GMT</Date></response></headers></item><item><type>css</type><url><![CDATA[http://www.microsoft.com/about/shared/core/2/css/css.ashx?sc=/about/en/us/site.config&pc=/about/en/us/PageConfig/default.xml&c=mscomSearch]]></url><size>3076</size><resp>1271</resp><gzip>3079</gzip><expires>2012/10/14</expires><etag>634121599210000000</etag><headers><request><User-Agent>Mozilla/5.0 (Macintosh; Intel Mac OS X) AppleWebKit/534.34 (KHTML, like Gecko) PhantomJS/1.7.0 Safari/534.34</User-Agent><Accept>text/css,*/*;q=0.1</Accept><Referer>http://www.microsoft.com/about/en/us/default.aspx</Referer></request><response><Cache-Control>public</Cache-Control><Content-Type>text/css; charset=utf-8</Content-Type><Content-Encoding>gzip</Content-Encoding><Expires>Sun, 14 Oct 2012 06:17:14 GMT</Expires><Last-Modified>Tue, 15 Jun 2010 07:52:01 GMT</Last-Modified><ETag>634121599210000000</ETag><Vary>Accept-Encoding</Vary><Server>Microsoft-IIS/8.0</Server><P3P>CP="ALL IND DSP COR ADM CONo CUR CUSo IVAo IVDo PSA PSD TAI TELo OUR SAMo CNT COM INT NAV ONL PHY PRE PUR UNI"</P3P><X-Aspnet-Version>2.0.50727</X-Aspnet-Version><X-Powered-By>ASP.NET, ARR/2.5, ASP.NET</X-Powered-By><Date>Sun, 14 Oct 2012 06:07:13 GMT</Date></response></headers></item><item><type>css</type><url><![CDATA[http://www.microsoft.com/about/shared/core/2/css/css.ashx?sc=/about/en/us/site.config&pc=/about/en/us/PageConfig/default.xml&c=mscomHorizNav]]></url><size>4003</size><resp>1216</resp><gzip>4006</gzip><expires>2012/10/14</expires><etag>634121599210000000</etag><headers><request><User-Agent>Mozilla/5.0 (Macintosh; Intel Mac OS X) AppleWebKit/534.34 (KHTML, like Gecko) PhantomJS/1.7.0 Safari/534.34</User-Agent><Accept>text/css,*/*;q=0.1</Accept><Referer>http://www.microsoft.com/about/en/us/default.aspx</Referer></request><response><Cache-Control>public</Cache-Control><Content-Type>text/css; charset=utf-8</Content-Type><Content-Encoding>gzip</Content-Encoding><Expires>Sun, 14 Oct 2012 06:17:14 GMT</Expires><Last-Modified>Tue, 15 Jun 2010 07:52:01 GMT</Last-Modified><ETag>634121599210000000</ETag><Vary>Accept-Encoding</Vary><Server>Microsoft-IIS/8.0</Server><P3P>CP="ALL IND DSP COR ADM CONo CUR CUSo IVAo IVDo PSA PSD TAI TELo OUR SAMo CNT COM INT NAV ONL PHY PRE PUR UNI"</P3P><X-Aspnet-Version>2.0.50727</X-Aspnet-Version><Vtag>438306633100000000</Vtag><X-Powered-By>ASP.NET, ARR/2.5, ASP.NET</X-Powered-By><Date>Sun, 14 Oct 2012 06:07:13 GMT</Date></response></headers></item><item><type>css</type><url><![CDATA[http://www.microsoft.com/about/shared/core/2/css/css.ashx?sc=/about/en/us/site.config&pc=/about/en/us/PageConfig/default.xml&pt=alHome&c=cspAdControl;alGenericComplexContent;alTable]]></url><size>1895</size><resp>1440</resp><gzip>1898</gzip><expires>2012/10/14</expires><etag>634121599210000000</etag><headers><request><User-Agent>Mozilla/5.0 (Macintosh; Intel Mac OS X) AppleWebKit/534.34 (KHTML, like Gecko) PhantomJS/1.7.0 Safari/534.34</User-Agent><Accept>text/css,*/*;q=0.1</Accept><Referer>http://www.microsoft.com/about/en/us/default.aspx</Referer></request><response><Cache-Control>public</Cache-Control><Content-Type>text/css; charset=utf-8</Content-Type><Content-Encoding>gzip</Content-Encoding><Expires>Sun, 14 Oct 2012 06:17:14 GMT</Expires><Last-Modified>Tue, 15 Jun 2010 07:52:01 GMT</Last-Modified><ETag>634121599210000000</ETag><Vary>Accept-Encoding</Vary><Server>Microsoft-IIS/8.0</Server><P3P>CP="ALL IND DSP COR ADM CONo CUR CUSo IVAo IVDo PSA PSD TAI TELo OUR SAMo CNT COM INT NAV ONL PHY PRE PUR UNI"</P3P><X-Aspnet-Version>2.0.50727</X-Aspnet-Version><X-Powered-By>ASP.NET, ARR/2.5, ASP.NET</X-Powered-By><Date>Sun, 14 Oct 2012 06:07:13 GMT</Date></response></headers></item><item><type>css</type><url>http://www.microsoft.com/global/about/en/us/RenderingAssets/default.css</url><size>1731</size><resp>1408</resp><gzip>1731</gzip><expires>2012/10/14</expires><etag>"abdc60ea74e0ca1:0"</etag><headers><request><User-Agent>Mozilla/5.0 (Macintosh; Intel Mac OS X) AppleWebKit/534.34 (KHTML, like Gecko) PhantomJS/1.7.0 Safari/534.34</User-Agent><Accept>text/css,*/*;q=0.1</Accept><Referer>http://www.microsoft.com/about/en/us/default.aspx</Referer></request><response><Cache-Control>max-age=900</Cache-Control><Content-Type>text/css</Content-Type><Content-Encoding>gzip</Content-Encoding><Last-Modified>Tue, 20 Apr 2010 10:33:28 GMT</Last-Modified><Accept-Ranges>bytes</Accept-Ranges><ETag>"abdc60ea74e0ca1:0"</ETag><Vary>Accept-Encoding</Vary><Server>Microsoft-IIS/7.5</Server><P3P>CP="ALL IND DSP COR ADM CONo CUR CUSo IVAo IVDo PSA PSD TAI TELo OUR SAMo CNT COM INT NAV ONL PHY PRE PUR UNI"</P3P><Vtag>791457231700000000</Vtag><X-Powered-By>ASP.NET, ARR/2.5, ASP.NET</X-Powered-By><Date>Sun, 14 Oct 2012 06:07:14 GMT</Date></response></headers></item><item><type>css</type><url><![CDATA[http://www.microsoft.com/about/shared/core/2/css/css.ashx?sc=/about/en/us/site.config&pc=/about/en/us/PageConfig/default.xml&c=alVertNav;cspAdControl]]></url><size>1924</size><resp>1456</resp><gzip>1927</gzip><expires>2012/10/14</expires><etag>634121599210000000</etag><headers><request><User-Agent>Mozilla/5.0 (Macintosh; Intel Mac OS X) AppleWebKit/534.34 (KHTML, like Gecko) PhantomJS/1.7.0 Safari/534.34</User-Agent><Accept>text/css,*/*;q=0.1</Accept><Referer>http://www.microsoft.com/about/en/us/default.aspx</Referer></request><response><Cache-Control>public</Cache-Control><Content-Type>text/css; charset=utf-8</Content-Type><Content-Encoding>gzip</Content-Encoding><Expires>Sun, 14 Oct 2012 06:17:14 GMT</Expires><Last-Modified>Tue, 15 Jun 2010 07:52:01 GMT</Last-Modified><ETag>634121599210000000</ETag><Vary>Accept-Encoding</Vary><Server>Microsoft-IIS/8.0</Server><P3P>CP="ALL IND DSP COR ADM CONo CUR CUSo IVAo IVDo PSA PSD TAI TELo OUR SAMo CNT COM INT NAV ONL PHY PRE PUR UNI"</P3P><X-Aspnet-Version>2.0.50727</X-Aspnet-Version><Vtag>279846832700000000</Vtag><X-Powered-By>ASP.NET, ARR/2.5, ASP.NET</X-Powered-By><Date>Sun, 14 Oct 2012 06:07:13 GMT</Date></response></headers></item><item><type>css</type><url><![CDATA[http://www.microsoft.com/about/shared/core/2/css/css.ashx?sc=/about/en/us/site.config&pc=/about/en/us/PageConfig/default.xml&c=mscomFooter]]></url><size>639</size><resp>1527</resp><gzip>642</gzip><expires>2012/10/14</expires><etag>634121599210000000</etag><headers><request><User-Agent>Mozilla/5.0 (Macintosh; Intel Mac OS X) AppleWebKit/534.34 (KHTML, like Gecko) PhantomJS/1.7.0 Safari/534.34</User-Agent><Accept>text/css,*/*;q=0.1</Accept><Referer>http://www.microsoft.com/about/en/us/default.aspx</Referer></request><response><Cache-Control>public</Cache-Control><Content-Type>text/css; charset=utf-8</Content-Type><Content-Encoding>gzip</Content-Encoding><Expires>Sun, 14 Oct 2012 06:17:14 GMT</Expires><Last-Modified>Tue, 15 Jun 2010 07:52:01 GMT</Last-Modified><ETag>634121599210000000</ETag><Vary>Accept-Encoding</Vary><Server>Microsoft-IIS/8.0</Server><P3P>CP="ALL IND DSP COR ADM CONo CUR CUSo IVAo IVDo PSA PSD TAI TELo OUR SAMo CNT COM INT NAV ONL PHY PRE PUR UNI"</P3P><X-Aspnet-Version>2.0.50727</X-Aspnet-Version><X-Powered-By>ASP.NET, ARR/2.5, ASP.NET</X-Powered-By><Date>Sun, 14 Oct 2012 06:07:14 GMT</Date></response></headers></item><item><type>js</type><url>http://www.microsoft.com/about/shared/core/2/js/js.ashx?s=Csp;shared</url><size>7749</size><resp>1025</resp><gzip>7752</gzip><expires>2012/10/14</expires><etag>634745848680000000</etag><headers><request><User-Agent>Mozilla/5.0 (Macintosh; Intel Mac OS X) AppleWebKit/534.34 (KHTML, like Gecko) PhantomJS/1.7.0 Safari/534.34</User-Agent><Accept>*/*</Accept><Referer>http://www.microsoft.com/about/en/us/default.aspx</Referer></request><response><Cache-Control>public</Cache-Control><Content-Type>text/javascript; charset=utf-8</Content-Type><Content-Encoding>gzip</Content-Encoding><Expires>Sun, 14 Oct 2012 06:17:13 GMT</Expires><Last-Modified>Wed, 06 Jun 2012 20:07:48 GMT</Last-Modified><ETag>634745848680000000</ETag><Vary>Accept-Encoding</Vary><Server>Microsoft-IIS/8.0</Server><P3P>CP="ALL IND DSP COR ADM CONo CUR CUSo IVAo IVDo PSA PSD TAI TELo OUR SAMo CNT COM INT NAV ONL PHY PRE PUR UNI"</P3P><X-Aspnet-Version>2.0.50727</X-Aspnet-Version><Vtag>791565733000000000</Vtag><X-Powered-By>ASP.NET, ARR/2.5, ASP.NET</X-Powered-By><Date>Sun, 14 Oct 2012 06:07:13 GMT</Date></response></headers></item><item><type>js</type><url>http://www.microsoft.com/about/shared/core/2/js/js.ashx?c=mscomSearch</url><size>2460</size><resp>1213</resp><gzip>2463</gzip><expires>2012/10/14</expires><etag>634020164870000000</etag><headers><request><User-Agent>Mozilla/5.0 (Macintosh; Intel Mac OS X) AppleWebKit/534.34 (KHTML, like Gecko) PhantomJS/1.7.0 Safari/534.34</User-Agent><Accept>*/*</Accept><Referer>http://www.microsoft.com/about/en/us/default.aspx</Referer></request><response><Cache-Control>public</Cache-Control><Content-Type>text/javascript; charset=utf-8</Content-Type><Content-Encoding>gzip</Content-Encoding><Expires>Sun, 14 Oct 2012 06:17:13 GMT</Expires><Last-Modified>Wed, 17 Feb 2010 23:14:47 GMT</Last-Modified><ETag>634020164870000000</ETag><Vary>Accept-Encoding</Vary><Server>Microsoft-IIS/7.5</Server><P3P>CP="ALL IND DSP COR ADM CONo CUR CUSo IVAo IVDo PSA PSD TAI TELo OUR SAMo CNT COM INT NAV ONL PHY PRE PUR UNI"</P3P><X-Aspnet-Version>2.0.50727</X-Aspnet-Version><Vtag>279444532000000000</Vtag><X-Powered-By>ASP.NET, ARR/2.5, ASP.NET</X-Powered-By><Date>Sun, 14 Oct 2012 06:07:14 GMT</Date></response></headers></item><item><type>js</type><url>http://www.microsoft.com/about/shared/core/2/js/js.ashx?c=mscomHorizNav</url><size>4721</size><resp>1217</resp><gzip>4724</gzip><expires>2012/10/14</expires><etag>634003968920000000</etag><headers><request><User-Agent>Mozilla/5.0 (Macintosh; Intel Mac OS X) AppleWebKit/534.34 (KHTML, like Gecko) PhantomJS/1.7.0 Safari/534.34</User-Agent><Accept>*/*</Accept><Referer>http://www.microsoft.com/about/en/us/default.aspx</Referer></request><response><Cache-Control>public</Cache-Control><Content-Type>text/javascript; charset=utf-8</Content-Type><Content-Encoding>gzip</Content-Encoding><Expires>Sun, 14 Oct 2012 06:17:14 GMT</Expires><Last-Modified>Sat, 30 Jan 2010 05:21:32 GMT</Last-Modified><ETag>634003968920000000</ETag><Vary>Accept-Encoding</Vary><Server>Microsoft-IIS/8.0</Server><P3P>CP="ALL IND DSP COR ADM CONo CUR CUSo IVAo IVDo PSA PSD TAI TELo OUR SAMo CNT COM INT NAV ONL PHY PRE PUR UNI"</P3P><X-Aspnet-Version>2.0.50727</X-Aspnet-Version><Vtag>791720331900000000</Vtag><X-Powered-By>ASP.NET, ARR/2.5, ASP.NET</X-Powered-By><Date>Sun, 14 Oct 2012 06:07:14 GMT</Date></response></headers></item><item><type>js</type><url><![CDATA[http://www.microsoft.com/about/shared/core/2/js/js.ashx?&]]></url><size>3</size><resp>1401</resp><gzip>3</gzip><headers><request><User-Agent>Mozilla/5.0 (Macintosh; Intel Mac OS X) AppleWebKit/534.34 (KHTML, like Gecko) PhantomJS/1.7.0 Safari/534.34</User-Agent><Accept>*/*</Accept><Referer>http://www.microsoft.com/about/en/us/default.aspx</Referer></request><response><Cache-Control>private</Cache-Control><Content-Type>text/javascript; charset=utf-8</Content-Type><Content-Encoding>gzip</Content-Encoding><Vary>Accept-Encoding</Vary><Server>Microsoft-IIS/7.5</Server><P3P>CP="ALL IND DSP COR ADM CONo CUR CUSo IVAo IVDo PSA PSD TAI TELo OUR SAMo CNT COM INT NAV ONL PHY PRE PUR UNI"</P3P><X-Aspnet-Version>2.0.50727</X-Aspnet-Version><Vtag>438134832200000000</Vtag><X-Powered-By>ASP.NET, ARR/2.5, ASP.NET</X-Powered-By><Date>Sun, 14 Oct 2012 06:07:14 GMT</Date></response></headers></item><item><type>js</type><url>http://ajax.microsoft.com/ajax/jquery/jquery-1.4.1.min.js</url><size>70822</size><resp>867</resp><gzip>38227</gzip><expires>2013/6/7</expires><etag>"7460b43d23b4ca1:0"</etag><headers><request><User-Agent>Mozilla/5.0 (Macintosh; Intel Mac OS X) AppleWebKit/534.34 (KHTML, like Gecko) PhantomJS/1.7.0 Safari/534.34</User-Agent><Accept>*/*</Accept><Referer>http://www.microsoft.com/about/en/us/default.aspx</Referer></request><response><Cache-Control>public,max-age=31536000</Cache-Control><Content-Type>application/x-javascript</Content-Type><Content-Encoding>gzip</Content-Encoding><Accept-Ranges>bytes</Accept-Ranges><ETag>"7460b43d23b4ca1:0"</ETag><Vary>Accept-Encoding</Vary><Server>Microsoft-IIS/8.0</Server><P3P>CP="ALL IND DSP COR ADM CONo CUR CUSo IVAo IVDo PSA PSD TAI TELo OUR SAMo CNT COM INT NAV ONL PHY PRE PUR UNI"</P3P><X-Powered-By>ASP.NET</X-Powered-By><Age>11131908</Age><Date>Sun, 14 Oct 2012 06:07:13 GMT</Date><Last-Modified>Tue, 23 Feb 2010 00:57:58 GMT</Last-Modified><Expires>Fri, 07 Jun 2013 09:55:25 GMT</Expires><Connection>keep-alive</Connection></response></headers></item><item><type>js</type><url>http://www.microsoft.com/about/shared/core/2/js/js.ashx?c=alVertNav</url><size>3839</size><resp>1406</resp><gzip>3842</gzip><expires>2012/10/14</expires><etag>634030331100000000</etag><headers><request><User-Agent>Mozilla/5.0 (Macintosh; Intel Mac OS X) AppleWebKit/534.34 (KHTML, like Gecko) PhantomJS/1.7.0 Safari/534.34</User-Agent><Accept>*/*</Accept><Referer>http://www.microsoft.com/about/en/us/default.aspx</Referer></request><response><Cache-Control>public</Cache-Control><Content-Type>text/javascript; charset=utf-8</Content-Type><Content-Encoding>gzip</Content-Encoding><Expires>Sun, 14 Oct 2012 06:17:14 GMT</Expires><Last-Modified>Mon, 01 Mar 2010 17:38:30 GMT</Last-Modified><ETag>634030331100000000</ETag><Vary>Accept-Encoding</Vary><Server>Microsoft-IIS/8.0</Server><P3P>CP="ALL IND DSP COR ADM CONo CUR CUSo IVAo IVDo PSA PSD TAI TELo OUR SAMo CNT COM INT NAV ONL PHY PRE PUR UNI"</P3P><X-Aspnet-Version>2.0.50727</X-Aspnet-Version><Vtag>438566132900000000</Vtag><X-Powered-By>ASP.NET, ARR/2.5, ASP.NET</X-Powered-By><Date>Sun, 14 Oct 2012 06:07:14 GMT</Date></response></headers></item><item><type>js</type><url>http://i3.microsoft.com/shared/core/2/swe/3.5.0.0/3.5.30729.1/MicrosoftAjax.js</url><size>99355</size><resp>860</resp><gzip>49829</gzip><expires>2012/10/14</expires><etag>"08221b2044cd1:0"</etag><headers><request><User-Agent>Mozilla/5.0 (Macintosh; Intel Mac OS X) AppleWebKit/534.34 (KHTML, like Gecko) PhantomJS/1.7.0 Safari/534.34</User-Agent><Accept>*/*</Accept><Referer>http://www.microsoft.com/about/en/us/default.aspx</Referer></request><response><Content-Type>application/x-javascript</Content-Type><Content-Encoding>gzip</Content-Encoding><Last-Modified>Wed, 06 Jun 2012 20:07:48 GMT</Last-Modified><Accept-Ranges>bytes</Accept-Ranges><ETag>"08221b2044cd1:0"</ETag><Vary>Accept-Encoding</Vary><Server>Microsoft-IIS/7.5</Server><Vtag>791515132600000000</Vtag><P3P>CP="ALL IND DSP COR ADM CONo CUR CUSo IVAo IVDo PSA PSD TAI TELo OUR SAMo CNT COM INT NAV ONL PHY PRE PUR UNI"</P3P><X-Powered-By>ASP.NET</X-Powered-By><Cache-Control>max-age=832</Cache-Control><Date>Sun, 14 Oct 2012 06:07:13 GMT</Date><Connection>keep-alive</Connection></response></headers></item><item><type>js</type><url>http://m.webtrends.com/dcsjwb9vb00000c932fd0rjc7_5p3t/wtid.js</url><size>65</size><resp>1883</resp><headers><request><User-Agent>Mozilla/5.0 (Macintosh; Intel Mac OS X) AppleWebKit/534.34 (KHTML, like Gecko) PhantomJS/1.7.0 Safari/534.34</User-Agent><Accept>*/*</Accept><Referer>http://www.microsoft.com/about/en/us/default.aspx</Referer></request><response><Connection>close</Connection><Date>Sun, 14 Oct 2012 06:07:14 GMT</Date><Server>Microsoft-IIS/6.0</Server><X-Powered-By>ASP.NET</X-Powered-By><Content-Type>application/x-javascript</Content-Type><Content-Length>65</Content-Length><Pragma>no-cache</Pragma><Expires>-1</Expires><Cache-Control>no-cache</Cache-Control></response></headers></item><item><type>js</type><url>http://i3.microsoft.com/global/en/us/renderingassets/webtrends_15_1.js</url><size>18278</size><resp>852</resp><gzip>18281</gzip><expires>2012/10/14</expires><etag>"2514409f9311cb1:0"</etag><headers><request><User-Agent>Mozilla/5.0 (Macintosh; Intel Mac OS X) AppleWebKit/534.34 (KHTML, like Gecko) PhantomJS/1.7.0 Safari/534.34</User-Agent><Accept>*/*</Accept><Referer>http://www.microsoft.com/about/en/us/default.aspx</Referer></request><response><Content-Type>application/x-javascript</Content-Type><Content-Encoding>gzip</Content-Encoding><Last-Modified>Mon, 21 Jun 2010 22:46:43 GMT</Last-Modified><Accept-Ranges>bytes</Accept-Ranges><ETag>"2514409f9311cb1:0"</ETag><Vary>Accept-Encoding</Vary><Server>Microsoft-IIS/7.5</Server><Vtag>791322832200000000</Vtag><P3P>CP="ALL IND DSP COR ADM CONo CUR CUSo IVAo IVDo PSA PSD TAI TELo OUR SAMo CNT COM INT NAV ONL PHY PRE PUR UNI"</P3P><X-Powered-By>ASP.NET</X-Powered-By><Cache-Control>max-age=882</Cache-Control><Date>Sun, 14 Oct 2012 06:07:13 GMT</Date><Connection>keep-alive</Connection></response></headers></item><item><type>js</type><url>http://c.microsoft.com/ms.js</url><size>13428</size><resp>2419</resp><gzip>13428</gzip><etag>"80f3f66b779ccd1:0"</etag><headers><request><User-Agent>Mozilla/5.0 (Macintosh; Intel Mac OS X) AppleWebKit/534.34 (KHTML, like Gecko) PhantomJS/1.7.0 Safari/534.34</User-Agent><Accept>*/*</Accept><Referer>http://www.microsoft.com/about/en/us/default.aspx</Referer></request><response><Content-Type>application/x-javascript</Content-Type><Content-Encoding>gzip</Content-Encoding><Last-Modified>Thu, 27 Sep 2012 06:14:59 GMT</Last-Modified><Accept-Ranges>bytes</Accept-Ranges><ETag>"80f3f66b779ccd1:0"</ETag><Vary>Accept-Encoding</Vary><Server>Microsoft-IIS/7.5</Server><X-Powered-By>ASP.NET</X-Powered-By><P3P>CP="CAO DSP TAIa OUR IND PHY ONL UNI PUR COM NAV INT DEM CNT STA PRE LOC"</P3P><Date>Sun, 14 Oct 2012 06:07:14 GMT</Date></response></headers></item><item><type>cssimage</type><url>http://i3.microsoft.com/about/shared/templates/master/AboutLegal/Stage_BG_btm.png</url><size>489</size><resp>1578</resp><expires>2012/10/17</expires><etag>"69165bd17f9bc91:0"</etag><headers><request><User-Agent>Mozilla/5.0 (Macintosh; Intel Mac OS X) AppleWebKit/534.34 (KHTML, like Gecko) PhantomJS/1.7.0 Safari/534.34</User-Agent><Referer>http://www.microsoft.com/about/en/us/default.aspx</Referer><Accept>*/*</Accept></request><response><Content-Type>image/png</Content-Type><Last-Modified>Mon, 02 Mar 2009 21:42:43 GMT</Last-Modified><Accept-Ranges>bytes</Accept-Ranges><ETag>"69165bd17f9bc91:0"</ETag><Server>Microsoft-IIS/7.5</Server><Vtag>791698331600000000</Vtag><P3P>CP="ALL IND DSP COR ADM CONo CUR CUSo IVAo IVDo PSA PSD TAI TELo OUR SAMo CNT COM INT NAV ONL PHY PRE PUR UNI"</P3P><X-Powered-By>ASP.NET</X-Powered-By><Content-Length>489</Content-Length><Cache-Control>max-age=300928</Cache-Control><Date>Sun, 14 Oct 2012 06:07:14 GMT</Date><Connection>keep-alive</Connection></response></headers></item><item><type>cssimage</type><url>http://i3.microsoft.com/about/shared/templates/master/AboutLegal/bg.jpg</url><size>7363</size><resp>1579</resp><expires>2012/11/5</expires><etag>"105394a45ea1ca1:0"</etag><headers><request><User-Agent>Mozilla/5.0 (Macintosh; Intel Mac OS X) AppleWebKit/534.34 (KHTML, like Gecko) PhantomJS/1.7.0 Safari/534.34</User-Agent><Referer>http://www.microsoft.com/about/en/us/default.aspx</Referer><Accept>*/*</Accept></request><response><Content-Type>image/jpeg</Content-Type><Last-Modified>Sat, 30 Jan 2010 03:45:19 GMT</Last-Modified><Accept-Ranges>bytes</Accept-Ranges><ETag>"105394a45ea1ca1:0"</ETag><Server>Microsoft-IIS/7.5</Server><Vtag>43861731900000000</Vtag><P3P>CP="ALL IND DSP COR ADM CONo CUR CUSo IVAo IVDo PSA PSD TAI TELo OUR SAMo CNT COM INT NAV ONL PHY PRE PUR UNI"</P3P><X-Powered-By>ASP.NET</X-Powered-By><Content-Length>7363</Content-Length><Cache-Control>max-age=1927096</Cache-Control><Date>Sun, 14 Oct 2012 06:07:14 GMT</Date><Connection>keep-alive</Connection></response></headers></item><item><type>cssimage</type><url>http://i3.microsoft.com/about/shared/templates/components/mscomSearch/glass.png</url><size>3295</size><resp>1579</resp><expires>2012/10/17</expires><etag>"74f3aaa99589ca1:0"</etag><headers><request><User-Agent>Mozilla/5.0 (Macintosh; Intel Mac OS X) AppleWebKit/534.34 (KHTML, like Gecko) PhantomJS/1.7.0 Safari/534.34</User-Agent><Referer>http://www.microsoft.com/about/en/us/default.aspx</Referer><Accept>*/*</Accept></request><response><Content-Length>3295</Content-Length><Content-Type>image/png</Content-Type><Last-Modified>Wed, 30 Dec 2009 21:18:42 GMT</Last-Modified><Accept-Ranges>bytes</Accept-Ranges><ETag>"74f3aaa99589ca1:0"</ETag><Server>Microsoft-IIS/8.0</Server><P3P>CP="ALL IND DSP COR ADM CONo CUR CUSo IVAo IVDo PSA PSD TAI TELo OUR SAMo CNT COM INT NAV ONL PHY PRE PUR UNI"</P3P><X-Powered-By>ASP.NET</X-Powered-By><Cache-Control>max-age=300928</Cache-Control><Date>Sun, 14 Oct 2012 06:07:14 GMT</Date><Connection>keep-alive</Connection></response></headers></item><item><type>cssimage</type><url>http://i3.microsoft.com/about/shared/templates/components/mscomSearch/search.gif</url><size>1774</size><resp>1580</resp><expires>2012/10/17</expires><etag>"ab40ff9cee3bca1:0"</etag><headers><request><User-Agent>Mozilla/5.0 (Macintosh; Intel Mac OS X) AppleWebKit/534.34 (KHTML, like Gecko) PhantomJS/1.7.0 Safari/534.34</User-Agent><Referer>http://www.microsoft.com/about/en/us/default.aspx</Referer><Accept>*/*</Accept></request><response><Content-Type>image/gif</Content-Type><Last-Modified>Wed, 23 Sep 2009 01:38:55 GMT</Last-Modified><Accept-Ranges>bytes</Accept-Ranges><ETag>"ab40ff9cee3bca1:0"</ETag><Server>Microsoft-IIS/7.5</Server><Vtag>791229331500000000</Vtag><P3P>CP="ALL IND DSP COR ADM CONo CUR CUSo IVAo IVDo PSA PSD TAI TELo OUR SAMo CNT COM INT NAV ONL PHY PRE PUR UNI"</P3P><X-Powered-By>ASP.NET</X-Powered-By><Content-Length>1774</Content-Length><Cache-Control>max-age=300928</Cache-Control><Date>Sun, 14 Oct 2012 06:07:14 GMT</Date><Connection>keep-alive</Connection></response></headers></item><item><type>cssimage</type><url>http://www.microsoft.com/global/about/twc/en/us/PublishingImages/ImportedContent/about/legal/en/us/en-US.gif</url><size>518</size><resp>1770</resp><expires>2012/10/14</expires><etag>"468bca7bafbfcc1:0"</etag><headers><request><User-Agent>Mozilla/5.0 (Macintosh; Intel Mac OS X) AppleWebKit/534.34 (KHTML, like Gecko) PhantomJS/1.7.0 Safari/534.34</User-Agent><Referer>http://www.microsoft.com/about/en/us/default.aspx</Referer><Accept>*/*</Accept></request><response><Cache-Control>max-age=900</Cache-Control><Content-Length>518</Content-Length><Content-Type>image/gif</Content-Type><Last-Modified>Wed, 21 Dec 2011 07:09:30 GMT</Last-Modified><Accept-Ranges>bytes</Accept-Ranges><ETag>"468bca7bafbfcc1:0"</ETag><Server>Microsoft-IIS/8.0</Server><P3P>CP="ALL IND DSP COR ADM CONo CUR CUSo IVAo IVDo PSA PSD TAI TELo OUR SAMo CNT COM INT NAV ONL PHY PRE PUR UNI"</P3P><X-Powered-By>ASP.NET, ARR/2.5, ASP.NET</X-Powered-By><Date>Sun, 14 Oct 2012 06:07:14 GMT</Date></response></headers></item><item><type>cssimage</type><url>http://i3.microsoft.com/about/shared/templates/components/mscomHorizNav/a.png</url><size>1117</size><resp>1582</resp><expires>2012/11/5</expires><etag>"cfdfa3814b84ca1:0"</etag><headers><request><User-Agent>Mozilla/5.0 (Macintosh; Intel Mac OS X) AppleWebKit/534.34 (KHTML, like Gecko) PhantomJS/1.7.0 Safari/534.34</User-Agent><Referer>http://www.microsoft.com/about/en/us/default.aspx</Referer><Accept>*/*</Accept></request><response><Content-Type>image/png</Content-Type><Last-Modified>Thu, 24 Dec 2009 03:45:16 GMT</Last-Modified><Accept-Ranges>bytes</Accept-Ranges><ETag>"cfdfa3814b84ca1:0"</ETag><Server>Microsoft-IIS/7.5</Server><Vtag>279265332700000000</Vtag><P3P>CP="ALL IND DSP COR ADM CONo CUR CUSo IVAo IVDo PSA PSD TAI TELo OUR SAMo CNT COM INT NAV ONL PHY PRE PUR UNI"</P3P><X-Powered-By>ASP.NET</X-Powered-By><Content-Length>1117</Content-Length><Cache-Control>max-age=1927096</Cache-Control><Date>Sun, 14 Oct 2012 06:07:14 GMT</Date><Connection>keep-alive</Connection></response></headers></item><item><type>cssimage</type><url>http://i2.microsoft.com/about/shared/templates/components/mscomHorizNav/b.png</url><size>256</size><resp>1581</resp><expires>2012/11/5</expires><etag>"9ff2b6814b84ca1:0"</etag><headers><request><User-Agent>Mozilla/5.0 (Macintosh; Intel Mac OS X) AppleWebKit/534.34 (KHTML, like Gecko) PhantomJS/1.7.0 Safari/534.34</User-Agent><Referer>http://www.microsoft.com/about/en/us/default.aspx</Referer><Accept>*/*</Accept></request><response><Content-Type>image/png</Content-Type><Last-Modified>Thu, 24 Dec 2009 03:45:16 GMT</Last-Modified><Accept-Ranges>bytes</Accept-Ranges><ETag>"9ff2b6814b84ca1:0"</ETag><Server>Microsoft-IIS/7.5</Server><Vtag>791686131500000000</Vtag><P3P>CP="ALL IND DSP COR ADM CONo CUR CUSo IVAo IVDo PSA PSD TAI TELo OUR SAMo CNT COM INT NAV ONL PHY PRE PUR UNI"</P3P><X-Powered-By>ASP.NET</X-Powered-By><Content-Length>256</Content-Length><Cache-Control>max-age=1927096</Cache-Control><Date>Sun, 14 Oct 2012 06:07:14 GMT</Date><Connection>keep-alive</Connection></response></headers></item><item><type>cssimage</type><url>http://i3.microsoft.com/about/shared/templates/components/mscomHorizNav/bullet.png</url><size>126</size><resp>1599</resp><expires>2012/10/17</expires><etag>"d616c3f2104ca1:0"</etag><headers><request><User-Agent>Mozilla/5.0 (Macintosh; Intel Mac OS X) AppleWebKit/534.34 (KHTML, like Gecko) PhantomJS/1.7.0 Safari/534.34</User-Agent><Referer>http://www.microsoft.com/about/en/us/default.aspx</Referer><Accept>*/*</Accept></request><response><Content-Type>image/png</Content-Type><Last-Modified>Mon, 13 Jul 2009 23:23:37 GMT</Last-Modified><Accept-Ranges>bytes</Accept-Ranges><ETag>"d616c3f2104ca1:0"</ETag><Server>Microsoft-IIS/7.5</Server><Vtag>279907331600000000</Vtag><P3P>CP="ALL IND DSP COR ADM CONo CUR CUSo IVAo IVDo PSA PSD TAI TELo OUR SAMo CNT COM INT NAV ONL PHY PRE PUR UNI"</P3P><X-Powered-By>ASP.NET</X-Powered-By><Content-Length>126</Content-Length><Cache-Control>max-age=300929</Cache-Control><Date>Sun, 14 Oct 2012 06:07:14 GMT</Date><Connection>keep-alive</Connection></response></headers></item><item><type>cssimage</type><url>http://i3.microsoft.com/about/shared/templates/components/mscomHorizNav/b.png</url><size>256</size><resp>1600</resp><expires>2012/11/5</expires><etag>"9ff2b6814b84ca1:0"</etag><headers><request><User-Agent>Mozilla/5.0 (Macintosh; Intel Mac OS X) AppleWebKit/534.34 (KHTML, like Gecko) PhantomJS/1.7.0 Safari/534.34</User-Agent><Referer>http://www.microsoft.com/about/en/us/default.aspx</Referer><Accept>*/*</Accept></request><response><Content-Type>image/png</Content-Type><Last-Modified>Thu, 24 Dec 2009 03:45:16 GMT</Last-Modified><Accept-Ranges>bytes</Accept-Ranges><ETag>"9ff2b6814b84ca1:0"</ETag><Server>Microsoft-IIS/7.5</Server><Vtag>791686131500000000</Vtag><P3P>CP="ALL IND DSP COR ADM CONo CUR CUSo IVAo IVDo PSA PSD TAI TELo OUR SAMo CNT COM INT NAV ONL PHY PRE PUR UNI"</P3P><X-Powered-By>ASP.NET</X-Powered-By><Content-Length>256</Content-Length><Cache-Control>max-age=1927096</Cache-Control><Date>Sun, 14 Oct 2012 06:07:14 GMT</Date><Connection>keep-alive</Connection></response></headers></item><item><type>cssimage</type><url>http://i2.microsoft.com/about/shared/templates/components/mscomHorizNav/a.png</url><size>1117</size><resp>1600</resp><expires>2012/11/5</expires><etag>"cfdfa3814b84ca1:0"</etag><headers><request><User-Agent>Mozilla/5.0 (Macintosh; Intel Mac OS X) AppleWebKit/534.34 (KHTML, like Gecko) PhantomJS/1.7.0 Safari/534.34</User-Agent><Referer>http://www.microsoft.com/about/en/us/default.aspx</Referer><Accept>*/*</Accept></request><response><Content-Type>image/png</Content-Type><Last-Modified>Thu, 24 Dec 2009 03:45:16 GMT</Last-Modified><Accept-Ranges>bytes</Accept-Ranges><ETag>"cfdfa3814b84ca1:0"</ETag><Server>Microsoft-IIS/7.5</Server><Vtag>279265332700000000</Vtag><P3P>CP="ALL IND DSP COR ADM CONo CUR CUSo IVAo IVDo PSA PSD TAI TELo OUR SAMo CNT COM INT NAV ONL PHY PRE PUR UNI"</P3P><X-Powered-By>ASP.NET</X-Powered-By><Content-Length>1117</Content-Length><Cache-Control>max-age=1927096</Cache-Control><Date>Sun, 14 Oct 2012 06:07:14 GMT</Date><Connection>keep-alive</Connection></response></headers></item><item><type>cssimage</type><url>http://i2.microsoft.com/about/shared/templates/master/AboutLegal/bg.jpg</url><size>7363</size><resp>1652</resp><expires>2012/11/5</expires><etag>"105394a45ea1ca1:0"</etag><headers><request><User-Agent>Mozilla/5.0 (Macintosh; Intel Mac OS X) AppleWebKit/534.34 (KHTML, like Gecko) PhantomJS/1.7.0 Safari/534.34</User-Agent><Referer>http://www.microsoft.com/about/en/us/default.aspx</Referer><Accept>*/*</Accept></request><response><Content-Type>image/jpeg</Content-Type><Last-Modified>Sat, 30 Jan 2010 03:45:19 GMT</Last-Modified><Accept-Ranges>bytes</Accept-Ranges><ETag>"105394a45ea1ca1:0"</ETag><Server>Microsoft-IIS/7.5</Server><Vtag>43861731900000000</Vtag><P3P>CP="ALL IND DSP COR ADM CONo CUR CUSo IVAo IVDo PSA PSD TAI TELo OUR SAMo CNT COM INT NAV ONL PHY PRE PUR UNI"</P3P><X-Powered-By>ASP.NET</X-Powered-By><Content-Length>7363</Content-Length><Cache-Control>max-age=1927096</Cache-Control><Date>Sun, 14 Oct 2012 06:07:14 GMT</Date><Connection>keep-alive</Connection></response></headers></item><item><type>cssimage</type><url>http://www.microsoft.com/global/about/twc/en/us/PublishingImages/Ip_Right_Rail.png</url><size>6737</size><resp>1803</resp><expires>2012/10/14</expires><etag>"d77debbfaebfcc1:0"</etag><headers><request><User-Agent>Mozilla/5.0 (Macintosh; Intel Mac OS X) AppleWebKit/534.34 (KHTML, like Gecko) PhantomJS/1.7.0 Safari/534.34</User-Agent><Referer>http://www.microsoft.com/about/en/us/default.aspx</Referer><Accept>*/*</Accept></request><response><Cache-Control>max-age=900</Cache-Control><Content-Length>6737</Content-Length><Content-Type>image/png</Content-Type><Last-Modified>Wed, 21 Dec 2011 07:04:15 GMT</Last-Modified><Accept-Ranges>bytes</Accept-Ranges><ETag>"d77debbfaebfcc1:0"</ETag><Server>Microsoft-IIS/8.0</Server><P3P>CP="ALL IND DSP COR ADM CONo CUR CUSo IVAo IVDo PSA PSD TAI TELo OUR SAMo CNT COM INT NAV ONL PHY PRE PUR UNI"</P3P><Vtag>791669931900000000</Vtag><X-Powered-By>ASP.NET, ARR/2.5, ASP.NET</X-Powered-By><Date>Sun, 14 Oct 2012 06:07:13 GMT</Date></response></headers></item><item><type>cssimage</type><url>http://i3.microsoft.com/about/shared/templates/master/mscomSuiteMaster/bg.png</url><size>26744</size><resp>1652</resp><expires>2012/10/17</expires><etag>"27b1c956795ca1:0"</etag><headers><request><User-Agent>Mozilla/5.0 (Macintosh; Intel Mac OS X) AppleWebKit/534.34 (KHTML, like Gecko) PhantomJS/1.7.0 Safari/534.34</User-Agent><Referer>http://www.microsoft.com/about/en/us/default.aspx</Referer><Accept>*/*</Accept></request><response><Content-Length>26744</Content-Length><Content-Type>image/png</Content-Type><Last-Modified>Thu, 14 Jan 2010 22:19:04 GMT</Last-Modified><Accept-Ranges>bytes</Accept-Ranges><ETag>"27b1c956795ca1:0"</ETag><Server>Microsoft-IIS/8.0</Server><P3P>CP="ALL IND DSP COR ADM CONo CUR CUSo IVAo IVDo PSA PSD TAI TELo OUR SAMo CNT COM INT NAV ONL PHY PRE PUR UNI"</P3P><X-Powered-By>ASP.NET</X-Powered-By><Cache-Control>max-age=300929</Cache-Control><Date>Sun, 14 Oct 2012 06:07:14 GMT</Date><Connection>keep-alive</Connection></response></headers></item><item><type>image</type><url>http://www.microsoft.com/global/en/publishingimages/sitebrand/microsoft.gif</url><size>1015</size><resp>2462</resp><expires>2012/10/14</expires><etag>"a4f4aedfe9d8c91:0"</etag><headers><request><User-Agent>Mozilla/5.0 (Macintosh; Intel Mac OS X) AppleWebKit/534.34 (KHTML, like Gecko) PhantomJS/1.7.0 Safari/534.34</User-Agent><Referer>http://www.microsoft.com/about/en/us/default.aspx</Referer><Accept>*/*</Accept></request><response><Cache-Control>max-age=900</Cache-Control><Content-Length>1015</Content-Length><Content-Type>image/gif</Content-Type><Last-Modified>Wed, 20 May 2009 01:25:34 GMT</Last-Modified><Accept-Ranges>bytes</Accept-Ranges><ETag>"a4f4aedfe9d8c91:0"</ETag><Server>Microsoft-IIS/8.0</Server><P3P>CP="ALL IND DSP COR ADM CONo CUR CUSo IVAo IVDo PSA PSD TAI TELo OUR SAMo CNT COM INT NAV ONL PHY PRE PUR UNI"</P3P><Vtag>279132932900000000</Vtag><X-Powered-By>ASP.NET, ARR/2.5, ASP.NET</X-Powered-By><Date>Sun, 14 Oct 2012 06:07:14 GMT</Date></response></headers></item><item><type>image</type><url>http://i.microsoft.com/global/about/en/us/PublishingImages/gptw.jpg</url><size>12179</size><resp>1580</resp><expires>2012/10/14</expires><etag>"a1d33f84d79bcc1:0"</etag><headers><request><User-Agent>Mozilla/5.0 (Macintosh; Intel Mac OS X) AppleWebKit/534.34 (KHTML, like Gecko) PhantomJS/1.7.0 Safari/534.34</User-Agent><Referer>http://www.microsoft.com/about/en/us/default.aspx</Referer><Accept>*/*</Accept></request><response><Content-Type>image/jpeg</Content-Type><Last-Modified>Sat, 05 Nov 2011 16:25:22 GMT</Last-Modified><Accept-Ranges>bytes</Accept-Ranges><ETag>"a1d33f84d79bcc1:0"</ETag><Server>Microsoft-IIS/8.0</Server><P3P>CP="ALL IND DSP COR ADM CONo CUR CUSo IVAo IVDo PSA PSD TAI TELo OUR SAMo CNT COM INT NAV ONL PHY PRE PUR UNI"</P3P><X-Powered-By>ASP.NET</X-Powered-By><Content-Length>12179</Content-Length><Cache-Control>max-age=860</Cache-Control><Date>Sun, 14 Oct 2012 06:07:14 GMT</Date><Connection>keep-alive</Connection></response></headers></item><item><type>image</type><url>http://i.microsoft.com/global/about/en/us/PublishingImages/ImportedContent/about/twc/en/us/About_Home_Hero.jpg</url><size>26524</size><resp>1780</resp><expires>2012/10/14</expires><etag>"6b59dbe974e0ca1:0"</etag><headers><request><User-Agent>Mozilla/5.0 (Macintosh; Intel Mac OS X) AppleWebKit/534.34 (KHTML, like Gecko) PhantomJS/1.7.0 Safari/534.34</User-Agent><Referer>http://www.microsoft.com/about/en/us/default.aspx</Referer><Accept>*/*</Accept></request><response><Content-Type>image/jpeg</Content-Type><Last-Modified>Tue, 20 Apr 2010 10:33:27 GMT</Last-Modified><Accept-Ranges>bytes</Accept-Ranges><ETag>"6b59dbe974e0ca1:0"</ETag><Server>Microsoft-IIS/8.0</Server><P3P>CP="ALL IND DSP COR ADM CONo CUR CUSo IVAo IVDo PSA PSD TAI TELo OUR SAMo CNT COM INT NAV ONL PHY PRE PUR UNI"</P3P><X-Powered-By>ASP.NET</X-Powered-By><Content-Length>26524</Content-Length><Cache-Control>max-age=900</Cache-Control><Date>Sun, 14 Oct 2012 06:07:14 GMT</Date><Connection>keep-alive</Connection></response></headers></item><item><type>image</type><url>http://i.microsoft.com/global/about/en/us/PublishingImages/70043_55x55_info.jpg</url><size>2136</size><resp>1769</resp><expires>2012/10/14</expires><etag>"7373cce774e0ca1:0"</etag><headers><request><User-Agent>Mozilla/5.0 (Macintosh; Intel Mac OS X) AppleWebKit/534.34 (KHTML, like Gecko) PhantomJS/1.7.0 Safari/534.34</User-Agent><Referer>http://www.microsoft.com/about/en/us/default.aspx</Referer><Accept>*/*</Accept></request><response><Content-Type>image/jpeg</Content-Type><Last-Modified>Tue, 20 Apr 2010 10:33:24 GMT</Last-Modified><Accept-Ranges>bytes</Accept-Ranges><ETag>"7373cce774e0ca1:0"</ETag><Server>Microsoft-IIS/8.0</Server><P3P>CP="ALL IND DSP COR ADM CONo CUR CUSo IVAo IVDo PSA PSD TAI TELo OUR SAMo CNT COM INT NAV ONL PHY PRE PUR UNI"</P3P><X-Powered-By>ASP.NET</X-Powered-By><Content-Length>2136</Content-Length><Cache-Control>max-age=900</Cache-Control><Date>Sun, 14 Oct 2012 06:07:14 GMT</Date><Connection>keep-alive</Connection></response></headers></item><item><type>image</type><url>http://i.microsoft.com/global/about/en/us/PublishingImages/70043_55x55_corp.jpg</url><size>2827</size><resp>1799</resp><expires>2012/10/14</expires><etag>"2bc93fe774e0ca1:0"</etag><headers><request><User-Agent>Mozilla/5.0 (Macintosh; Intel Mac OS X) AppleWebKit/534.34 (KHTML, like Gecko) PhantomJS/1.7.0 Safari/534.34</User-Agent><Referer>http://www.microsoft.com/about/en/us/default.aspx</Referer><Accept>*/*</Accept></request><response><Content-Type>image/jpeg</Content-Type><Last-Modified>Tue, 20 Apr 2010 10:33:23 GMT</Last-Modified><Accept-Ranges>bytes</Accept-Ranges><ETag>"2bc93fe774e0ca1:0"</ETag><Server>Microsoft-IIS/8.0</Server><P3P>CP="ALL IND DSP COR ADM CONo CUR CUSo IVAo IVDo PSA PSD TAI TELo OUR SAMo CNT COM INT NAV ONL PHY PRE PUR UNI"</P3P><X-Powered-By>ASP.NET</X-Powered-By><Content-Length>2827</Content-Length><Cache-Control>max-age=900</Cache-Control><Date>Sun, 14 Oct 2012 06:07:14 GMT</Date><Connection>keep-alive</Connection></response></headers></item><item><type>image</type><url>http://i.microsoft.com/global/about/en/us/PublishingImages/CPE_About_55x55.jpg</url><size>1510</size><resp>1769</resp><expires>2012/10/14</expires><etag>"eb52d0e874e0ca1:0"</etag><headers><request><User-Agent>Mozilla/5.0 (Macintosh; Intel Mac OS X) AppleWebKit/534.34 (KHTML, like Gecko) PhantomJS/1.7.0 Safari/534.34</User-Agent><Referer>http://www.microsoft.com/about/en/us/default.aspx</Referer><Accept>*/*</Accept></request><response><Content-Type>image/jpeg</Content-Type><Last-Modified>Tue, 20 Apr 2010 10:33:26 GMT</Last-Modified><Accept-Ranges>bytes</Accept-Ranges><ETag>"eb52d0e874e0ca1:0"</ETag><Server>Microsoft-IIS/8.0</Server><P3P>CP="ALL IND DSP COR ADM CONo CUR CUSo IVAo IVDo PSA PSD TAI TELo OUR SAMo CNT COM INT NAV ONL PHY PRE PUR UNI"</P3P><X-Powered-By>ASP.NET</X-Powered-By><Content-Length>1510</Content-Length><Cache-Control>max-age=900</Cache-Control><Date>Sun, 14 Oct 2012 06:07:14 GMT</Date><Connection>keep-alive</Connection></response></headers></item><item><type>image</type><url>http://i.microsoft.com/global/about/en/us/PublishingImages/70043_55x55_legal.jpg</url><size>2666</size><resp>1775</resp><expires>2012/10/14</expires><etag>"5b944fe874e0ca1:0"</etag><headers><request><User-Agent>Mozilla/5.0 (Macintosh; Intel Mac OS X) AppleWebKit/534.34 (KHTML, like Gecko) PhantomJS/1.7.0 Safari/534.34</User-Agent><Referer>http://www.microsoft.com/about/en/us/default.aspx</Referer><Accept>*/*</Accept></request><response><Content-Type>image/jpeg</Content-Type><Last-Modified>Tue, 20 Apr 2010 10:33:25 GMT</Last-Modified><Accept-Ranges>bytes</Accept-Ranges><ETag>"5b944fe874e0ca1:0"</ETag><Server>Microsoft-IIS/8.0</Server><P3P>CP="ALL IND DSP COR ADM CONo CUR CUSo IVAo IVDo PSA PSD TAI TELo OUR SAMo CNT COM INT NAV ONL PHY PRE PUR UNI"</P3P><X-Powered-By>ASP.NET</X-Powered-By><Content-Length>2666</Content-Length><Cache-Control>max-age=900</Cache-Control><Date>Sun, 14 Oct 2012 06:07:14 GMT</Date><Connection>keep-alive</Connection></response></headers></item><item><type>image</type><url>http://i.microsoft.com/global/about/en/us/PublishingImages/d_inc_about_hp.png</url><size>7248</size><resp>1773</resp><expires>2012/10/14</expires><etag>"62e37b788975cd1:0"</etag><headers><request><User-Agent>Mozilla/5.0 (Macintosh; Intel Mac OS X) AppleWebKit/534.34 (KHTML, like Gecko) PhantomJS/1.7.0 Safari/534.34</User-Agent><Referer>http://www.microsoft.com/about/en/us/default.aspx</Referer><Accept>*/*</Accept></request><response><Content-Type>image/png</Content-Type><Last-Modified>Wed, 08 Aug 2012 17:15:55 GMT</Last-Modified><Accept-Ranges>bytes</Accept-Ranges><ETag>"62e37b788975cd1:0"</ETag><Server>Microsoft-IIS/8.0</Server><P3P>CP="ALL IND DSP COR ADM CONo CUR CUSo IVAo IVDo PSA PSD TAI TELo OUR SAMo CNT COM INT NAV ONL PHY PRE PUR UNI"</P3P><X-Powered-By>ASP.NET</X-Powered-By><Content-Length>7248</Content-Length><Cache-Control>max-age=900</Cache-Control><Date>Sun, 14 Oct 2012 06:07:14 GMT</Date><Connection>keep-alive</Connection></response></headers></item><item><type>image</type><url>http://www.microsoft.com/about/shared/Templates/Components/cueRSSConsumer/synd.gif</url><size>1023</size><resp>1768</resp><expires>2012/11/13</expires><etag>"9c905287c4fc91:0"</etag><headers><request><User-Agent>Mozilla/5.0 (Macintosh; Intel Mac OS X) AppleWebKit/534.34 (KHTML, like Gecko) PhantomJS/1.7.0 Safari/534.34</User-Agent><Referer>http://www.microsoft.com/about/en/us/default.aspx</Referer><Accept>*/*</Accept></request><response><Cache-Control>max-age=2592000</Cache-Control><Content-Length>1023</Content-Length><Content-Type>image/gif</Content-Type><Last-Modified>Wed, 26 Nov 2008 04:04:09 GMT</Last-Modified><Accept-Ranges>bytes</Accept-Ranges><ETag>"9c905287c4fc91:0"</ETag><Server>Microsoft-IIS/7.5</Server><P3P>CP="ALL IND DSP COR ADM CONo CUR CUSo IVAo IVDo PSA PSD TAI TELo OUR SAMo CNT COM INT NAV ONL PHY PRE PUR UNI"</P3P><Vtag>438593032500000000</Vtag><X-Powered-By>ASP.NET, ARR/2.5, ASP.NET</X-Powered-By><Date>Sun, 14 Oct 2012 06:07:14 GMT</Date></response></headers></item><item><type>image</type><url>http://i.microsoft.com/about/shared/templates/components/mscomfooter/logo.png</url><size>784</size><resp>1774</resp><expires>2012/11/10</expires><etag>"672969dad18dca1:0"</etag><headers><request><User-Agent>Mozilla/5.0 (Macintosh; Intel Mac OS X) AppleWebKit/534.34 (KHTML, like Gecko) PhantomJS/1.7.0 Safari/534.34</User-Agent><Referer>http://www.microsoft.com/about/en/us/default.aspx</Referer><Accept>*/*</Accept></request><response><Content-Type>image/png</Content-Type><Last-Modified>Tue, 05 Jan 2010 06:39:38 GMT</Last-Modified><Accept-Ranges>bytes</Accept-Ranges><ETag>"672969dad18dca1:0"</ETag><Server>Microsoft-IIS/7.5</Server><Vtag>791872642600000000</Vtag><P3P>CP="ALL IND DSP COR ADM CONo CUR CUSo IVAo IVDo PSA PSD TAI TELo OUR SAMo CNT COM INT NAV ONL PHY PRE PUR UNI"</P3P><X-Powered-By>ASP.NET</X-Powered-By><Content-Length>784</Content-Length><Cache-Control>max-age=2375499</Cache-Control><Date>Sun, 14 Oct 2012 06:07:14 GMT</Date><Connection>keep-alive</Connection></response></headers></item><item><type>favicon</type><url>http://www.microsoft.com/favicon.ico</url><size>0</size><resp>null</resp><headers><response></response></headers></item><item><type>iframe</type><url><![CDATA[http://c1.microsoft.com/c.gif?DI=4050&did=1&t=]]></url><size>42</size><resp>2665</resp><cr>115</cr><cs>115</cs><headers><request><User-Agent>Mozilla/5.0 (Macintosh; Intel Mac OS X) AppleWebKit/534.34 (KHTML, like Gecko) PhantomJS/1.7.0 Safari/534.34</User-Agent><Accept>text/html,application/xhtml+xml,application/xml;q=0.9,*/*;q=0.8</Accept><Referer>http://www.microsoft.com/about/en/us/default.aspx</Referer></request><response><Cache-Control>private, no-cache, proxy-revalidate, no-store</Cache-Control><Pragma>no-cache</Pragma><Location><![CDATA[http://c1.atdmt.com/c.gif?DI=4050&did=1&t=&RedC=c1.microsoft.com&MXFR=226701A86523686C08E5025161236856]]></Location><Server>Microsoft-IIS/7.5</Server><X-Powered-By>ASP.NET</X-Powered-By><P3P>CP="BUS CUR CONo FIN IVDo ONL OUR PHY SAMo TELo"</P3P><Set-Cookie><![CDATA[MUID=226701A86523686C08E5025161236856&TUID=1; domain=.microsoft.com; expires=Tue, 14-Oct-2014 06:07:15 GMT; path=/;]]></Set-Cookie><Date>Sun, 14 Oct 2012 06:07:14 GMT</Date><Content-Length>0</Content-Length></response></headers></item><item><type>image</type><url><![CDATA[http://c1.microsoft.com/c.gif?DI=4050&did=1&t=&MUID=3B7B8ECF7E2566272C918D367A256663&cb=1cda9d229093cf0]]></url><size>42</size><resp>3152</resp><cr>190</cr><cs>190</cs><etag>"04baaef128fcc1:0"</etag><headers><request><User-Agent>Mozilla/5.0 (Macintosh; Intel Mac OS X) AppleWebKit/534.34 (KHTML, like Gecko) PhantomJS/1.7.0 Safari/534.34</User-Agent><Accept>text/html,application/xhtml+xml,application/xml;q=0.9,*/*;q=0.8</Accept><Referer>http://www.microsoft.com/about/en/us/default.aspx</Referer></request><response><Cache-Control>private, no-cache, proxy-revalidate, no-store</Cache-Control><Pragma>no-cache</Pragma><Content-Type>image/gif</Content-Type><Last-Modified>Thu, 20 Oct 2011 10:27:58 GMT</Last-Modified><Accept-Ranges>bytes</Accept-Ranges><ETag>"04baaef128fcc1:0"</ETag><Server>Microsoft-IIS/7.5</Server><X-Powered-By>ASP.NET</X-Powered-By><P3P>CP="BUS CUR CONo FIN IVDo ONL OUR PHY SAMo TELo"</P3P><Set-Cookie>MUID=3B7B8ECF7E2566272C918D367A256663; domain=.microsoft.com; expires=Tue, 14-Oct-2014 06:07:16 GMT; path=/;
ANONCHK=0; domain=c1.microsoft.com; expires=Wed, 17-Oct-2012 06:07:16 GMT; path=/;</Set-Cookie><Date>Sun, 14 Oct 2012 06:07:15 GMT</Date><Content-Length>42</Content-Length></response></headers></item></comps></results>
