<?xml version="1.0" encoding="UTF-8"?><results filename="125"><w>1248141</w><o>81</o><u>http://en.wikipedia.org/wiki/Influenza</u><r>53</r><i>sitespeed.io</i><lt>7279</lt><g><ynumreq><score>44</score><message>This page has 13 external Javascript scripts.  Try combining them into one.
This page has 6 external background images.  Try combining them with CSS sprites.</message><components></components></ynumreq><yemptysrc><score>100</score><message></message><components></components></yemptysrc><ycompress><score>100</score><message></message><components></components></ycompress><ycsstop><score>100</score><message></message><components></components></ycsstop><yjsbottom><score>100</score><message></message><components></components></yjsbottom><yexpressions><score>100</score><message></message><components></components></yexpressions><yexternal><message>Only consider this if your property is a common user home page.</message><components><item>There is a total of 16 inline css</item><item>There is a total of 6 inline scripts</item></components></yexternal><ydns><score>100</score><message></message><components><item>en.wikipedia.org: 3 components, 579.1K (72.4K GZip)</item><item>bits.wikimedia.org: 18 components, 707.6K (617.9K GZip)</item><item>meta.wikimedia.org: 1 component, 23.2K (24.3K GZip)</item><item>upload.wikimedia.org: 31 components, 526.0K</item></components></ydns><yminify><score>90</score><message>There is 1 component that can be minified</message><components><item><![CDATA[http://en.wikipedia.org/w/index.php?title=MediaWiki:Gadget-ReferenceTooltips.js&action=raw&ctype=text/javascript&508635914]]></item></components></yminify><yredirects><score>100</score><message></message><components></components></yredirects><ydupes><score>100</score><message></message><components></components></ydupes><yetags><score>100</score><message></message><components></components></yetags><yxhr><score>100</score><message></message><components></components></yxhr><yxhrmethod><score>100</score><message></message><components></components></yxhrmethod><ymindom><score>0</score><message>There are 7717 DOM elements on the page</message><components></components></ymindom><yno404><score>100</score><message></message><components></components></yno404><ymincookie><score>100</score><message></message><components></components></ymincookie><ycookiefree><score>100</score><message></message><components></components></ycookiefree><ynofilter><score>100</score><message></message><components></components></ynofilter><yimgnoscale><score>100</score><message></message><components></components></yimgnoscale><_3po_asyncjs><score>100</score><message></message><components></components></_3po_asyncjs><_3po_jsonce><score>100</score><message></message><components></components></_3po_jsonce><cssprint><score>100</score><message></message><components></components></cssprint><cssinheaddomain><score>90</score><message>The following 2 css are loaded from a different domain inside head, causing DNS lookups before page is rendered. Unique DNS in head that decreases the score:1.</message><components><item><![CDATA[http://bits.wikimedia.org/en.wikipedia.org/load.php?debug=false&lang=en&modules=ext.gadget.DRN-wizard%2CReferenceTooltips%2Ccharinsert%2Cteahouse%7Cext.wikihiero%7Cmediawiki.legacy.commonPrint%2Cshared%7Cskins.vector&only=styles&skin=vector&*]]></item><item><![CDATA[http://bits.wikimedia.org/en.wikipedia.org/load.php?debug=false&lang=en&modules=site&only=styles&skin=vector&*]]></item></components></cssinheaddomain><syncjsinhead><score>60</score><message>There are 4 scripts that are not loaded asynchronously in head, that will block the rendering.</message><components><item><![CDATA[http://bits.wikimedia.org/en.wikipedia.org/load.php?debug=false&lang=en&modules=startup&only=scripts&skin=vector&*]]></item><item><![CDATA[http://bits.wikimedia.org/en.wikipedia.org/load.php?debug=false&lang=en&modules=jquery%2Cmediawiki&only=scripts&skin=vector&version=20121009T222616Z]]></item><item><![CDATA[http://bits.wikimedia.org/en.wikipedia.org/load.php?debug=false&lang=en&modules=ext.centralNotice.bannerController%7Cext.postEdit%7Cext.wikimediaShopLink.core%7Cjquery.client%2Ccookie%2CmwExtension%7Cmediawiki.legacy.ajax%2Cwikibits%7Cmediawiki.notify%2Cutil%7Cmediawiki.page.startup&skin=vector&version=20121021T024945Z&*]]></item><item>http://bits.wikimedia.org/geoiplookup</item></components></syncjsinhead><avoidfont><score>100</score><message></message><components></components></avoidfont><totalrequests><score>73</score><message>The page uses 53 requests, that is too many to make the page load fast.</message><components><item>http://en.wikipedia.org/wiki/Influenza</item><item><![CDATA[http://bits.wikimedia.org/en.wikipedia.org/load.php?debug=false&lang=en&modules=ext.gadget.DRN-wizard%2CReferenceTooltips%2Ccharinsert%2Cteahouse%7Cext.wikihiero%7Cmediawiki.legacy.commonPrint%2Cshared%7Cskins.vector&only=styles&skin=vector&*]]></item><item><![CDATA[http://bits.wikimedia.org/en.wikipedia.org/load.php?debug=false&lang=en&modules=site&only=styles&skin=vector&*]]></item><item><![CDATA[http://bits.wikimedia.org/en.wikipedia.org/load.php?debug=false&lang=en&modules=startup&only=scripts&skin=vector&*]]></item><item><![CDATA[http://bits.wikimedia.org/en.wikipedia.org/load.php?debug=false&lang=en&modules=jquery%2Cmediawiki&only=scripts&skin=vector&version=20121009T222616Z]]></item><item><![CDATA[http://bits.wikimedia.org/en.wikipedia.org/load.php?debug=false&lang=en&modules=ext.centralNotice.bannerController%7Cext.postEdit%7Cext.wikimediaShopLink.core%7Cjquery.client%2Ccookie%2CmwExtension%7Cmediawiki.legacy.ajax%2Cwikibits%7Cmediawiki.notify%2Cutil%7Cmediawiki.page.startup&skin=vector&version=20121021T024945Z&*]]></item><item>http://bits.wikimedia.org/geoiplookup</item><item><![CDATA[http://bits.wikimedia.org/en.wikipedia.org/load.php?debug=false&lang=en&modules=skins.vector&only=scripts&skin=vector&*]]></item><item><![CDATA[http://bits.wikimedia.org/en.wikipedia.org/load.php?debug=false&lang=en&modules=ext.Experiments.experiments%2Clib%7Cext.UserBuckets%2CmarkAsHelpful%7Cext.articleFeedback.startup%7Cext.articleFeedbackv5.startup%7Cext.gadget.DRN-wizard%2CReferenceTooltips%2Ccharinsert%2Cteahouse%7Cjquery.articleFeedbackv5.verify%7Cjquery.autoEllipsis%2CcheckboxShiftClick%2CclickTracking%2CcollapsibleTabs%2CdelayedBind%2ChighlightText%2Cjson%2CmakeCollapsible%2Cmw-jump%2Cplaceholder%2Csuggestions%2CtabIndex%7Cmediawiki.api%2Ccldr%2CjqueryMsg%2Clanguage%2CsearchSuggest%2Cuser%7Cmediawiki.language.data%2Cinit%7Cmediawiki.libs.pluralruleparser%7Cmediawiki.page.ready%7Cmobile.desktop&skin=vector&version=20121021T073203Z&*]]></item><item><![CDATA[http://bits.wikimedia.org/en.wikipedia.org/load.php?debug=false&lang=en&modules=ext.vector.collapsibleNav%2CcollapsibleTabs%2CeditWarning%2CfooterCleanup%2CsimpleSearch&skin=vector&version=20121021T024938Z&*]]></item><item><![CDATA[http://bits.wikimedia.org/en.wikipedia.org/load.php?debug=false&lang=en&modules=jquery.ui.button%2Ccore%2Cwidget&skin=vector&version=20121001T132818Z&*]]></item><item><![CDATA[http://en.wikipedia.org/w/index.php?title=MediaWiki:Gadget-ReferenceTooltips.js&action=raw&ctype=text/javascript&508635914]]></item><item><![CDATA[http://bits.wikimedia.org/en.wikipedia.org/load.php?debug=false&lang=en&modules=site&only=scripts&skin=vector&*]]></item><item><![CDATA[http://meta.wikimedia.org/w/index.php?title=MediaWiki:Wikiminiatlas.js&action=raw&ctype=text/javascript&smaxage=21600&maxage=86400]]></item><item><![CDATA[http://bits.wikimedia.org/en.wikipedia.org/load.php?debug=false&lang=en&modules=ext.articleFeedback%7Cext.articleFeedback.ratingi18n%7Cjquery.appear%2CarticleFeedback%2Clocalize%2Ctipsy&skin=vector&version=20121021T024937Z&*]]></item><item><![CDATA[http://bits.wikimedia.org/en.wikipedia.org/load.php?debug=false&lang=en&modules=jquery.ui.dialog%2Cdraggable%2Cmouse%2Cposition%2Cresizable&skin=vector&version=20121001T132818Z&*]]></item><item>http://upload.wikimedia.org/wikipedia/foundation/b/b5/Jimmy_ks_close.png</item><item>http://upload.wikimedia.org/wikipedia/foundation/a/a7/CNtranslatebutton2.png</item><item>http://upload.wikimedia.org/wikipedia/commons/2/23/Icons-mini-file_acrobat.gif</item><item>http://upload.wikimedia.org/wikipedia/en/b/bc/Wiki.png</item><item>http://upload.wikimedia.org/wikipedia/commons/d/d4/Monobook-bullet-star.png</item><item>http://upload.wikimedia.org/wikipedia/commons/4/42/Monobook-bullet-ga.png</item><item>http://bits.wikimedia.org/skins/common/images/closewindow19x19.png</item><item>http://upload.wikimedia.org/wikipedia/commons/thumb/f/fc/Padlock-silver.svg/20px-Padlock-silver.svg.png</item><item>http://upload.wikimedia.org/wikipedia/commons/thumb/a/a4/EM_of_influenza_virus.jpg/226px-EM_of_influenza_virus.jpg</item><item>http://upload.wikimedia.org/wikipedia/commons/thumb/9/9e/Symptoms_of_influenza.svg/300px-Symptoms_of_influenza.svg.png</item><item>http://bits.wikimedia.org/static-1.21wmf1/skins/common/images/magnify-clip.png</item><item>http://upload.wikimedia.org/wikipedia/commons/thumb/3/3b/3D_Influenza_virus.png/300px-3D_Influenza_virus.png</item><item>http://upload.wikimedia.org/wikipedia/commons/thumb/7/7a/Influenza_nomenclature.svg/300px-Influenza_nomenclature.svg.png</item><item>http://upload.wikimedia.org/wikipedia/commons/thumb/a/a0/Virus_Replication_large.svg/300px-Virus_Replication_large.svg.png</item><item>http://upload.wikimedia.org/wikipedia/commons/thumb/b/b0/H1N1_versus_H5N1_pathology.png/280px-H1N1_versus_H5N1_pathology.png</item><item>http://upload.wikimedia.org/wikipedia/commons/thumb/c/c2/Vaccination_US_Navy.jpg/220px-Vaccination_US_Navy.jpg</item><item>http://upload.wikimedia.org/wikipedia/commons/thumb/3/30/Influenza_Seasonal_Risk_Areas.svg/300px-Influenza_Seasonal_Risk_Areas.svg.png</item><item>http://upload.wikimedia.org/wikipedia/commons/thumb/c/ca/Antigenic_drift_vs_shift.png/220px-Antigenic_drift_vs_shift.png</item><item>http://upload.wikimedia.org/wikipedia/commons/thumb/d/d2/Influenza_geneticshift.svg/220px-Influenza_geneticshift.svg.png</item><item>http://upload.wikimedia.org/wikipedia/commons/thumb/4/4f/Ferguson_influenza_generation_time_distribution.png/220px-Ferguson_influenza_generation_time_distribution.png</item><item>http://upload.wikimedia.org/wikipedia/commons/thumb/7/70/W_curve.png/300px-W_curve.png</item><item>http://upload.wikimedia.org/wikipedia/commons/thumb/b/b8/Influenza_subtypes.svg/350px-Influenza_subtypes.svg.png</item><item>http://upload.wikimedia.org/wikipedia/commons/thumb/8/86/Influenza_virus_research.jpg/170px-Influenza_virus_research.jpg</item><item>http://upload.wikimedia.org/wikipedia/commons/thumb/0/0d/Colorized_transmission_electron_micrograph_of_Avian_influenza_A_H5N1_viruses.jpg/138px-Colorized_transmission_electron_micrograph_of_Avian_influenza_A_H5N1_viruses.jpg</item><item>http://upload.wikimedia.org/wikipedia/commons/thumb/6/6d/ChineseFluInspectors.JPG/170px-ChineseFluInspectors.JPG</item><item>http://upload.wikimedia.org/wikipedia/commons/thumb/f/f8/Wiktionary-logo-en.svg/23px-Wiktionary-logo-en.svg.png</item><item>http://upload.wikimedia.org/wikipedia/en/thumb/4/4a/Commons-logo.svg/18px-Commons-logo.svg.png</item><item>http://upload.wikimedia.org/wikipedia/commons/thumb/1/1b/Wikiversity-logo-en.svg/25px-Wikiversity-logo-en.svg.png</item><item>http://upload.wikimedia.org/wikipedia/commons/thumb/2/24/Wikinews-logo.svg/25px-Wikinews-logo.svg.png</item><item>http://upload.wikimedia.org/wikipedia/commons/thumb/f/fa/Wikiquote-logo.svg/21px-Wikiquote-logo.svg.png</item><item>http://upload.wikimedia.org/wikipedia/commons/thumb/4/4c/Wikisource-logo.svg/24px-Wikisource-logo.svg.png</item><item>http://upload.wikimedia.org/wikipedia/commons/thumb/f/fa/Wikibooks-logo.svg/25px-Wikibooks-logo.svg.png</item><item>http://upload.wikimedia.org/wikipedia/en/thumb/e/e7/Cscr-featured.svg/15px-Cscr-featured.svg.png</item><item>http://bits.wikimedia.org/static-1.21wmf1/skins/vector/images/search-ltr.png?303-4</item><item>http://bits.wikimedia.org/images/wikimedia-button.png</item><item>http://bits.wikimedia.org/static-1.21wmf1/skins/common/images/poweredby_mediawiki_88x31.png</item><item>http://en.wikipedia.org/favicon.ico</item></components></totalrequests><expiresmod><score>0</score><message>There are 40 static components without a far-future expiration date.</message><components><item><![CDATA[http://bits.wikimedia.org/en.wikipedia.org/load.php?debug=false&lang=en&modules=ext.gadget.DRN-wizard%2CReferenceTooltips%2Ccharinsert%2Cteahouse%7Cext.wikihiero%7Cmediawiki.legacy.commonPrint%2Cshared%7Cskins.vector&only=styles&skin=vector&*]]></item><item><![CDATA[http://bits.wikimedia.org/en.wikipedia.org/load.php?debug=false&lang=en&modules=site&only=styles&skin=vector&*]]></item><item><![CDATA[http://bits.wikimedia.org/en.wikipedia.org/load.php?debug=false&lang=en&modules=startup&only=scripts&skin=vector&*]]></item><item>http://bits.wikimedia.org/geoiplookup</item><item><![CDATA[http://bits.wikimedia.org/en.wikipedia.org/load.php?debug=false&lang=en&modules=skins.vector&only=scripts&skin=vector&*]]></item><item><![CDATA[http://bits.wikimedia.org/en.wikipedia.org/load.php?debug=false&lang=en&modules=site&only=scripts&skin=vector&*]]></item><item><![CDATA[http://meta.wikimedia.org/w/index.php?title=MediaWiki:Wikiminiatlas.js&action=raw&ctype=text/javascript&smaxage=21600&maxage=86400]]></item><item>http://upload.wikimedia.org/wikipedia/foundation/b/b5/Jimmy_ks_close.png</item><item>http://upload.wikimedia.org/wikipedia/foundation/a/a7/CNtranslatebutton2.png</item><item>http://upload.wikimedia.org/wikipedia/commons/2/23/Icons-mini-file_acrobat.gif</item><item>http://upload.wikimedia.org/wikipedia/en/b/bc/Wiki.png</item><item>http://upload.wikimedia.org/wikipedia/commons/d/d4/Monobook-bullet-star.png</item><item>http://upload.wikimedia.org/wikipedia/commons/4/42/Monobook-bullet-ga.png</item><item>http://bits.wikimedia.org/skins/common/images/closewindow19x19.png</item><item>http://upload.wikimedia.org/wikipedia/commons/thumb/f/fc/Padlock-silver.svg/20px-Padlock-silver.svg.png</item><item>http://upload.wikimedia.org/wikipedia/commons/thumb/a/a4/EM_of_influenza_virus.jpg/226px-EM_of_influenza_virus.jpg</item><item>http://upload.wikimedia.org/wikipedia/commons/thumb/9/9e/Symptoms_of_influenza.svg/300px-Symptoms_of_influenza.svg.png</item><item>http://upload.wikimedia.org/wikipedia/commons/thumb/3/3b/3D_Influenza_virus.png/300px-3D_Influenza_virus.png</item><item>http://upload.wikimedia.org/wikipedia/commons/thumb/7/7a/Influenza_nomenclature.svg/300px-Influenza_nomenclature.svg.png</item><item>http://upload.wikimedia.org/wikipedia/commons/thumb/a/a0/Virus_Replication_large.svg/300px-Virus_Replication_large.svg.png</item><item>http://upload.wikimedia.org/wikipedia/commons/thumb/b/b0/H1N1_versus_H5N1_pathology.png/280px-H1N1_versus_H5N1_pathology.png</item><item>http://upload.wikimedia.org/wikipedia/commons/thumb/c/c2/Vaccination_US_Navy.jpg/220px-Vaccination_US_Navy.jpg</item><item>http://upload.wikimedia.org/wikipedia/commons/thumb/3/30/Influenza_Seasonal_Risk_Areas.svg/300px-Influenza_Seasonal_Risk_Areas.svg.png</item><item>http://upload.wikimedia.org/wikipedia/commons/thumb/c/ca/Antigenic_drift_vs_shift.png/220px-Antigenic_drift_vs_shift.png</item><item>http://upload.wikimedia.org/wikipedia/commons/thumb/d/d2/Influenza_geneticshift.svg/220px-Influenza_geneticshift.svg.png</item><item>http://upload.wikimedia.org/wikipedia/commons/thumb/4/4f/Ferguson_influenza_generation_time_distribution.png/220px-Ferguson_influenza_generation_time_distribution.png</item><item>http://upload.wikimedia.org/wikipedia/commons/thumb/7/70/W_curve.png/300px-W_curve.png</item><item>http://upload.wikimedia.org/wikipedia/commons/thumb/b/b8/Influenza_subtypes.svg/350px-Influenza_subtypes.svg.png</item><item>http://upload.wikimedia.org/wikipedia/commons/thumb/8/86/Influenza_virus_research.jpg/170px-Influenza_virus_research.jpg</item><item>http://upload.wikimedia.org/wikipedia/commons/thumb/0/0d/Colorized_transmission_electron_micrograph_of_Avian_influenza_A_H5N1_viruses.jpg/138px-Colorized_transmission_electron_micrograph_of_Avian_influenza_A_H5N1_viruses.jpg</item><item>http://upload.wikimedia.org/wikipedia/commons/thumb/6/6d/ChineseFluInspectors.JPG/170px-ChineseFluInspectors.JPG</item><item>http://upload.wikimedia.org/wikipedia/commons/thumb/f/f8/Wiktionary-logo-en.svg/23px-Wiktionary-logo-en.svg.png</item><item>http://upload.wikimedia.org/wikipedia/en/thumb/4/4a/Commons-logo.svg/18px-Commons-logo.svg.png</item><item>http://upload.wikimedia.org/wikipedia/commons/thumb/1/1b/Wikiversity-logo-en.svg/25px-Wikiversity-logo-en.svg.png</item><item>http://upload.wikimedia.org/wikipedia/commons/thumb/2/24/Wikinews-logo.svg/25px-Wikinews-logo.svg.png</item><item>http://upload.wikimedia.org/wikipedia/commons/thumb/f/fa/Wikiquote-logo.svg/21px-Wikiquote-logo.svg.png</item><item>http://upload.wikimedia.org/wikipedia/commons/thumb/4/4c/Wikisource-logo.svg/24px-Wikisource-logo.svg.png</item><item>http://upload.wikimedia.org/wikipedia/commons/thumb/f/fa/Wikibooks-logo.svg/25px-Wikibooks-logo.svg.png</item><item>http://upload.wikimedia.org/wikipedia/en/thumb/e/e7/Cscr-featured.svg/15px-Cscr-featured.svg.png</item><item>http://bits.wikimedia.org/images/wikimedia-button.png</item></components></expiresmod><spof><score>40</score><message>The following 6 assets are loaded from a different domain inside head and could be a single point of failure. </message><components><item><![CDATA[http://bits.wikimedia.org/en.wikipedia.org/load.php?debug=false&lang=en&modules=ext.gadget.DRN-wizard%2CReferenceTooltips%2Ccharinsert%2Cteahouse%7Cext.wikihiero%7Cmediawiki.legacy.commonPrint%2Cshared%7Cskins.vector&only=styles&skin=vector&*]]></item><item><![CDATA[http://bits.wikimedia.org/en.wikipedia.org/load.php?debug=false&lang=en&modules=site&only=styles&skin=vector&*]]></item><item><![CDATA[http://bits.wikimedia.org/en.wikipedia.org/load.php?debug=false&lang=en&modules=startup&only=scripts&skin=vector&*]]></item><item><![CDATA[http://bits.wikimedia.org/en.wikipedia.org/load.php?debug=false&lang=en&modules=jquery%2Cmediawiki&only=scripts&skin=vector&version=20121009T222616Z]]></item><item><![CDATA[http://bits.wikimedia.org/en.wikipedia.org/load.php?debug=false&lang=en&modules=ext.centralNotice.bannerController%7Cext.postEdit%7Cext.wikimediaShopLink.core%7Cjquery.client%2Ccookie%2CmwExtension%7Cmediawiki.legacy.ajax%2Cwikibits%7Cmediawiki.notify%2Cutil%7Cmediawiki.page.startup&skin=vector&version=20121021T024945Z&*]]></item><item>http://bits.wikimedia.org/geoiplookup</item></components></spof></g><w_c>74294</w_c><r_c>42</r_c><stats><doc><r>1</r><w>62980</w></doc><css><r>2</r><w>80695</w></css><js><r>13</r><w>571165</w></js><cssimage><r>6</r><w>62662</w></cssimage><image><r>30</r><w>470639</w></image><favicon><r>1</r><w>0</w></favicon></stats><stats_c><doc><r>1</r><w>0</w></doc><css><r>2</r><w>20867</w></css><js><r>5</r><w>38093</w></js><cssimage><r>6</r><w>0</w></cssimage><image><r>27</r><w>15334</w></image><favicon><r>1</r><w>0</w></favicon></stats_c><comps><item><type>doc</type><url>http://en.wikipedia.org/wiki/Influenza</url><size>569726</size><resp>373</resp><gzip>62980</gzip><headers><request><User-Agent>Mozilla/5.0 (Macintosh; Intel Mac OS X) AppleWebKit/534.34 (KHTML, like Gecko) PhantomJS/1.7.0 Safari/534.34</User-Agent><Accept>text/html,application/xhtml+xml,application/xml;q=0.9,*/*;q=0.8</Accept></request><response><Date>Sat, 20 Oct 2012 14:53:49 GMT</Date><Server>Apache</Server><X-Content-Type-Options>nosniff</X-Content-Type-Options><Cache-Control>private, s-maxage=0, max-age=0, must-revalidate</Cache-Control><Content-Language>en</Content-Language><Vary>Accept-Encoding,Cookie</Vary><Last-Modified>Fri, 19 Oct 2012 15:49:48 GMT</Last-Modified><Content-Encoding>gzip</Content-Encoding><Content-Type>text/html; charset=UTF-8</Content-Type><Age>60050</Age><X-Cache>MISS from sq71.wikimedia.org, HIT from amssq37.esams.wikimedia.org, MISS from amssq40.esams.wikimedia.org</X-Cache><X-Cache-Lookup>HIT from sq71.wikimedia.org:3128, HIT from amssq37.esams.wikimedia.org:3128, MISS from amssq40.esams.wikimedia.org:80</X-Cache-Lookup><Connection>keep-alive</Connection></response></headers></item><item><type>css</type><url><![CDATA[http://bits.wikimedia.org/en.wikipedia.org/load.php?debug=false&lang=en&modules=ext.gadget.DRN-wizard%2CReferenceTooltips%2Ccharinsert%2Cteahouse%7Cext.wikihiero%7Cmediawiki.legacy.commonPrint%2Cshared%7Cskins.vector&only=styles&skin=vector&*]]></url><size>59828</size><resp>347</resp><gzip>59828</gzip><expires>2012/10/21</expires><headers><request><User-Agent>Mozilla/5.0 (Macintosh; Intel Mac OS X) AppleWebKit/534.34 (KHTML, like Gecko) PhantomJS/1.7.0 Safari/534.34</User-Agent><Accept>text/css,*/*;q=0.1</Accept><Referer>http://en.wikipedia.org/wiki/Influenza</Referer></request><response><Server>Apache</Server><X-Powered-By>PHP/5.3.10-1ubuntu3.4+wmf1</X-Powered-By><X-Content-Type-Options>nosniff</X-Content-Type-Options><Cache-Control>public, max-age=300, s-maxage=300</Cache-Control><Last-Modified>Mon, 01 Oct 2012 14:33:46 GMT</Last-Modified><Expires>Sun, 21 Oct 2012 07:34:39 GMT</Expires><Content-Encoding>gzip</Content-Encoding><Vary>Accept-Encoding</Vary><X-Vary-Options>Accept-Encoding;list-contains=gzip</X-Vary-Options><Content-Type>text/css; charset=utf-8</Content-Type><Accept-Ranges>bytes</Accept-Ranges><Date>Sun, 21 Oct 2012 07:34:39 GMT</Date><X-Varnish>2223476546 2223476545, 1533754533 1532372833</X-Varnish><Age>300</Age><Via>1.1 varnish, 1.1 varnish</Via><Connection>keep-alive</Connection><X-Cache>cp3001 hit (23473)</X-Cache></response></headers></item><item><type>css</type><url><![CDATA[http://bits.wikimedia.org/en.wikipedia.org/load.php?debug=false&lang=en&modules=site&only=styles&skin=vector&*]]></url><size>20866</size><resp>319</resp><gzip>20867</gzip><expires>2012/10/21</expires><headers><request><User-Agent>Mozilla/5.0 (Macintosh; Intel Mac OS X) AppleWebKit/534.34 (KHTML, like Gecko) PhantomJS/1.7.0 Safari/534.34</User-Agent><Accept>text/css,*/*;q=0.1</Accept><Referer>http://en.wikipedia.org/wiki/Influenza</Referer></request><response><Server>Apache</Server><X-Powered-By>PHP/5.3.2-2wm1</X-Powered-By><X-Content-Type-Options>nosniff</X-Content-Type-Options><Cache-Control>public, max-age=300, s-maxage=300</Cache-Control><Last-Modified>Sat, 20 Oct 2012 11:30:24 GMT</Last-Modified><Expires>Sun, 21 Oct 2012 07:37:51 GMT</Expires><Content-Encoding>gzip</Content-Encoding><Vary>Accept-Encoding</Vary><X-Vary-Options>Accept-Encoding;list-contains=gzip</X-Vary-Options><Content-Type>text/css; charset=utf-8</Content-Type><Accept-Ranges>bytes</Accept-Ranges><Date>Sun, 21 Oct 2012 07:34:39 GMT</Date><X-Varnish>2223478231, 1533754558 1533253903</X-Varnish><Age>107</Age><Via>1.1 varnish, 1.1 varnish</Via><Connection>keep-alive</Connection><X-Cache>cp3001 hit (10280)</X-Cache></response></headers></item><item><type>js</type><url><![CDATA[http://bits.wikimedia.org/en.wikipedia.org/load.php?debug=false&lang=en&modules=startup&only=scripts&skin=vector&*]]></url><size>29780</size><resp>322</resp><gzip>29780</gzip><expires>2012/10/21</expires><headers><request><User-Agent>Mozilla/5.0 (Macintosh; Intel Mac OS X) AppleWebKit/534.34 (KHTML, like Gecko) PhantomJS/1.7.0 Safari/534.34</User-Agent><Accept>*/*</Accept><Referer>http://en.wikipedia.org/wiki/Influenza</Referer></request><response><Server>Apache</Server><X-Powered-By>PHP/5.3.2-2wm1</X-Powered-By><X-Content-Type-Options>nosniff</X-Content-Type-Options><Cache-Control>public, max-age=300, s-maxage=300</Cache-Control><Last-Modified>Sun, 21 Oct 2012 07:32:05 GMT</Last-Modified><Expires>Sun, 21 Oct 2012 07:37:05 GMT</Expires><Content-Encoding>gzip</Content-Encoding><Vary>Accept-Encoding</Vary><X-Vary-Options>Accept-Encoding;list-contains=gzip</X-Vary-Options><Content-Type>text/javascript; charset=utf-8</Content-Type><Accept-Ranges>bytes</Accept-Ranges><Date>Sun, 21 Oct 2012 07:34:39 GMT</Date><X-Varnish>2929998852 2929998345, 787462927 787083499</X-Varnish><Age>153</Age><Via>1.1 varnish, 1.1 varnish</Via><Connection>keep-alive</Connection><X-Cache>cp3002 hit (7852)</X-Cache></response></headers></item><item><type>js</type><url><![CDATA[http://bits.wikimedia.org/en.wikipedia.org/load.php?debug=false&lang=en&modules=jquery%2Cmediawiki&only=scripts&skin=vector&version=20121009T222616Z]]></url><size>162079</size><resp>443</resp><gzip>78139</gzip><expires>2012/11/11</expires><headers><request><User-Agent>Mozilla/5.0 (Macintosh; Intel Mac OS X) AppleWebKit/534.34 (KHTML, like Gecko) PhantomJS/1.7.0 Safari/534.34</User-Agent><Accept>*/*</Accept><Referer>http://en.wikipedia.org/wiki/Influenza</Referer></request><response><Server>Apache</Server><X-Powered-By>PHP/5.3.2-2wm1</X-Powered-By><X-Content-Type-Options>nosniff</X-Content-Type-Options><Cache-Control>public, max-age=2592000, s-maxage=2592000</Cache-Control><Last-Modified>Tue, 09 Oct 2012 22:26:16 GMT</Last-Modified><Expires>Sun, 11 Nov 2012 15:41:57 GMT</Expires><Content-Encoding>gzip</Content-Encoding><Vary>Accept-Encoding</Vary><X-Vary-Options>Accept-Encoding;list-contains=gzip</X-Vary-Options><Content-Type>text/javascript; charset=utf-8</Content-Type><Accept-Ranges>bytes</Accept-Ranges><Date>Sun, 21 Oct 2012 07:34:39 GMT</Date><X-Varnish>2223159215 1485872358, 1533754897 1362707142</X-Varnish><Age>748362</Age><Via>1.1 varnish, 1.1 varnish</Via><Connection>keep-alive</Connection><X-Cache>cp3001 hit (1565567)</X-Cache></response></headers></item><item><type>js</type><url><![CDATA[http://bits.wikimedia.org/en.wikipedia.org/load.php?debug=false&lang=en&modules=ext.centralNotice.bannerController%7Cext.postEdit%7Cext.wikimediaShopLink.core%7Cjquery.client%2Ccookie%2CmwExtension%7Cmediawiki.legacy.ajax%2Cwikibits%7Cmediawiki.notify%2Cutil%7Cmediawiki.page.startup&skin=vector&version=20121021T024945Z&*]]></url><size>40221</size><resp>508</resp><gzip>40222</gzip><expires>2012/11/20</expires><headers><request><User-Agent>Mozilla/5.0 (Macintosh; Intel Mac OS X) AppleWebKit/534.34 (KHTML, like Gecko) PhantomJS/1.7.0 Safari/534.34</User-Agent><Accept>*/*</Accept><Referer>http://en.wikipedia.org/wiki/Influenza</Referer></request><response><Server>Apache</Server><X-Powered-By>PHP/5.3.2-2wm1</X-Powered-By><X-Content-Type-Options>nosniff</X-Content-Type-Options><Cache-Control>public, max-age=2592000, s-maxage=2592000</Cache-Control><Last-Modified>Sun, 21 Oct 2012 02:49:45 GMT</Last-Modified><Expires>Tue, 20 Nov 2012 02:50:16 GMT</Expires><Content-Encoding>gzip</Content-Encoding><Vary>Accept-Encoding</Vary><X-Vary-Options>Accept-Encoding;list-contains=gzip</X-Vary-Options><Content-Type>text/javascript; charset=utf-8</Content-Type><Accept-Ranges>bytes</Accept-Ranges><Date>Sun, 21 Oct 2012 07:34:39 GMT</Date><X-Varnish>2223388011, 1533755498 1504097933</X-Varnish><Age>17063</Age><Via>1.1 varnish, 1.1 varnish</Via><Connection>keep-alive</Connection><X-Cache>cp3001 hit (171964)</X-Cache></response></headers></item><item><type>js</type><url>http://bits.wikimedia.org/geoiplookup</url><size>114</size><resp>322</resp><expires>2012/10/22</expires><headers><request><User-Agent>Mozilla/5.0 (Macintosh; Intel Mac OS X) AppleWebKit/534.34 (KHTML, like Gecko) PhantomJS/1.7.0 Safari/534.34</User-Agent><Accept>*/*</Accept><Referer>http://en.wikipedia.org/wiki/Influenza</Referer></request><response><Server>Varnish</Server><Content-Type>text/javascript</Content-Type><Content-Length>114</Content-Length><Last-Modified>Sun, 21 Oct 2012 07:34:39 GMT</Last-Modified><Cache-Control>private, max-age=86400, s-maxage=0</Cache-Control><Accept-Ranges>bytes</Accept-Ranges><Date>Sun, 21 Oct 2012 07:34:39 GMT</Date><X-Varnish>1533754559</X-Varnish><Age>0</Age><Via>1.1 varnish</Via><Connection>close</Connection><X-Cache>cp3001 miss (0)</X-Cache></response></headers></item><item><type>js</type><url><![CDATA[http://bits.wikimedia.org/en.wikipedia.org/load.php?debug=false&lang=en&modules=skins.vector&only=scripts&skin=vector&*]]></url><size>441</size><resp>405</resp><gzip>441</gzip><expires>2012/10/21</expires><headers><request><User-Agent>Mozilla/5.0 (Macintosh; Intel Mac OS X) AppleWebKit/534.34 (KHTML, like Gecko) PhantomJS/1.7.0 Safari/534.34</User-Agent><Accept>*/*</Accept><Referer>http://en.wikipedia.org/wiki/Influenza</Referer></request><response><Server>Apache</Server><X-Powered-By>PHP/5.3.2-2wm1</X-Powered-By><X-Content-Type-Options>nosniff</X-Content-Type-Options><Cache-Control>public, max-age=300, s-maxage=300</Cache-Control><Last-Modified>Mon, 01 Oct 2012 13:28:18 GMT</Last-Modified><Expires>Sun, 21 Oct 2012 07:34:43 GMT</Expires><Content-Encoding>gzip</Content-Encoding><Vary>Accept-Encoding</Vary><X-Vary-Options>Accept-Encoding;list-contains=gzip</X-Vary-Options><Content-Type>text/javascript; charset=utf-8</Content-Type><Accept-Ranges>bytes</Accept-Ranges><Date>Sun, 21 Oct 2012 07:34:39 GMT</Date><X-Varnish>2929997270, 787463372 786097578</X-Varnish><Age>296</Age><Via>1.1 varnish, 1.1 varnish</Via><Connection>keep-alive</Connection><X-Cache>cp3002 hit (24242)</X-Cache></response></headers></item><item><type>js</type><url><![CDATA[http://bits.wikimedia.org/en.wikipedia.org/load.php?debug=false&lang=en&modules=ext.Experiments.experiments%2Clib%7Cext.UserBuckets%2CmarkAsHelpful%7Cext.articleFeedback.startup%7Cext.articleFeedbackv5.startup%7Cext.gadget.DRN-wizard%2CReferenceTooltips%2Ccharinsert%2Cteahouse%7Cjquery.articleFeedbackv5.verify%7Cjquery.autoEllipsis%2CcheckboxShiftClick%2CclickTracking%2CcollapsibleTabs%2CdelayedBind%2ChighlightText%2Cjson%2CmakeCollapsible%2Cmw-jump%2Cplaceholder%2Csuggestions%2CtabIndex%7Cmediawiki.api%2Ccldr%2CjqueryMsg%2Clanguage%2CsearchSuggest%2Cuser%7Cmediawiki.language.data%2Cinit%7Cmediawiki.libs.pluralruleparser%7Cmediawiki.page.ready%7Cmobile.desktop&skin=vector&version=20121021T073203Z&*]]></url><size>152323</size><resp>2353</resp><gzip>153928</gzip><expires>2012/11/20</expires><headers><request><User-Agent>Mozilla/5.0 (Macintosh; Intel Mac OS X) AppleWebKit/534.34 (KHTML, like Gecko) PhantomJS/1.7.0 Safari/534.34</User-Agent><Accept>*/*</Accept><Referer>http://en.wikipedia.org/wiki/Influenza</Referer></request><response><Server>Apache</Server><X-Powered-By>PHP/5.3.2-2wm1</X-Powered-By><X-Content-Type-Options>nosniff</X-Content-Type-Options><Cache-Control>public, max-age=2592000, s-maxage=2592000</Cache-Control><Last-Modified>Sun, 21 Oct 2012 07:33:15 GMT</Last-Modified><Expires>Tue, 20 Nov 2012 07:33:18 GMT</Expires><Content-Encoding>gzip</Content-Encoding><Vary>Accept-Encoding</Vary><X-Vary-Options>Accept-Encoding;list-contains=gzip</X-Vary-Options><Content-Type>text/javascript; charset=utf-8</Content-Type><Accept-Ranges>bytes</Accept-Ranges><Date>Sun, 21 Oct 2012 07:34:41 GMT</Date><X-Varnish>2223478389, 1533764268 1533375840</X-Varnish><Age>83</Age><Via>1.1 varnish, 1.1 varnish</Via><Connection>keep-alive</Connection><X-Cache>cp3001 hit (1808)</X-Cache></response></headers></item><item><type>js</type><url><![CDATA[http://bits.wikimedia.org/en.wikipedia.org/load.php?debug=false&lang=en&modules=ext.vector.collapsibleNav%2CcollapsibleTabs%2CeditWarning%2CfooterCleanup%2CsimpleSearch&skin=vector&version=20121021T024938Z&*]]></url><size>17035</size><resp>2350</resp><gzip>17035</gzip><expires>2012/11/20</expires><headers><request><User-Agent>Mozilla/5.0 (Macintosh; Intel Mac OS X) AppleWebKit/534.34 (KHTML, like Gecko) PhantomJS/1.7.0 Safari/534.34</User-Agent><Accept>*/*</Accept><Referer>http://en.wikipedia.org/wiki/Influenza</Referer></request><response><Server>Apache</Server><X-Powered-By>PHP/5.3.2-2wm1</X-Powered-By><X-Content-Type-Options>nosniff</X-Content-Type-Options><Cache-Control>public, max-age=2592000, s-maxage=2592000</Cache-Control><Last-Modified>Sun, 21 Oct 2012 02:49:38 GMT</Last-Modified><Expires>Tue, 20 Nov 2012 02:50:16 GMT</Expires><Content-Encoding>gzip</Content-Encoding><Vary>Accept-Encoding</Vary><X-Vary-Options>Accept-Encoding;list-contains=gzip</X-Vary-Options><Content-Type>text/javascript; charset=utf-8</Content-Type><Accept-Ranges>bytes</Accept-Ranges><Date>Sun, 21 Oct 2012 07:34:41 GMT</Date><X-Varnish>3332133885, 787472742 757840372</X-Varnish><Age>17064</Age><Via>1.1 varnish, 1.1 varnish</Via><Connection>keep-alive</Connection><X-Cache>cp3002 hit (313588)</X-Cache></response></headers></item><item><type>js</type><url><![CDATA[http://bits.wikimedia.org/en.wikipedia.org/load.php?debug=false&lang=en&modules=jquery.ui.button%2Ccore%2Cwidget&skin=vector&version=20121001T132818Z&*]]></url><size>85830</size><resp>2352</resp><gzip>85830</gzip><expires>2012/11/11</expires><headers><request><User-Agent>Mozilla/5.0 (Macintosh; Intel Mac OS X) AppleWebKit/534.34 (KHTML, like Gecko) PhantomJS/1.7.0 Safari/534.34</User-Agent><Accept>*/*</Accept><Referer>http://en.wikipedia.org/wiki/Influenza</Referer></request><response><Server>Apache</Server><X-Powered-By>PHP/5.3.10-1ubuntu3.4+wmf1</X-Powered-By><X-Content-Type-Options>nosniff</X-Content-Type-Options><Cache-Control>public, max-age=2592000, s-maxage=2592000</Cache-Control><Last-Modified>Mon, 01 Oct 2012 13:28:18 GMT</Last-Modified><Expires>Sun, 11 Nov 2012 14:07:04 GMT</Expires><Content-Encoding>gzip</Content-Encoding><Vary>Accept-Encoding</Vary><X-Vary-Options>Accept-Encoding;list-contains=gzip</X-Vary-Options><Content-Type>text/javascript; charset=utf-8</Content-Type><Accept-Ranges>bytes</Accept-Ranges><Date>Sun, 21 Oct 2012 07:34:41 GMT</Date><X-Varnish>3331906409 2594374373, 1533764290 1362706248</X-Varnish><Age>754057</Age><Via>1.1 varnish, 1.1 varnish</Via><Connection>keep-alive</Connection><X-Cache>cp3001 hit (1536428)</X-Cache></response></headers></item><item><type>js</type><url><![CDATA[http://en.wikipedia.org/w/index.php?title=MediaWiki:Gadget-ReferenceTooltips.js&action=raw&ctype=text/javascript&508635914]]></url><size>9470</size><resp>406</resp><gzip>9470</gzip><expires>2012/11/21</expires><headers><request><User-Agent>Mozilla/5.0 (Macintosh; Intel Mac OS X) AppleWebKit/534.34 (KHTML, like Gecko) PhantomJS/1.7.0 Safari/534.34</User-Agent><Accept>*/*</Accept><Referer>http://en.wikipedia.org/wiki/Influenza</Referer></request><response><Server>Apache</Server><X-Content-Type-Options>nosniff</X-Content-Type-Options><Cache-Control>public, s-maxage=300, max-age=2678400</Cache-Control><Content-Encoding>gzip</Content-Encoding><Vary>Accept-Encoding</Vary><Date>Sun, 21 Oct 2012 07:34:31 GMT</Date><Content-Type>text/javascript; charset=UTF-8</Content-Type><Last-Modified>Wed, 22 Aug 2012 16:12:35 GMT</Last-Modified><Age>8</Age><X-Cache>HIT from amssq37.esams.wikimedia.org, HIT from amssq40.esams.wikimedia.org</X-Cache><X-Cache-Lookup>HIT from amssq37.esams.wikimedia.org:3128, HIT from amssq40.esams.wikimedia.org:80</X-Cache-Lookup><Connection>keep-alive</Connection></response></headers></item><item><type>js</type><url><![CDATA[http://bits.wikimedia.org/en.wikipedia.org/load.php?debug=false&lang=en&modules=site&only=scripts&skin=vector&*]]></url><size>8199</size><resp>405</resp><gzip>8199</gzip><expires>2012/10/21</expires><headers><request><User-Agent>Mozilla/5.0 (Macintosh; Intel Mac OS X) AppleWebKit/534.34 (KHTML, like Gecko) PhantomJS/1.7.0 Safari/534.34</User-Agent><Accept>*/*</Accept><Referer>http://en.wikipedia.org/wiki/Influenza</Referer></request><response><Server>Apache</Server><X-Powered-By>PHP/5.3.2-2wm1</X-Powered-By><X-Content-Type-Options>nosniff</X-Content-Type-Options><Cache-Control>public, max-age=300, s-maxage=300</Cache-Control><Last-Modified>Sat, 20 Oct 2012 11:30:24 GMT</Last-Modified><Expires>Sun, 21 Oct 2012 07:36:56 GMT</Expires><Content-Encoding>gzip</Content-Encoding><Vary>Accept-Encoding</Vary><X-Vary-Options>Accept-Encoding;list-contains=gzip</X-Vary-Options><Content-Type>text/javascript; charset=utf-8</Content-Type><Accept-Ranges>bytes</Accept-Ranges><Date>Sun, 21 Oct 2012 07:34:39 GMT</Date><X-Varnish>2929998255, 1533754960 1533000785</X-Varnish><Age>163</Age><Via>1.1 varnish, 1.1 varnish</Via><Connection>keep-alive</Connection><X-Cache>cp3001 hit (13829)</X-Cache></response></headers></item><item><type>js</type><url><![CDATA[http://meta.wikimedia.org/w/index.php?title=MediaWiki:Wikiminiatlas.js&action=raw&ctype=text/javascript&smaxage=21600&maxage=86400]]></url><size>23206</size><resp>2351</resp><gzip>24302</gzip><expires>1970/1/1</expires><headers><request><User-Agent>Mozilla/5.0 (Macintosh; Intel Mac OS X) AppleWebKit/534.34 (KHTML, like Gecko) PhantomJS/1.7.0 Safari/534.34</User-Agent><Accept>*/*</Accept><Referer>http://en.wikipedia.org/wiki/Influenza</Referer></request><response><X-Content-Type-Options>nosniff</X-Content-Type-Options><Content-Encoding>gzip</Content-Encoding><Server>Apache</Server><Cache-Control>private, must-revalidate, max-age=0</Cache-Control><Vary>Accept-Encoding,Cookie</Vary><Expires>Thu, 01 Jan 1970 00:00:00 GMT</Expires><Date>Sun, 21 Oct 2012 07:34:40 GMT</Date><Content-Type>text/javascript; charset=UTF-8</Content-Type><Last-Modified>Tue, 02 Oct 2012 18:03:27 GMT</Last-Modified><Age>1</Age><X-Cache>HIT from sq66.wikimedia.org, HIT from amssq33.esams.wikimedia.org, MISS from knsq23.knams.wikimedia.org</X-Cache><X-Cache-Lookup>HIT from sq66.wikimedia.org:3128, HIT from amssq33.esams.wikimedia.org:3128, MISS from knsq23.knams.wikimedia.org:80</X-Cache-Lookup><Connection>keep-alive</Connection></response></headers></item><item><type>js</type><url><![CDATA[http://bits.wikimedia.org/en.wikipedia.org/load.php?debug=false&lang=en&modules=ext.articleFeedback%7Cext.articleFeedback.ratingi18n%7Cjquery.appear%2CarticleFeedback%2Clocalize%2Ctipsy&skin=vector&version=20121021T024937Z&*]]></url><size>55639</size><resp>6989</resp><gzip>55639</gzip><expires>2012/11/20</expires><headers><request><User-Agent>Mozilla/5.0 (Macintosh; Intel Mac OS X) AppleWebKit/534.34 (KHTML, like Gecko) PhantomJS/1.7.0 Safari/534.34</User-Agent><Accept>*/*</Accept><Referer>http://en.wikipedia.org/wiki/Influenza</Referer></request><response><Server>Apache</Server><X-Powered-By>PHP/5.3.2-2wm1</X-Powered-By><X-Content-Type-Options>nosniff</X-Content-Type-Options><Cache-Control>public, max-age=2592000, s-maxage=2592000</Cache-Control><Last-Modified>Sun, 21 Oct 2012 02:49:37 GMT</Last-Modified><Expires>Tue, 20 Nov 2012 02:49:54 GMT</Expires><Content-Encoding>gzip</Content-Encoding><Vary>Accept-Encoding</Vary><X-Vary-Options>Accept-Encoding;list-contains=gzip</X-Vary-Options><Content-Type>text/javascript; charset=utf-8</Content-Type><Accept-Ranges>bytes</Accept-Ranges><Date>Sun, 21 Oct 2012 07:34:45 GMT</Date><X-Varnish>2223387901, 1533784753 1504079194</X-Varnish><Age>17091</Age><Via>1.1 varnish, 1.1 varnish</Via><Connection>keep-alive</Connection><X-Cache>cp3001 hit (262635)</X-Cache></response></headers></item><item><type>js</type><url><![CDATA[http://bits.wikimedia.org/en.wikipedia.org/load.php?debug=false&lang=en&modules=jquery.ui.dialog%2Cdraggable%2Cmouse%2Cposition%2Cresizable&skin=vector&version=20121001T132818Z&*]]></url><size>68066</size><resp>6990</resp><gzip>68066</gzip><expires>2012/11/11</expires><headers><request><User-Agent>Mozilla/5.0 (Macintosh; Intel Mac OS X) AppleWebKit/534.34 (KHTML, like Gecko) PhantomJS/1.7.0 Safari/534.34</User-Agent><Accept>*/*</Accept><Referer>http://en.wikipedia.org/wiki/Influenza</Referer></request><response><Server>Apache</Server><X-Powered-By>PHP/5.3.2-2wm1</X-Powered-By><X-Content-Type-Options>nosniff</X-Content-Type-Options><Cache-Control>public, max-age=2592000, s-maxage=2592000</Cache-Control><Last-Modified>Mon, 01 Oct 2012 13:28:18 GMT</Last-Modified><Expires>Sun, 11 Nov 2012 15:42:13 GMT</Expires><Content-Encoding>gzip</Content-Encoding><Vary>Accept-Encoding</Vary><X-Vary-Options>Accept-Encoding;list-contains=gzip</X-Vary-Options><Content-Type>text/javascript; charset=utf-8</Content-Type><Accept-Ranges>bytes</Accept-Ranges><Date>Sun, 21 Oct 2012 07:34:45 GMT</Date><X-Varnish>2929735246 2191750644, 787493419 664764809</X-Varnish><Age>748352</Age><Via>1.1 varnish, 1.1 varnish</Via><Connection>keep-alive</Connection><X-Cache>cp3002 hit (954446)</X-Cache></response></headers></item><item><type>cssimage</type><url>http://upload.wikimedia.org/wikipedia/foundation/b/b5/Jimmy_ks_close.png</url><size>38909</size><resp>7277</resp><etag>a969a4b5d157e3d3bec4cdc6e5dbb665</etag><headers><request><User-Agent>Mozilla/5.0 (Macintosh; Intel Mac OS X) AppleWebKit/534.34 (KHTML, like Gecko) PhantomJS/1.7.0 Safari/534.34</User-Agent><Referer>http://en.wikipedia.org/wiki/Influenza</Referer><Accept>*/*</Accept></request><response><X-Object-Meta-Sha1base36>r56gcw87cmqu25n5qcbmd3hsv5ayfej</X-Object-Meta-Sha1base36><X-Timestamp>1343375847.85735</X-Timestamp><Accept-Ranges>bytes</Accept-Ranges><Content-Length>38909</Content-Length><Date>Thu, 18 Oct 2012 07:11:45 GMT</Date><Content-Type>image/png</Content-Type><Last-Modified>Fri, 27 Jul 2012 07:57:27 GMT</Last-Modified><ETag>a969a4b5d157e3d3bec4cdc6e5dbb665</ETag><Age>260581</Age><X-Cache>HIT from amssq58.esams.wikimedia.org, HIT from amssq54.esams.wikimedia.org</X-Cache><X-Cache-Lookup>HIT from amssq58.esams.wikimedia.org:3128, HIT from amssq54.esams.wikimedia.org:80</X-Cache-Lookup><Connection>keep-alive</Connection></response></headers></item><item><type>cssimage</type><url>http://upload.wikimedia.org/wikipedia/foundation/a/a7/CNtranslatebutton2.png</url><size>3046</size><resp>7276</resp><etag>"be6-4ef363f7"</etag><headers><request><User-Agent>Mozilla/5.0 (Macintosh; Intel Mac OS X) AppleWebKit/534.34 (KHTML, like Gecko) PhantomJS/1.7.0 Safari/534.34</User-Agent><Referer>http://en.wikipedia.org/wiki/Influenza</Referer><Accept>*/*</Accept></request><response><Server>Sun-Java-System-Web-Server/7.0</Server><Content-Length>3046</Content-Length><Accept-Ranges>bytes</Accept-Ranges><Date>Sat, 25 Aug 2012 08:42:09 GMT</Date><Content-Type>image/png</Content-Type><Last-Modified>Thu, 22 Dec 2011 17:08:07 GMT</Last-Modified><ETag>"be6-4ef363f7"</ETag><Age>4920757</Age><X-Cache>HIT from amssq54.esams.wikimedia.org, HIT from amssq54.esams.wikimedia.org</X-Cache><X-Cache-Lookup>HIT from amssq54.esams.wikimedia.org:3128, HIT from amssq54.esams.wikimedia.org:80</X-Cache-Lookup><Connection>keep-alive</Connection></response></headers></item><item><type>cssimage</type><url>http://upload.wikimedia.org/wikipedia/commons/2/23/Icons-mini-file_acrobat.gif</url><size>291</size><resp>1261</resp><etag>5f29c417cdbae1c11f4451f0428ef444</etag><headers><request><User-Agent>Mozilla/5.0 (Macintosh; Intel Mac OS X) AppleWebKit/534.34 (KHTML, like Gecko) PhantomJS/1.7.0 Safari/534.34</User-Agent><Referer>http://en.wikipedia.org/wiki/Influenza</Referer><Accept>*/*</Accept></request><response><X-Object-Meta-Sha1base36>lwohv5rxnuoyzvtwvg2jugrrqvdefu2</X-Object-Meta-Sha1base36><X-Timestamp>1342405729.98084</X-Timestamp><Accept-Ranges>bytes</Accept-Ranges><Content-Length>291</Content-Length><Date>Mon, 24 Sep 2012 03:48:25 GMT</Date><Content-Type>image/gif</Content-Type><Last-Modified>Mon, 16 Jul 2012 02:28:49 GMT</Last-Modified><ETag>5f29c417cdbae1c11f4451f0428ef444</ETag><Age>2346375</Age><X-Cache>HIT from knsq20.knams.wikimedia.org, HIT from amssq54.esams.wikimedia.org</X-Cache><X-Cache-Lookup>HIT from knsq20.knams.wikimedia.org:3128, HIT from amssq54.esams.wikimedia.org:80</X-Cache-Lookup><Connection>keep-alive</Connection></response></headers></item><item><type>cssimage</type><url>http://upload.wikimedia.org/wikipedia/en/b/bc/Wiki.png</url><size>19670</size><resp>1267</resp><etag>81a7ce38ad250ee09209b1b2cdf50830</etag><headers><request><User-Agent>Mozilla/5.0 (Macintosh; Intel Mac OS X) AppleWebKit/534.34 (KHTML, like Gecko) PhantomJS/1.7.0 Safari/534.34</User-Agent><Referer>http://en.wikipedia.org/wiki/Influenza</Referer><Accept>*/*</Accept></request><response><X-Object-Meta-Sha1base36>c2gn6q1vfgxtngkjx99jp4t9jdpyzzo</X-Object-Meta-Sha1base36><Last-Modified>Sun, 29 Jul 2012 15:27:45 GMT</Last-Modified><ETag>81a7ce38ad250ee09209b1b2cdf50830</ETag><X-Timestamp>1343575665.99288</X-Timestamp><Accept-Ranges>bytes</Accept-Ranges><Content-Length>19670</Content-Length><Content-Type>image/png</Content-Type><Date>Thu, 18 Oct 2012 15:06:43 GMT</Date><Age>232077</Age><X-Cache>HIT from sq85.wikimedia.org, HIT from amssq50.esams.wikimedia.org, HIT from amssq54.esams.wikimedia.org</X-Cache><X-Cache-Lookup>HIT from sq85.wikimedia.org:3128, HIT from amssq50.esams.wikimedia.org:3128, HIT from amssq54.esams.wikimedia.org:80</X-Cache-Lookup><Connection>keep-alive</Connection></response></headers></item><item><type>cssimage</type><url>http://upload.wikimedia.org/wikipedia/commons/d/d4/Monobook-bullet-star.png</url><size>272</size><resp>6986</resp><etag>6c1b50f606e58b85245e6c9fe4b1c62f</etag><headers><request><User-Agent>Mozilla/5.0 (Macintosh; Intel Mac OS X) AppleWebKit/534.34 (KHTML, like Gecko) PhantomJS/1.7.0 Safari/534.34</User-Agent><Referer>http://en.wikipedia.org/wiki/Influenza</Referer><Accept>*/*</Accept></request><response><X-Object-Meta-Sha1base36>m22fpdjmsnyyoxorhv5uszjz14jeoif</X-Object-Meta-Sha1base36><X-Timestamp>1342766531.17577</X-Timestamp><Accept-Ranges>bytes</Accept-Ranges><Content-Length>272</Content-Length><Date>Tue, 16 Oct 2012 13:39:16 GMT</Date><Content-Type>image/png</Content-Type><Last-Modified>Fri, 20 Jul 2012 06:42:11 GMT</Last-Modified><ETag>6c1b50f606e58b85245e6c9fe4b1c62f</ETag><Age>410125</Age><X-Cache>HIT from amssq57.esams.wikimedia.org, HIT from amssq54.esams.wikimedia.org</X-Cache><X-Cache-Lookup>HIT from amssq57.esams.wikimedia.org:3128, HIT from amssq54.esams.wikimedia.org:80</X-Cache-Lookup><Connection>keep-alive</Connection></response></headers></item><item><type>cssimage</type><url>http://upload.wikimedia.org/wikipedia/commons/4/42/Monobook-bullet-ga.png</url><size>474</size><resp>6988</resp><etag>4d76b5b3c3c96f9c45385587e0440c9e</etag><headers><request><User-Agent>Mozilla/5.0 (Macintosh; Intel Mac OS X) AppleWebKit/534.34 (KHTML, like Gecko) PhantomJS/1.7.0 Safari/534.34</User-Agent><Referer>http://en.wikipedia.org/wiki/Influenza</Referer><Accept>*/*</Accept></request><response><X-Object-Meta-Sha1base36>mbo1us58ann7uu1gno7f8ubu9gfxvv4</X-Object-Meta-Sha1base36><X-Timestamp>1342191757.62493</X-Timestamp><Accept-Ranges>bytes</Accept-Ranges><Content-Length>474</Content-Length><Date>Thu, 18 Oct 2012 06:02:31 GMT</Date><Content-Type>image/png</Content-Type><Last-Modified>Fri, 13 Jul 2012 15:02:37 GMT</Last-Modified><ETag>4d76b5b3c3c96f9c45385587e0440c9e</ETag><Age>264730</Age><X-Cache>HIT from amssq61.esams.wikimedia.org, HIT from amssq54.esams.wikimedia.org</X-Cache><X-Cache-Lookup>HIT from amssq61.esams.wikimedia.org:3128, HIT from amssq54.esams.wikimedia.org:80</X-Cache-Lookup><Connection>keep-alive</Connection></response></headers></item><item><type>image</type><url>http://bits.wikimedia.org/skins/common/images/closewindow19x19.png</url><size>833</size><resp>6988</resp><etag>"341-4caff60e60080"</etag><headers><request><User-Agent>Mozilla/5.0 (Macintosh; Intel Mac OS X) AppleWebKit/534.34 (KHTML, like Gecko) PhantomJS/1.7.0 Safari/534.34</User-Agent><Referer>http://en.wikipedia.org/wiki/Influenza</Referer><Accept>*/*</Accept></request><response><Server>Apache</Server><Last-Modified>Mon, 01 Oct 2012 13:28:18 GMT</Last-Modified><ETag>"341-4caff60e60080"</ETag><Content-Type>image/png</Content-Type><Content-Length>833</Content-Length><Accept-Ranges>bytes</Accept-Ranges><Date>Sun, 21 Oct 2012 07:34:41 GMT</Date><X-Varnish>2929998670 2929998004, 1533764681 1533275826</X-Varnish><Age>202</Age><Via>1.1 varnish, 1.1 varnish</Via><Connection>keep-alive</Connection><X-Cache>cp3001 hit (17088)</X-Cache></response></headers></item><item><type>image</type><url>http://upload.wikimedia.org/wikipedia/commons/thumb/f/fc/Padlock-silver.svg/20px-Padlock-silver.svg.png</url><size>837</size><resp>617</resp><headers><request><User-Agent>Mozilla/5.0 (Macintosh; Intel Mac OS X) AppleWebKit/534.34 (KHTML, like Gecko) PhantomJS/1.7.0 Safari/534.34</User-Agent><Referer>http://en.wikipedia.org/wiki/Influenza</Referer><Accept>*/*</Accept></request><response><Server>nginx/0.7.65</Server><Content-Length>837</Content-Length><Accept-Ranges>bytes</Accept-Ranges><Date>Wed, 17 Oct 2012 00:27:28 GMT</Date><Content-Type>image/png</Content-Type><Last-Modified>Tue, 22 May 2012 20:07:10 GMT</Last-Modified><Age>371231</Age><X-Cache>HIT from amssq56.esams.wikimedia.org, HIT from amssq54.esams.wikimedia.org</X-Cache><X-Cache-Lookup>HIT from amssq56.esams.wikimedia.org:3128, HIT from amssq54.esams.wikimedia.org:80</X-Cache-Lookup><Connection>keep-alive</Connection></response></headers></item><item><type>image</type><url>http://upload.wikimedia.org/wikipedia/commons/thumb/a/a4/EM_of_influenza_virus.jpg/226px-EM_of_influenza_virus.jpg</url><size>16671</size><resp>1209</resp><headers><request><User-Agent>Mozilla/5.0 (Macintosh; Intel Mac OS X) AppleWebKit/534.34 (KHTML, like Gecko) PhantomJS/1.7.0 Safari/534.34</User-Agent><Referer>http://en.wikipedia.org/wiki/Influenza</Referer><Accept>*/*</Accept></request><response><Server>nginx/0.7.65</Server><Date>Mon, 15 Oct 2012 15:25:27 GMT</Date><Content-Type>image/jpeg</Content-Type><Content-Length>16671</Content-Length><Last-Modified>Fri, 17 Jul 2009 20:29:46 GMT</Last-Modified><Accept-Ranges>bytes</Accept-Ranges><Age>490152</Age><X-Cache>HIT from amssq56.esams.wikimedia.org, MISS from amssq54.esams.wikimedia.org</X-Cache><X-Cache-Lookup>HIT from amssq56.esams.wikimedia.org:3128, MISS from amssq54.esams.wikimedia.org:80</X-Cache-Lookup><Connection>keep-alive</Connection></response></headers></item><item><type>image</type><url>http://upload.wikimedia.org/wikipedia/commons/thumb/9/9e/Symptoms_of_influenza.svg/300px-Symptoms_of_influenza.svg.png</url><size>65488</size><resp>1222</resp><headers><request><User-Agent>Mozilla/5.0 (Macintosh; Intel Mac OS X) AppleWebKit/534.34 (KHTML, like Gecko) PhantomJS/1.7.0 Safari/534.34</User-Agent><Referer>http://en.wikipedia.org/wiki/Influenza</Referer><Accept>*/*</Accept></request><response><Last-Modified>Sun, 19 Feb 2012 18:43:06 GMT</Last-Modified><Accept-Ranges>bytes</Accept-Ranges><Content-Type>image/png</Content-Type><Content-Length>65488</Content-Length><Date>Mon, 04 Jun 2012 14:30:48 GMT</Date><Age>5187256</Age><X-Cache>HIT from sq52.wikimedia.org, HIT from amssq54.esams.wikimedia.org, MISS from amssq54.esams.wikimedia.org</X-Cache><X-Cache-Lookup>HIT from sq52.wikimedia.org:3128, HIT from amssq54.esams.wikimedia.org:3128, MISS from amssq54.esams.wikimedia.org:80</X-Cache-Lookup><Connection>keep-alive</Connection></response></headers></item><item><type>image</type><url>http://bits.wikimedia.org/static-1.21wmf1/skins/common/images/magnify-clip.png</url><size>204</size><resp>615</resp><expires>2012/11/11</expires><etag>"cc-4caff60e60080"</etag><headers><request><User-Agent>Mozilla/5.0 (Macintosh; Intel Mac OS X) AppleWebKit/534.34 (KHTML, like Gecko) PhantomJS/1.7.0 Safari/534.34</User-Agent><Referer>http://en.wikipedia.org/wiki/Influenza</Referer><Accept>*/*</Accept></request><response><Server>Apache</Server><Last-Modified>Mon, 01 Oct 2012 13:28:18 GMT</Last-Modified><ETag>"cc-4caff60e60080"</ETag><Cache-Control>max-age=2592000</Cache-Control><Expires>Sun, 11 Nov 2012 15:41:52 GMT</Expires><Access-Control-Allow-Origin>*</Access-Control-Allow-Origin><Content-Type>image/png</Content-Type><Content-Length>204</Content-Length><Accept-Ranges>bytes</Accept-Ranges><Date>Sun, 21 Oct 2012 07:34:39 GMT</Date><X-Varnish>2929674614 2191750055, 1533755850 1362706164</X-Varnish><Age>748367</Age><Via>1.1 varnish, 1.1 varnish</Via><Connection>keep-alive</Connection><X-Cache>cp3001 hit (2890188)</X-Cache></response></headers></item><item><type>image</type><url>http://upload.wikimedia.org/wikipedia/commons/thumb/3/3b/3D_Influenza_virus.png/300px-3D_Influenza_virus.png</url><size>63318</size><resp>1222</resp><etag>338dd29335b86d24de3f403a1b01a6bc</etag><headers><request><User-Agent>Mozilla/5.0 (Macintosh; Intel Mac OS X) AppleWebKit/534.34 (KHTML, like Gecko) PhantomJS/1.7.0 Safari/534.34</User-Agent><Referer>http://en.wikipedia.org/wiki/Influenza</Referer><Accept>*/*</Accept></request><response><Last-Modified>Thu, 19 Apr 2012 11:17:19 GMT</Last-Modified><ETag>338dd29335b86d24de3f403a1b01a6bc</ETag><X-Timestamp>1334834239.68948</X-Timestamp><Accept-Ranges>bytes</Accept-Ranges><Content-Length>63318</Content-Length><Content-Type>image/png</Content-Type><Date>Mon, 15 Oct 2012 20:55:44 GMT</Date><Age>470335</Age><X-Cache>HIT from sq52.wikimedia.org, HIT from amssq62.esams.wikimedia.org, MISS from amssq59.esams.wikimedia.org</X-Cache><X-Cache-Lookup>HIT from sq52.wikimedia.org:3128, HIT from amssq62.esams.wikimedia.org:3128, MISS from amssq59.esams.wikimedia.org:80</X-Cache-Lookup><Connection>keep-alive</Connection></response></headers></item><item><type>image</type><url>http://upload.wikimedia.org/wikipedia/commons/thumb/7/7a/Influenza_nomenclature.svg/300px-Influenza_nomenclature.svg.png</url><size>19364</size><resp>1209</resp><headers><request><User-Agent>Mozilla/5.0 (Macintosh; Intel Mac OS X) AppleWebKit/534.34 (KHTML, like Gecko) PhantomJS/1.7.0 Safari/534.34</User-Agent><Referer>http://en.wikipedia.org/wiki/Influenza</Referer><Accept>*/*</Accept></request><response><Server>nginx/0.7.65</Server><Date>Fri, 19 Oct 2012 23:38:44 GMT</Date><Content-Type>image/png</Content-Type><Content-Length>19364</Content-Length><Last-Modified>Sat, 18 Jul 2009 22:27:21 GMT</Last-Modified><Accept-Ranges>bytes</Accept-Ranges><Age>114955</Age><X-Cache>HIT from amssq50.esams.wikimedia.org, MISS from amssq48.esams.wikimedia.org</X-Cache><X-Cache-Lookup>HIT from amssq50.esams.wikimedia.org:3128, MISS from amssq48.esams.wikimedia.org:80</X-Cache-Lookup><Connection>keep-alive</Connection></response></headers></item><item><type>image</type><url>http://upload.wikimedia.org/wikipedia/commons/thumb/a/a0/Virus_Replication_large.svg/300px-Virus_Replication_large.svg.png</url><size>55077</size><resp>1224</resp><headers><request><User-Agent>Mozilla/5.0 (Macintosh; Intel Mac OS X) AppleWebKit/534.34 (KHTML, like Gecko) PhantomJS/1.7.0 Safari/534.34</User-Agent><Referer>http://en.wikipedia.org/wiki/Influenza</Referer><Accept>*/*</Accept></request><response><Server>nginx/0.7.65</Server><Date>Sat, 20 Oct 2012 20:37:15 GMT</Date><Content-Type>image/png</Content-Type><Content-Length>55077</Content-Length><Last-Modified>Sat, 18 Jul 2009 22:27:23 GMT</Last-Modified><Accept-Ranges>bytes</Accept-Ranges><Age>39444</Age><X-Cache>HIT from amssq53.esams.wikimedia.org, MISS from knsq16.knams.wikimedia.org</X-Cache><X-Cache-Lookup>HIT from amssq53.esams.wikimedia.org:3128, MISS from knsq16.knams.wikimedia.org:80</X-Cache-Lookup><Connection>keep-alive</Connection></response></headers></item><item><type>image</type><url>http://upload.wikimedia.org/wikipedia/commons/thumb/b/b0/H1N1_versus_H5N1_pathology.png/280px-H1N1_versus_H5N1_pathology.png</url><size>58644</size><resp>1223</resp><headers><request><User-Agent>Mozilla/5.0 (Macintosh; Intel Mac OS X) AppleWebKit/534.34 (KHTML, like Gecko) PhantomJS/1.7.0 Safari/534.34</User-Agent><Referer>http://en.wikipedia.org/wiki/Influenza</Referer><Accept>*/*</Accept></request><response><Server>nginx/0.7.65</Server><Date>Sat, 20 Oct 2012 20:14:13 GMT</Date><Content-Type>image/png</Content-Type><Content-Length>58644</Content-Length><Last-Modified>Tue, 24 Aug 2010 01:07:33 GMT</Last-Modified><Accept-Ranges>bytes</Accept-Ranges><Age>40826</Age><X-Cache>HIT from amssq60.esams.wikimedia.org, MISS from amssq51.esams.wikimedia.org</X-Cache><X-Cache-Lookup>HIT from amssq60.esams.wikimedia.org:3128, MISS from amssq51.esams.wikimedia.org:80</X-Cache-Lookup><Connection>keep-alive</Connection></response></headers></item><item><type>image</type><url>http://upload.wikimedia.org/wikipedia/commons/thumb/c/c2/Vaccination_US_Navy.jpg/220px-Vaccination_US_Navy.jpg</url><size>10140</size><resp>1211</resp><headers><request><User-Agent>Mozilla/5.0 (Macintosh; Intel Mac OS X) AppleWebKit/534.34 (KHTML, like Gecko) PhantomJS/1.7.0 Safari/534.34</User-Agent><Referer>http://en.wikipedia.org/wiki/Influenza</Referer><Accept>*/*</Accept></request><response><Server>nginx/0.7.65</Server><Date>Wed, 17 Oct 2012 17:51:07 GMT</Date><Content-Type>image/jpeg</Content-Type><Content-Length>10140</Content-Length><Last-Modified>Sun, 09 Nov 2008 17:31:29 GMT</Last-Modified><Accept-Ranges>bytes</Accept-Ranges><Age>308612</Age><X-Cache>HIT from amssq47.esams.wikimedia.org, MISS from amssq54.esams.wikimedia.org</X-Cache><X-Cache-Lookup>HIT from amssq47.esams.wikimedia.org:3128, MISS from amssq54.esams.wikimedia.org:80</X-Cache-Lookup><Connection>keep-alive</Connection></response></headers></item><item><type>image</type><url>http://upload.wikimedia.org/wikipedia/commons/thumb/3/30/Influenza_Seasonal_Risk_Areas.svg/300px-Influenza_Seasonal_Risk_Areas.svg.png</url><size>27710</size><resp>1224</resp><headers><request><User-Agent>Mozilla/5.0 (Macintosh; Intel Mac OS X) AppleWebKit/534.34 (KHTML, like Gecko) PhantomJS/1.7.0 Safari/534.34</User-Agent><Referer>http://en.wikipedia.org/wiki/Influenza</Referer><Accept>*/*</Accept></request><response><Server>nginx/0.7.65</Server><Date>Sat, 04 Aug 2012 11:17:08 GMT</Date><Content-Type>image/png</Content-Type><Content-Length>27710</Content-Length><Last-Modified>Sat, 10 Dec 2011 03:41:34 GMT</Last-Modified><Accept-Ranges>bytes</Accept-Ranges><Age>6725851</Age><X-Cache>HIT from amssq59.esams.wikimedia.org, MISS from amssq48.esams.wikimedia.org</X-Cache><X-Cache-Lookup>HIT from amssq59.esams.wikimedia.org:3128, MISS from amssq48.esams.wikimedia.org:80</X-Cache-Lookup><Connection>keep-alive</Connection></response></headers></item><item><type>image</type><url>http://upload.wikimedia.org/wikipedia/commons/thumb/c/ca/Antigenic_drift_vs_shift.png/220px-Antigenic_drift_vs_shift.png</url><size>25050</size><resp>1225</resp><headers><request><User-Agent>Mozilla/5.0 (Macintosh; Intel Mac OS X) AppleWebKit/534.34 (KHTML, like Gecko) PhantomJS/1.7.0 Safari/534.34</User-Agent><Referer>http://en.wikipedia.org/wiki/Influenza</Referer><Accept>*/*</Accept></request><response><Server>nginx/0.7.65</Server><Date>Mon, 15 Oct 2012 12:30:45 GMT</Date><Content-Type>image/png</Content-Type><Content-Length>25050</Content-Length><Last-Modified>Sat, 09 Apr 2011 23:17:41 GMT</Last-Modified><Accept-Ranges>bytes</Accept-Ranges><Age>500634</Age><X-Cache>HIT from amssq48.esams.wikimedia.org, MISS from amssq54.esams.wikimedia.org</X-Cache><X-Cache-Lookup>HIT from amssq48.esams.wikimedia.org:3128, MISS from amssq54.esams.wikimedia.org:80</X-Cache-Lookup><Connection>keep-alive</Connection></response></headers></item><item><type>image</type><url>http://upload.wikimedia.org/wikipedia/commons/thumb/d/d2/Influenza_geneticshift.svg/220px-Influenza_geneticshift.svg.png</url><size>37856</size><resp>1230</resp><headers><request><User-Agent>Mozilla/5.0 (Macintosh; Intel Mac OS X) AppleWebKit/534.34 (KHTML, like Gecko) PhantomJS/1.7.0 Safari/534.34</User-Agent><Referer>http://en.wikipedia.org/wiki/Influenza</Referer><Accept>*/*</Accept></request><response><Server>nginx/0.7.65</Server><Date>Fri, 19 Oct 2012 00:41:29 GMT</Date><Content-Type>image/png</Content-Type><Content-Length>37856</Content-Length><Last-Modified>Sun, 19 Aug 2012 17:13:03 GMT</Last-Modified><Accept-Ranges>bytes</Accept-Ranges><Age>197590</Age><X-Cache>HIT from amssq57.esams.wikimedia.org, MISS from amssq54.esams.wikimedia.org</X-Cache><X-Cache-Lookup>HIT from amssq57.esams.wikimedia.org:3128, MISS from amssq54.esams.wikimedia.org:80</X-Cache-Lookup><Connection>keep-alive</Connection></response></headers></item><item><type>image</type><url>http://upload.wikimedia.org/wikipedia/commons/thumb/4/4f/Ferguson_influenza_generation_time_distribution.png/220px-Ferguson_influenza_generation_time_distribution.png</url><size>6220</size><resp>1229</resp><headers><request><User-Agent>Mozilla/5.0 (Macintosh; Intel Mac OS X) AppleWebKit/534.34 (KHTML, like Gecko) PhantomJS/1.7.0 Safari/534.34</User-Agent><Referer>http://en.wikipedia.org/wiki/Influenza</Referer><Accept>*/*</Accept></request><response><Server>nginx/0.7.65</Server><Date>Sun, 21 Oct 2012 04:33:39 GMT</Date><Content-Type>image/png</Content-Type><Content-Length>6220</Content-Length><Accept-Ranges>bytes</Accept-Ranges><Age>10860</Age><X-Cache>HIT from amssq60.esams.wikimedia.org, MISS from amssq59.esams.wikimedia.org</X-Cache><X-Cache-Lookup>HIT from amssq60.esams.wikimedia.org:3128, MISS from amssq59.esams.wikimedia.org:80</X-Cache-Lookup><Connection>keep-alive</Connection></response></headers></item><item><type>image</type><url>http://upload.wikimedia.org/wikipedia/commons/thumb/7/70/W_curve.png/300px-W_curve.png</url><size>19369</size><resp>1227</resp><etag>e5db4a22a6fa3f7e6ee69adcacef8794</etag><headers><request><User-Agent>Mozilla/5.0 (Macintosh; Intel Mac OS X) AppleWebKit/534.34 (KHTML, like Gecko) PhantomJS/1.7.0 Safari/534.34</User-Agent><Referer>http://en.wikipedia.org/wiki/Influenza</Referer><Accept>*/*</Accept></request><response><Content-Type>image/png</Content-Type><Content-Length>19369</Content-Length><Last-Modified>Tue, 24 Apr 2012 12:30:41 GMT</Last-Modified><ETag>e5db4a22a6fa3f7e6ee69adcacef8794</ETag><X-Timestamp>1335270641.13886</X-Timestamp><Accept-Ranges>bytes</Accept-Ranges><Date>Sat, 29 Sep 2012 11:08:29 GMT</Date><Age>1887970</Age><X-Cache>HIT from sq42.wikimedia.org, HIT from amssq48.esams.wikimedia.org, MISS from amssq51.esams.wikimedia.org</X-Cache><X-Cache-Lookup>HIT from sq42.wikimedia.org:3128, HIT from amssq48.esams.wikimedia.org:3128, MISS from amssq51.esams.wikimedia.org:80</X-Cache-Lookup><Connection>keep-alive</Connection></response></headers></item><item><type>image</type><url>http://upload.wikimedia.org/wikipedia/commons/thumb/b/b8/Influenza_subtypes.svg/350px-Influenza_subtypes.svg.png</url><size>13817</size><resp>1228</resp><headers><request><User-Agent>Mozilla/5.0 (Macintosh; Intel Mac OS X) AppleWebKit/534.34 (KHTML, like Gecko) PhantomJS/1.7.0 Safari/534.34</User-Agent><Referer>http://en.wikipedia.org/wiki/Influenza</Referer><Accept>*/*</Accept></request><response><Server>nginx/0.7.65</Server><Date>Sat, 20 Oct 2012 20:37:15 GMT</Date><Content-Type>image/png</Content-Type><Content-Length>13817</Content-Length><Last-Modified>Thu, 30 Apr 2009 21:24:55 GMT</Last-Modified><Accept-Ranges>bytes</Accept-Ranges><Age>39444</Age><X-Cache>HIT from amssq53.esams.wikimedia.org, MISS from amssq48.esams.wikimedia.org</X-Cache><X-Cache-Lookup>HIT from amssq53.esams.wikimedia.org:3128, MISS from amssq48.esams.wikimedia.org:80</X-Cache-Lookup><Connection>keep-alive</Connection></response></headers></item><item><type>image</type><url>http://upload.wikimedia.org/wikipedia/commons/thumb/8/86/Influenza_virus_research.jpg/170px-Influenza_virus_research.jpg</url><size>15284</size><resp>1228</resp><etag>6e88c246e909384037231ae88825d1bf</etag><headers><request><User-Agent>Mozilla/5.0 (Macintosh; Intel Mac OS X) AppleWebKit/534.34 (KHTML, like Gecko) PhantomJS/1.7.0 Safari/534.34</User-Agent><Referer>http://en.wikipedia.org/wiki/Influenza</Referer><Accept>*/*</Accept></request><response><Last-Modified>Thu, 23 Feb 2012 05:17:15 GMT</Last-Modified><ETag>6e88c246e909384037231ae88825d1bf</ETag><X-Timestamp>1329974235.97197</X-Timestamp><Accept-Ranges>bytes</Accept-Ranges><Content-Length>15284</Content-Length><Content-Type>image/jpeg</Content-Type><Date>Tue, 16 Oct 2012 10:51:49 GMT</Date><Age>420170</Age><X-Cache>HIT from sq57.wikimedia.org, HIT from amssq54.esams.wikimedia.org, MISS from knsq16.knams.wikimedia.org</X-Cache><X-Cache-Lookup>HIT from sq57.wikimedia.org:3128, HIT from amssq54.esams.wikimedia.org:3128, MISS from knsq16.knams.wikimedia.org:80</X-Cache-Lookup><Connection>keep-alive</Connection></response></headers></item><item><type>image</type><url>http://upload.wikimedia.org/wikipedia/commons/thumb/0/0d/Colorized_transmission_electron_micrograph_of_Avian_influenza_A_H5N1_viruses.jpg/138px-Colorized_transmission_electron_micrograph_of_Avian_influenza_A_H5N1_viruses.jpg</url><size>10971</size><resp>1230</resp><headers><request><User-Agent>Mozilla/5.0 (Macintosh; Intel Mac OS X) AppleWebKit/534.34 (KHTML, like Gecko) PhantomJS/1.7.0 Safari/534.34</User-Agent><Referer>http://en.wikipedia.org/wiki/Influenza</Referer><Accept>*/*</Accept></request><response><Server>nginx/0.7.65</Server><Date>Mon, 15 Oct 2012 12:17:00 GMT</Date><Content-Type>image/jpeg</Content-Type><Content-Length>10971</Content-Length><Last-Modified>Wed, 24 Nov 2010 19:52:32 GMT</Last-Modified><Accept-Ranges>bytes</Accept-Ranges><Age>501459</Age><X-Cache>HIT from amssq52.esams.wikimedia.org, MISS from amssq54.esams.wikimedia.org</X-Cache><X-Cache-Lookup>HIT from amssq52.esams.wikimedia.org:3128, MISS from amssq54.esams.wikimedia.org:80</X-Cache-Lookup><Connection>keep-alive</Connection></response></headers></item><item><type>image</type><url>http://upload.wikimedia.org/wikipedia/commons/thumb/6/6d/ChineseFluInspectors.JPG/170px-ChineseFluInspectors.JPG</url><size>9114</size><resp>1231</resp><headers><request><User-Agent>Mozilla/5.0 (Macintosh; Intel Mac OS X) AppleWebKit/534.34 (KHTML, like Gecko) PhantomJS/1.7.0 Safari/534.34</User-Agent><Referer>http://en.wikipedia.org/wiki/Influenza</Referer><Accept>*/*</Accept></request><response><Server>nginx/0.7.65</Server><Date>Sun, 21 Oct 2012 04:33:39 GMT</Date><Content-Type>image/jpeg</Content-Type><Content-Length>9114</Content-Length><Accept-Ranges>bytes</Accept-Ranges><Age>10860</Age><X-Cache>HIT from amssq49.esams.wikimedia.org, MISS from amssq51.esams.wikimedia.org</X-Cache><X-Cache-Lookup>HIT from amssq49.esams.wikimedia.org:3128, MISS from amssq51.esams.wikimedia.org:80</X-Cache-Lookup><Connection>keep-alive</Connection></response></headers></item><item><type>image</type><url>http://upload.wikimedia.org/wikipedia/commons/thumb/f/f8/Wiktionary-logo-en.svg/23px-Wiktionary-logo-en.svg.png</url><size>1061</size><resp>1233</resp><headers><request><User-Agent>Mozilla/5.0 (Macintosh; Intel Mac OS X) AppleWebKit/534.34 (KHTML, like Gecko) PhantomJS/1.7.0 Safari/534.34</User-Agent><Referer>http://en.wikipedia.org/wiki/Influenza</Referer><Accept>*/*</Accept></request><response><Server>nginx/0.7.65</Server><Content-Length>1061</Content-Length><Accept-Ranges>bytes</Accept-Ranges><Date>Tue, 16 Oct 2012 02:31:59 GMT</Date><Content-Type>image/png</Content-Type><Last-Modified>Sun, 03 Apr 2011 16:21:52 GMT</Last-Modified><Age>450160</Age><X-Cache>HIT from knsq22.knams.wikimedia.org, HIT from knsq16.knams.wikimedia.org</X-Cache><X-Cache-Lookup>HIT from knsq22.knams.wikimedia.org:3128, HIT from knsq16.knams.wikimedia.org:80</X-Cache-Lookup><Connection>keep-alive</Connection></response></headers></item><item><type>image</type><url>http://upload.wikimedia.org/wikipedia/en/thumb/4/4a/Commons-logo.svg/18px-Commons-logo.svg.png</url><size>870</size><resp>1249</resp><etag>2c525828521cd4a8bec25eb72c7e8544</etag><headers><request><User-Agent>Mozilla/5.0 (Macintosh; Intel Mac OS X) AppleWebKit/534.34 (KHTML, like Gecko) PhantomJS/1.7.0 Safari/534.34</User-Agent><Referer>http://en.wikipedia.org/wiki/Influenza</Referer><Accept>*/*</Accept></request><response><X-Object-Meta-Sha1base36>qwotmdgxno6v6igwp8a5p1s6r9paujr</X-Object-Meta-Sha1base36><Content-Disposition>inline;filename*=UTF-8''Commons-logo.svg.png</Content-Disposition><X-Timestamp>1349914752.83665</X-Timestamp><Accept-Ranges>bytes</Accept-Ranges><Content-Length>870</Content-Length><Date>Thu, 18 Oct 2012 00:06:09 GMT</Date><Content-Type>image/png</Content-Type><Last-Modified>Thu, 11 Oct 2012 00:19:12 GMT</Last-Modified><ETag>2c525828521cd4a8bec25eb72c7e8544</ETag><Age>286110</Age><X-Cache>HIT from amssq62.esams.wikimedia.org, HIT from amssq48.esams.wikimedia.org</X-Cache><X-Cache-Lookup>HIT from amssq62.esams.wikimedia.org:3128, HIT from amssq48.esams.wikimedia.org:80</X-Cache-Lookup><Connection>keep-alive</Connection></response></headers></item><item><type>image</type><url>http://upload.wikimedia.org/wikipedia/commons/thumb/1/1b/Wikiversity-logo-en.svg/25px-Wikiversity-logo-en.svg.png</url><size>1032</size><resp>1254</resp><etag>a078bfb075ea27364cfc2840cf670890</etag><headers><request><User-Agent>Mozilla/5.0 (Macintosh; Intel Mac OS X) AppleWebKit/534.34 (KHTML, like Gecko) PhantomJS/1.7.0 Safari/534.34</User-Agent><Referer>http://en.wikipedia.org/wiki/Influenza</Referer><Accept>*/*</Accept></request><response><X-Object-Meta-Sha1base36>aeqyllwaxkp7l2kjgvqub5k4tq7w8tx</X-Object-Meta-Sha1base36><Content-Disposition>inline;filename*=UTF-8''Wikiversity-logo-en.svg.png</Content-Disposition><X-Timestamp>1347440155.36819</X-Timestamp><Accept-Ranges>bytes</Accept-Ranges><Content-Length>1032</Content-Length><Date>Sat, 20 Oct 2012 18:42:08 GMT</Date><Content-Type>image/png</Content-Type><Last-Modified>Wed, 12 Sep 2012 08:55:55 GMT</Last-Modified><ETag>a078bfb075ea27364cfc2840cf670890</ETag><Age>46351</Age><X-Cache>HIT from amssq49.esams.wikimedia.org, HIT from amssq59.esams.wikimedia.org</X-Cache><X-Cache-Lookup>HIT from amssq49.esams.wikimedia.org:3128, HIT from amssq59.esams.wikimedia.org:80</X-Cache-Lookup><Connection>keep-alive</Connection></response></headers></item><item><type>image</type><url>http://upload.wikimedia.org/wikipedia/commons/thumb/2/24/Wikinews-logo.svg/25px-Wikinews-logo.svg.png</url><size>995</size><resp>1254</resp><etag>75b266d47bbbf7647cc3026d1189db25</etag><headers><request><User-Agent>Mozilla/5.0 (Macintosh; Intel Mac OS X) AppleWebKit/534.34 (KHTML, like Gecko) PhantomJS/1.7.0 Safari/534.34</User-Agent><Referer>http://en.wikipedia.org/wiki/Influenza</Referer><Accept>*/*</Accept></request><response><X-Object-Meta-Sha1base36>iunwmw5j3cgdeitnntfjdumr9kht9vt</X-Object-Meta-Sha1base36><Content-Disposition>inline;filename*=UTF-8''Wikinews-logo.svg.png</Content-Disposition><X-Timestamp>1350362920.56095</X-Timestamp><Accept-Ranges>bytes</Accept-Ranges><Content-Length>995</Content-Length><Server>nginx/0.7.65</Server><Date>Sat, 20 Oct 2012 02:03:52 GMT</Date><Content-Type>image/png</Content-Type><Last-Modified>Tue, 16 Oct 2012 04:48:40 GMT</Last-Modified><ETag>75b266d47bbbf7647cc3026d1189db25</ETag><Age>106247</Age><X-Cache>HIT from knsq22.knams.wikimedia.org, HIT from amssq54.esams.wikimedia.org</X-Cache><X-Cache-Lookup>HIT from knsq22.knams.wikimedia.org:3128, HIT from amssq54.esams.wikimedia.org:80</X-Cache-Lookup><Connection>keep-alive</Connection></response></headers></item><item><type>image</type><url>http://upload.wikimedia.org/wikipedia/commons/thumb/f/fa/Wikiquote-logo.svg/21px-Wikiquote-logo.svg.png</url><size>1081</size><resp>1256</resp><etag>8697f37af88573ae62d950a17020ff3a</etag><headers><request><User-Agent>Mozilla/5.0 (Macintosh; Intel Mac OS X) AppleWebKit/534.34 (KHTML, like Gecko) PhantomJS/1.7.0 Safari/534.34</User-Agent><Referer>http://en.wikipedia.org/wiki/Influenza</Referer><Accept>*/*</Accept></request><response><Content-Length>1081</Content-Length><X-Object-Meta-Sha1base36>9w9wcr9vy3mbmb6mzcatz75e39kc7tj</X-Object-Meta-Sha1base36><Content-Disposition>inline;filename*=UTF-8''Wikiquote-logo.svg.png</Content-Disposition><X-Timestamp>1350363074.99414</X-Timestamp><Accept-Ranges>bytes</Accept-Ranges><Date>Sat, 20 Oct 2012 02:06:32 GMT</Date><Content-Type>image/png</Content-Type><Last-Modified>Tue, 16 Oct 2012 04:51:14 GMT</Last-Modified><ETag>8697f37af88573ae62d950a17020ff3a</ETag><Age>106087</Age><X-Cache>HIT from amssq52.esams.wikimedia.org, HIT from amssq54.esams.wikimedia.org</X-Cache><X-Cache-Lookup>HIT from amssq52.esams.wikimedia.org:3128, HIT from amssq54.esams.wikimedia.org:80</X-Cache-Lookup><Connection>keep-alive</Connection></response></headers></item><item><type>image</type><url>http://upload.wikimedia.org/wikipedia/commons/thumb/4/4c/Wikisource-logo.svg/24px-Wikisource-logo.svg.png</url><size>1364</size><resp>1257</resp><etag>94b0c7aaab734b4f5c4eb9ae284be615</etag><headers><request><User-Agent>Mozilla/5.0 (Macintosh; Intel Mac OS X) AppleWebKit/534.34 (KHTML, like Gecko) PhantomJS/1.7.0 Safari/534.34</User-Agent><Referer>http://en.wikipedia.org/wiki/Influenza</Referer><Accept>*/*</Accept></request><response><Content-Length>1364</Content-Length><X-Object-Meta-Sha1base36>odsq2jcvrbtxk6n7w8baudo2ihgcqea</X-Object-Meta-Sha1base36><Content-Disposition>inline;filename*=UTF-8''Wikisource-logo.svg.png</Content-Disposition><X-Timestamp>1350680212.95316</X-Timestamp><Accept-Ranges>bytes</Accept-Ranges><Server>nginx/0.7.65</Server><Date>Sun, 21 Oct 2012 01:43:50 GMT</Date><Content-Type>image/png</Content-Type><Last-Modified>Fri, 19 Oct 2012 20:56:52 GMT</Last-Modified><ETag>94b0c7aaab734b4f5c4eb9ae284be615</ETag><Age>21049</Age><X-Cache>HIT from amssq57.esams.wikimedia.org, HIT from amssq51.esams.wikimedia.org</X-Cache><X-Cache-Lookup>HIT from amssq57.esams.wikimedia.org:3128, HIT from amssq51.esams.wikimedia.org:80</X-Cache-Lookup><Connection>keep-alive</Connection></response></headers></item><item><type>image</type><url>http://upload.wikimedia.org/wikipedia/commons/thumb/f/fa/Wikibooks-logo.svg/25px-Wikibooks-logo.svg.png</url><size>1442</size><resp>1256</resp><etag>1e96b9f648c7037847f10763bdb5fd30</etag><headers><request><User-Agent>Mozilla/5.0 (Macintosh; Intel Mac OS X) AppleWebKit/534.34 (KHTML, like Gecko) PhantomJS/1.7.0 Safari/534.34</User-Agent><Referer>http://en.wikipedia.org/wiki/Influenza</Referer><Accept>*/*</Accept></request><response><Content-Length>1442</Content-Length><X-Object-Meta-Sha1base36>p5dqtnrnxxwefvib3zn39dm5ukly4z1</X-Object-Meta-Sha1base36><Content-Disposition>inline;filename*=UTF-8''Wikibooks-logo.svg.png</Content-Disposition><X-Timestamp>1350380401.59263</X-Timestamp><Accept-Ranges>bytes</Accept-Ranges><Server>nginx/0.7.65</Server><Date>Sat, 20 Oct 2012 06:55:13 GMT</Date><Content-Type>image/png</Content-Type><Last-Modified>Tue, 16 Oct 2012 09:40:01 GMT</Last-Modified><ETag>1e96b9f648c7037847f10763bdb5fd30</ETag><Age>88766</Age><X-Cache>HIT from amssq50.esams.wikimedia.org, HIT from knsq16.knams.wikimedia.org</X-Cache><X-Cache-Lookup>HIT from amssq50.esams.wikimedia.org:3128, HIT from knsq16.knams.wikimedia.org:80</X-Cache-Lookup><Connection>keep-alive</Connection></response></headers></item><item><type>image</type><url>http://upload.wikimedia.org/wikipedia/en/thumb/e/e7/Cscr-featured.svg/15px-Cscr-featured.svg.png</url><size>662</size><resp>1257</resp><etag>34a31adcdd562fe19e9ec15a0b40fb27</etag><headers><request><User-Agent>Mozilla/5.0 (Macintosh; Intel Mac OS X) AppleWebKit/534.34 (KHTML, like Gecko) PhantomJS/1.7.0 Safari/534.34</User-Agent><Referer>http://en.wikipedia.org/wiki/Influenza</Referer><Accept>*/*</Accept></request><response><X-Object-Meta-Sha1base36>gw2ynqoya3jhkzjlnrcjawd7adydzkv</X-Object-Meta-Sha1base36><Content-Disposition>inline;filename*=UTF-8''Cscr-featured.svg.png</Content-Disposition><X-Timestamp>1349922770.62209</X-Timestamp><Accept-Ranges>bytes</Accept-Ranges><Content-Length>662</Content-Length><Date>Fri, 19 Oct 2012 20:29:14 GMT</Date><Content-Type>image/png</Content-Type><Last-Modified>Thu, 11 Oct 2012 02:32:50 GMT</Last-Modified><ETag>34a31adcdd562fe19e9ec15a0b40fb27</ETag><Age>126325</Age><X-Cache>HIT from amssq53.esams.wikimedia.org, HIT from amssq48.esams.wikimedia.org</X-Cache><X-Cache-Lookup>HIT from amssq53.esams.wikimedia.org:3128, HIT from amssq48.esams.wikimedia.org:80</X-Cache-Lookup><Connection>keep-alive</Connection></response></headers></item><item><type>image</type><url>http://bits.wikimedia.org/static-1.21wmf1/skins/vector/images/search-ltr.png?303-4</url><size>214</size><resp>616</resp><expires>2012/11/9</expires><etag>"d6-4caff60e60080"</etag><headers><request><User-Agent>Mozilla/5.0 (Macintosh; Intel Mac OS X) AppleWebKit/534.34 (KHTML, like Gecko) PhantomJS/1.7.0 Safari/534.34</User-Agent><Referer>http://en.wikipedia.org/wiki/Influenza</Referer><Accept>*/*</Accept></request><response><Server>Apache</Server><Last-Modified>Mon, 01 Oct 2012 13:28:18 GMT</Last-Modified><ETag>"d6-4caff60e60080"</ETag><Cache-Control>max-age=2592000</Cache-Control><Expires>Fri, 09 Nov 2012 19:07:38 GMT</Expires><Access-Control-Allow-Origin>*</Access-Control-Allow-Origin><Content-Type>image/png</Content-Type><Content-Length>214</Content-Length><Accept-Ranges>bytes</Accept-Ranges><Date>Sun, 21 Oct 2012 07:34:39 GMT</Date><X-Varnish>2223219434 1472904339, 787464310 664764460</X-Varnish><Age>908821</Age><Via>1.1 varnish, 1.1 varnish</Via><Connection>keep-alive</Connection><X-Cache>cp3002 hit (2948158)</X-Cache></response></headers></item><item><type>image</type><url>http://bits.wikimedia.org/images/wikimedia-button.png</url><size>2426</size><resp>616</resp><etag>"97a-494505e0c46c0"</etag><headers><request><User-Agent>Mozilla/5.0 (Macintosh; Intel Mac OS X) AppleWebKit/534.34 (KHTML, like Gecko) PhantomJS/1.7.0 Safari/534.34</User-Agent><Referer>http://en.wikipedia.org/wiki/Influenza</Referer><Accept>*/*</Accept></request><response><Server>Apache</Server><Last-Modified>Fri, 05 Nov 2010 16:00:03 GMT</Last-Modified><ETag>"97a-494505e0c46c0"</ETag><Content-Type>image/png</Content-Type><Content-Length>2426</Content-Length><Accept-Ranges>bytes</Accept-Ranges><Date>Sun, 21 Oct 2012 07:34:39 GMT</Date><X-Varnish>2929998664 2929998483, 1533755920 1533271821</X-Varnish><Age>131</Age><Via>1.1 varnish, 1.1 varnish</Via><Connection>keep-alive</Connection><X-Cache>cp3001 hit (14695)</X-Cache></response></headers></item><item><type>image</type><url>http://bits.wikimedia.org/static-1.21wmf1/skins/common/images/poweredby_mediawiki_88x31.png</url><size>3525</size><resp>1200</resp><expires>2012/11/9</expires><etag>"dc5-4caff60e60080"</etag><headers><request><User-Agent>Mozilla/5.0 (Macintosh; Intel Mac OS X) AppleWebKit/534.34 (KHTML, like Gecko) PhantomJS/1.7.0 Safari/534.34</User-Agent><Referer>http://en.wikipedia.org/wiki/Influenza</Referer><Accept>*/*</Accept></request><response><Server>Apache</Server><Last-Modified>Mon, 01 Oct 2012 13:28:18 GMT</Last-Modified><ETag>"dc5-4caff60e60080"</ETag><Cache-Control>max-age=2592000</Cache-Control><Expires>Fri, 09 Nov 2012 18:35:35 GMT</Expires><Access-Control-Allow-Origin>*</Access-Control-Allow-Origin><Content-Type>image/png</Content-Type><Content-Length>3525</Content-Length><Accept-Ranges>bytes</Accept-Ranges><Date>Sun, 21 Oct 2012 07:34:39 GMT</Date><X-Varnish>2223159153 1472880494, 1533756078 1362706096</X-Varnish><Age>910744</Age><Via>1.1 varnish, 1.1 varnish</Via><Connection>keep-alive</Connection><X-Cache>cp3001 hit (4194551)</X-Cache></response></headers></item><item><type>favicon</type><url>http://en.wikipedia.org/favicon.ico</url><size>0</size><resp>null</resp><headers><response></response></headers></item></comps></results>
