<?xml version="1.0" encoding="UTF-8"?><results filename="11"><w>303772</w><o>95</o><u><![CDATA[http://www.amazon.com/gp/help/customer/display.html/ref=footer_shiprates?ie=UTF8&nodeId=468520]]></u><r>16</r><i>sitespeed.io</i><lt>1034</lt><g><ynumreq><score>76</score><message>This page has 5 external stylesheets.  Try combining them into one.
This page has 6 external background images.  Try combining them with CSS sprites.</message><components></components></ynumreq><yemptysrc><score>100</score><message></message><components></components></yemptysrc><ycompress><score>100</score><message></message><components></components></ycompress><ycsstop><score>100</score><message></message><components></components></ycsstop><yjsbottom><score>100</score><message></message><components></components></yjsbottom><yexpressions><score>100</score><message></message><components></components></yexpressions><yexternal><message>Only consider this if your property is a common user home page.</message><components><item>There is a total of 7 inline css</item><item>There is a total of 16 inline scripts</item></components></yexternal><ydns><score>100</score><message></message><components><item>www.amazon.com: 2 components, 104.0K (72.5K GZip)</item><item>z-ecx.images-amazon.com: 7 components, 411.9K (155.4K GZip)</item><item>g-ecx.images-amazon.com: 6 components, 32.3K</item><item>ecx.images-amazon.com: 1 component, 0.04K</item></components></ydns><yminify><score>50</score><message>There are 5 components that can be minified</message><components><item><![CDATA[inline &lt;style&gt; tag #5]]></item><item><![CDATA[inline &lt;script&gt; tag #4]]></item><item><![CDATA[inline &lt;script&gt; tag #7]]></item><item><![CDATA[inline &lt;script&gt; tag #8]]></item><item><![CDATA[inline &lt;script&gt; tag #15]]></item></components></yminify><yredirects><score>100</score><message></message><components></components></yredirects><ydupes><score>100</score><message></message><components></components></ydupes><yetags><score>100</score><message></message><components></components></yetags><yxhr><score>100</score><message></message><components></components></yxhr><yxhrmethod><score>100</score><message></message><components></components></yxhrmethod><ymindom><score>79</score><message>There are 1247 DOM elements on the page</message><components></components></ymindom><yno404><score>100</score><message></message><components></components></yno404><ymincookie><score>100</score><message></message><components></components></ymincookie><ycookiefree><score>100</score><message></message><components></components></ycookiefree><ynofilter><score>100</score><message></message><components></components></ynofilter><yimgnoscale><score>100</score><message></message><components></components></yimgnoscale><_3po_asyncjs><score>100</score><message></message><components></components></_3po_asyncjs><_3po_jsonce><score>100</score><message></message><components></components></_3po_jsonce><cssprint><score>100</score><message></message><components></components></cssprint><cssinheaddomain><score>90</score><message>The following 5 css are loaded from a different domain inside head, causing DNS lookups before page is rendered. Unique DNS in head that decreases the score:1.</message><components><item>http://z-ecx.images-amazon.com/images/G/01/nav2/gamma/websiteGlobalCSS/websiteGlobalCSS-websiteGlobal-10346._V1_.css</item><item>http://z-ecx.images-amazon.com/images/G/01/browser-scripts/fruitCSS/US-combined-3926343938._V146284167_.css</item><item>http://z-ecx.images-amazon.com/images/G/01/browser-scripts/us-site-wide-css-beacon/site-wide-9037275515._V1_.css</item><item>http://z-ecx.images-amazon.com/images/G/01/browser-scripts/wcs-css-buttons/wcs-css-buttons-3112498172._V1_.css</item><item>http://z-ecx.images-amazon.com/images/G/01/browser-scripts/wcs-help-base/wcs-help-base-1289191008._V1_.css</item></components></cssinheaddomain><syncjsinhead><score>100</score><message></message><components></components></syncjsinhead><avoidfont><score>100</score><message></message><components></components></avoidfont><totalrequests><score>100</score><message></message></totalrequests><expiresmod><score>78</score><message>There are 2 static components without a far-future expiration date.</message><components><item>http://z-ecx.images-amazon.com/images/G/01/x-locale/cs/css/images/amznbtn-sprite03.png</item><item>http://g-ecx.images-amazon.com/images/G/01/marketing/prime/ev/Sprite_Nav._V389709824_.png</item></components></expiresmod><spof><score>100</score><message></message><components></components></spof></g><w_c>72502</w_c><r_c>4</r_c><stats><doc><r>1</r><w>72502</w></doc><css><r>5</r><w>96823</w></css><js><r>1</r><w>58622</w></js><cssimage><r>6</r><w>74566</w></cssimage><image><r>2</r><w>1259</w></image><favicon><r>1</r><w>0</w></favicon></stats><stats_c><doc><r>1</r><w>72502</w></doc><cssimage><r>2</r><w>0</w></cssimage><favicon><r>1</r><w>0</w></favicon></stats_c><comps><item><type>doc</type><url><![CDATA[http://www.amazon.com/gp/help/customer/display.html/ref=footer_shiprates?ie=UTF8&nodeId=468520]]></url><size>104060</size><resp>874</resp><gzip>72502</gzip><cr>191</cr><cs>191</cs><headers><request><User-Agent>Mozilla/5.0 (Macintosh; Intel Mac OS X) AppleWebKit/534.34 (KHTML, like Gecko) PhantomJS/1.7.0 Safari/534.34</User-Agent><Accept>text/html,application/xhtml+xml,application/xml;q=0.9,*/*;q=0.8</Accept></request><response><Date>Sun, 21 Oct 2012 11:29:04 GMT</Date><Server>Server</Server><X-Amz-Id-1>1CRKF8CKNN167RQKWS5Q</X-Amz-Id-1><P3P>policyref="http://www.amazon.com/w3c/p3p.xml",CP="CAO DSP LAW CUR ADM IVAo IVDo CONo OTPo OUR DELi PUBi OTRi BUS PHY ONL UNI PUR FIN COM NAV INT DEM CNT STA HEA PRE LOC GOV OTC "</P3P><X-Amz-Id-2>pWlyai1JsHhW9M7/lfgUABQeteYG5ylRRxYik6BJ7eMZT7BrcvdM/Ng93/esdQFy</X-Amz-Id-2><Vary>Accept-Encoding,User-Agent</Vary><Content-Encoding>gzip</Content-Encoding><Content-Type>text/html; charset=ISO-8859-1</Content-Type><Set-Cookie>session-id-time=2082787201l; path=/; domain=.amazon.com; expires=Tue, 01-Jan-2036 08:00:01 GMT
session-id=000-0000000-0000000; path=/; domain=.amazon.com; expires=Tue, 01-Jan-2036 08:00:01 GMT</Set-Cookie><Transfer-Encoding>chunked</Transfer-Encoding></response></headers></item><item><type>css</type><url>http://z-ecx.images-amazon.com/images/G/01/nav2/gamma/websiteGlobalCSS/websiteGlobalCSS-websiteGlobal-10346._V1_.css</url><size>14270</size><resp>761</resp><gzip>14270</gzip><expires>2032/8/11</expires><headers><request><User-Agent>Mozilla/5.0 (Macintosh; Intel Mac OS X) AppleWebKit/534.34 (KHTML, like Gecko) PhantomJS/1.7.0 Safari/534.34</User-Agent><Accept>text/css,*/*;q=0.1</Accept><Referer><![CDATA[http://www.amazon.com/gp/help/customer/display.html/ref=footer_shiprates?ie=UTF8&nodeId=468520]]></Referer></request><response><Server>Server</Server><Last-Modified>Fri, 25 Jun 2010 18:22:49 GMT</Last-Modified><Content-Type>text/css</Content-Type><Vary>Accept-Encoding</Vary><Content-Encoding>gzip</Content-Encoding><Cache-Control>public, max-age=625008708</Cache-Control><Expires>Wed, 11 Aug 2032 09:00:53 GMT</Expires><Date>Sun, 21 Oct 2012 11:29:05 GMT</Date><Connection>keep-alive</Connection></response></headers></item><item><type>css</type><url>http://z-ecx.images-amazon.com/images/G/01/browser-scripts/fruitCSS/US-combined-3926343938._V146284167_.css</url><size>13519</size><resp>763</resp><gzip>13519</gzip><expires>2032/6/4</expires><headers><request><User-Agent>Mozilla/5.0 (Macintosh; Intel Mac OS X) AppleWebKit/534.34 (KHTML, like Gecko) PhantomJS/1.7.0 Safari/534.34</User-Agent><Accept>text/css,*/*;q=0.1</Accept><Referer><![CDATA[http://www.amazon.com/gp/help/customer/display.html/ref=footer_shiprates?ie=UTF8&nodeId=468520]]></Referer></request><response><Server>Server</Server><Last-Modified>Sat, 02 Jun 2012 17:24:51 GMT</Last-Modified><Content-Type>text/css</Content-Type><Vary>Accept-Encoding</Vary><Content-Encoding>gzip</Content-Encoding><Cache-Control>public, max-age=619102498</Cache-Control><Expires>Fri, 04 Jun 2032 00:24:03 GMT</Expires><Date>Sun, 21 Oct 2012 11:29:05 GMT</Date><Connection>keep-alive</Connection></response></headers></item><item><type>css</type><url>http://z-ecx.images-amazon.com/images/G/01/browser-scripts/us-site-wide-css-beacon/site-wide-9037275515._V1_.css</url><size>36378</size><resp>770</resp><gzip>36378</gzip><expires>2032/10/11</expires><headers><request><User-Agent>Mozilla/5.0 (Macintosh; Intel Mac OS X) AppleWebKit/534.34 (KHTML, like Gecko) PhantomJS/1.7.0 Safari/534.34</User-Agent><Accept>text/css,*/*;q=0.1</Accept><Referer><![CDATA[http://www.amazon.com/gp/help/customer/display.html/ref=footer_shiprates?ie=UTF8&nodeId=468520]]></Referer></request><response><Server>Server</Server><Last-Modified>Fri, 12 Oct 2012 00:26:38 GMT</Last-Modified><Content-Type>text/css</Content-Type><Vary>Accept-Encoding</Vary><Content-Encoding>gzip</Content-Encoding><Cache-Control>public, max-age=630267340</Cache-Control><Expires>Mon, 11 Oct 2032 05:44:45 GMT</Expires><Date>Sun, 21 Oct 2012 11:29:05 GMT</Date><Connection>keep-alive</Connection></response></headers></item><item><type>css</type><url>http://z-ecx.images-amazon.com/images/G/01/browser-scripts/wcs-css-buttons/wcs-css-buttons-3112498172._V1_.css</url><size>17238</size><resp>766</resp><gzip>17238</gzip><expires>2032/5/19</expires><headers><request><User-Agent>Mozilla/5.0 (Macintosh; Intel Mac OS X) AppleWebKit/534.34 (KHTML, like Gecko) PhantomJS/1.7.0 Safari/534.34</User-Agent><Accept>text/css,*/*;q=0.1</Accept><Referer><![CDATA[http://www.amazon.com/gp/help/customer/display.html/ref=footer_shiprates?ie=UTF8&nodeId=468520]]></Referer></request><response><Server>Server</Server><Last-Modified>Tue, 22 May 2012 23:19:34 GMT</Last-Modified><Content-Type>text/css</Content-Type><Vary>Accept-Encoding</Vary><Content-Encoding>gzip</Content-Encoding><Cache-Control>public, max-age=617733025</Cache-Control><Expires>Wed, 19 May 2032 03:59:30 GMT</Expires><Date>Sun, 21 Oct 2012 11:29:05 GMT</Date><Connection>keep-alive</Connection></response></headers></item><item><type>css</type><url>http://z-ecx.images-amazon.com/images/G/01/browser-scripts/wcs-help-base/wcs-help-base-1289191008._V1_.css</url><size>15418</size><resp>768</resp><gzip>15418</gzip><expires>2032/6/9</expires><headers><request><User-Agent>Mozilla/5.0 (Macintosh; Intel Mac OS X) AppleWebKit/534.34 (KHTML, like Gecko) PhantomJS/1.7.0 Safari/534.34</User-Agent><Accept>text/css,*/*;q=0.1</Accept><Referer><![CDATA[http://www.amazon.com/gp/help/customer/display.html/ref=footer_shiprates?ie=UTF8&nodeId=468520]]></Referer></request><response><Server>Server</Server><Last-Modified>Wed, 06 Jun 2012 23:53:26 GMT</Last-Modified><Content-Type>text/css</Content-Type><Vary>Accept-Encoding</Vary><Content-Encoding>gzip</Content-Encoding><Cache-Control>public, max-age=619600520</Cache-Control><Expires>Wed, 09 Jun 2032 18:44:25 GMT</Expires><Date>Sun, 21 Oct 2012 11:29:05 GMT</Date><Connection>keep-alive</Connection></response></headers></item><item><type>js</type><url>http://z-ecx.images-amazon.com/images/G/01/browser-scripts/site-wide-js-1.7-beacon/site-wide-9578934314._V1_.js</url><size>271698</size><resp>911</resp><gzip>58622</gzip><expires>2032/10/10</expires><headers><request><User-Agent>Mozilla/5.0 (Macintosh; Intel Mac OS X) AppleWebKit/534.34 (KHTML, like Gecko) PhantomJS/1.7.0 Safari/534.34</User-Agent><Accept>*/*</Accept><Referer><![CDATA[http://www.amazon.com/gp/help/customer/display.html/ref=footer_shiprates?ie=UTF8&nodeId=468520]]></Referer></request><response><Server>Server</Server><Last-Modified>Thu, 11 Oct 2012 10:40:06 GMT</Last-Modified><Content-Type>application/x-javascript</Content-Type><Vary>Accept-Encoding</Vary><Content-Encoding>gzip</Content-Encoding><Cache-Control>public, max-age=630168296</Cache-Control><Expires>Sun, 10 Oct 2032 02:14:01 GMT</Expires><Date>Sun, 21 Oct 2012 11:29:05 GMT</Date><Connection>keep-alive</Connection></response></headers></item><item><type>cssimage</type><url>http://g-ecx.images-amazon.com/images/G/01/gno/beacon/BeaconSprite-US-01._V394051227_.png</url><size>6413</size><resp>817</resp><expires>2033/5/18</expires><headers><request><User-Agent>Mozilla/5.0 (Macintosh; Intel Mac OS X) AppleWebKit/534.34 (KHTML, like Gecko) PhantomJS/1.7.0 Safari/534.34</User-Agent><Referer><![CDATA[http://www.amazon.com/gp/help/customer/display.html/ref=footer_shiprates?ie=UTF8&nodeId=468520]]></Referer><Accept>*/*</Accept></request><response><Content-Type>image/png</Content-Type><Content-Length>6413</Content-Length><Connection>keep-alive</Connection><Date>Wed, 25 Jul 2012 20:19:40 GMT</Date><Server>Server</Server><Last-Modified>Tue, 24 Jul 2012 18:39:50 GMT</Last-Modified><Cache-Control>max-age=630720000,public</Cache-Control><Expires>Wed, 18 May 2033 03:33:20 GMT</Expires><Age>7571365</Age><X-Amz-Cf-Id>yP4I9GlIf1YhowLWdUoAVxv8lHMkueoxSsGn9E9wuODMDH7-4f8mNQ==</X-Amz-Cf-Id><Via>1.0 0b5a53004df3247b04bccfea37864767.cloudfront.net (CloudFront)</Via><X-Cache>Hit from cloudfront</X-Cache></response></headers></item><item><type>cssimage</type><url>http://g-ecx.images-amazon.com/images/G/01/x-locale/common/transparent-pixel._V386942464_.gif</url><size>43</size><resp>831</resp><expires>2033/5/18</expires><headers><request><User-Agent>Mozilla/5.0 (Macintosh; Intel Mac OS X) AppleWebKit/534.34 (KHTML, like Gecko) PhantomJS/1.7.0 Safari/534.34</User-Agent><Referer><![CDATA[http://www.amazon.com/gp/help/customer/display.html/ref=footer_shiprates?ie=UTF8&nodeId=468520]]></Referer><Accept>*/*</Accept></request><response><Content-Type>image/gif</Content-Type><Content-Length>43</Content-Length><Connection>keep-alive</Connection><Date>Tue, 25 Sep 2012 20:26:23 GMT</Date><Server>Server</Server><Cache-Control>max-age=630720000,public</Cache-Control><Expires>Wed, 18 May 2033 03:33:20 GMT</Expires><Last-Modified>Fri, 12 Sep 2008 10:13:34 GMT</Last-Modified><Age>2214162</Age><X-Amz-Cf-Id>sHLaOcPAVOuBu2Qg1QmhvnG1zQNZo89G818Y83eTVNnWq4ceyXi9_w==</X-Amz-Cf-Id><Via>1.0 0b5a53004df3247b04bccfea37864767.cloudfront.net (CloudFront)</Via><X-Cache>Hit from cloudfront</X-Cache></response></headers></item><item><type>cssimage</type><url>http://g-ecx.images-amazon.com/images/G/01/img12/APPAREL/EDITORIAL/FALL_1/HALLOWEEN/HELVETICA/3/HALLOWEEN_300x50_2._V386753010_.jpg</url><size>9864</size><resp>854</resp><expires>2033/5/18</expires><headers><request><User-Agent>Mozilla/5.0 (Macintosh; Intel Mac OS X) AppleWebKit/534.34 (KHTML, like Gecko) PhantomJS/1.7.0 Safari/534.34</User-Agent><Referer><![CDATA[http://www.amazon.com/gp/help/customer/display.html/ref=footer_shiprates?ie=UTF8&nodeId=468520]]></Referer><Accept>*/*</Accept></request><response><Content-Type>image/jpeg</Content-Type><Content-Length>9864</Content-Length><Connection>keep-alive</Connection><Date>Wed, 17 Oct 2012 23:27:03 GMT</Date><Server>Server</Server><Cache-Control>max-age=630720000,public</Cache-Control><Expires>Wed, 18 May 2033 03:33:20 GMT</Expires><Last-Modified>Wed, 17 Oct 2012 22:45:43 GMT</Last-Modified><Age>302522</Age><X-Amz-Cf-Id>Afq6RF74rMojDD70gLp33zC4VVEQFaGi4sEcQ1IQgmwzkjEd8Ei3cA==</X-Amz-Cf-Id><Via>1.0 0b5a53004df3247b04bccfea37864767.cloudfront.net (CloudFront)</Via><X-Cache>Hit from cloudfront</X-Cache></response></headers></item><item><type>cssimage</type><url>http://g-ecx.images-amazon.com/images/G/01/common/sprites/sprite-site-wide-2._V146303866_.png</url><size>14808</size><resp>874</resp><expires>2033/5/18</expires><headers><request><User-Agent>Mozilla/5.0 (Macintosh; Intel Mac OS X) AppleWebKit/534.34 (KHTML, like Gecko) PhantomJS/1.7.0 Safari/534.34</User-Agent><Referer><![CDATA[http://www.amazon.com/gp/help/customer/display.html/ref=footer_shiprates?ie=UTF8&nodeId=468520]]></Referer><Accept>*/*</Accept></request><response><Content-Type>image/png</Content-Type><Content-Length>14808</Content-Length><Connection>keep-alive</Connection><Date>Fri, 14 Sep 2012 19:42:20 GMT</Date><Server>Server</Server><Cache-Control>max-age=630720000,public</Cache-Control><Expires>Wed, 18 May 2033 03:33:20 GMT</Expires><Last-Modified>Sat, 02 Jun 2012 16:25:51 GMT</Last-Modified><Age>3167205</Age><X-Amz-Cf-Id>F-fBubETSDaemKAEuKrD2gzLkNwuY2AB15ZAj-zayDVFm6GK277Gkw==</X-Amz-Cf-Id><Via>1.0 0b5a53004df3247b04bccfea37864767.cloudfront.net (CloudFront)</Via><X-Cache>Hit from cloudfront</X-Cache></response></headers></item><item><type>cssimage</type><url>http://z-ecx.images-amazon.com/images/G/01/x-locale/cs/css/images/amznbtn-sprite03.png</url><size>43438</size><resp>830</resp><headers><request><User-Agent>Mozilla/5.0 (Macintosh; Intel Mac OS X) AppleWebKit/534.34 (KHTML, like Gecko) PhantomJS/1.7.0 Safari/534.34</User-Agent><Referer><![CDATA[http://www.amazon.com/gp/help/customer/display.html/ref=footer_shiprates?ie=UTF8&nodeId=468520]]></Referer><Accept>*/*</Accept></request><response><Server>Server</Server><Last-Modified>Thu, 27 Sep 2012 21:18:59 GMT</Last-Modified><Content-Length>43438</Content-Length><Content-Type>image/png</Content-Type><Date>Sun, 21 Oct 2012 11:29:05 GMT</Date><Connection>keep-alive</Connection></response></headers></item><item><type>cssimage</type><url>http://g-ecx.images-amazon.com/images/G/01/marketing/prime/ev/Sprite_Nav._V389709824_.png</url><size>0</size><resp>null</resp><headers><response></response></headers></item><item><type>image</type><url>http://ecx.images-amazon.com/images/G/01/x-locale/common/transparent-pixel._V386942464_.gif</url><size>43</size><resp>821</resp><expires>2033/5/18</expires><headers><request><User-Agent>Mozilla/5.0 (Macintosh; Intel Mac OS X) AppleWebKit/534.34 (KHTML, like Gecko) PhantomJS/1.7.0 Safari/534.34</User-Agent><Referer><![CDATA[http://www.amazon.com/gp/help/customer/display.html/ref=footer_shiprates?ie=UTF8&nodeId=468520]]></Referer><Accept>*/*</Accept></request><response><Content-Type>image/gif</Content-Type><Content-Length>43</Content-Length><Connection>keep-alive</Connection><Date>Tue, 25 Sep 2012 20:26:23 GMT</Date><Server>Server</Server><Cache-Control>max-age=630720000,public</Cache-Control><Expires>Wed, 18 May 2033 03:33:20 GMT</Expires><Last-Modified>Fri, 12 Sep 2008 10:13:34 GMT</Last-Modified><Age>2214162</Age><X-Amz-Cf-Id>pgYcJKOc88eXJbz5vL7cnEtZ7V0ZV77D221a8aowZKIhrXQvoHzvJA==</X-Amz-Cf-Id><Via>1.0 0b5a53004df3247b04bccfea37864767.cloudfront.net (CloudFront)</Via><X-Cache>Hit from cloudfront</X-Cache></response></headers></item><item><type>image</type><url>http://g-ecx.images-amazon.com/images/G/01/gno/images/general/navAmazonLogoFooter._V169459313_.gif</url><size>1216</size><resp>848</resp><expires>2033/5/18</expires><headers><request><User-Agent>Mozilla/5.0 (Macintosh; Intel Mac OS X) AppleWebKit/534.34 (KHTML, like Gecko) PhantomJS/1.7.0 Safari/534.34</User-Agent><Referer><![CDATA[http://www.amazon.com/gp/help/customer/display.html/ref=footer_shiprates?ie=UTF8&nodeId=468520]]></Referer><Accept>*/*</Accept></request><response><Content-Type>image/gif</Content-Type><Content-Length>1216</Content-Length><Connection>keep-alive</Connection><Date>Sat, 19 Nov 2011 13:44:21 GMT</Date><Server>Server</Server><Last-Modified>Mon, 28 Feb 2011 18:36:12 GMT</Last-Modified><Cache-Control>max-age=630720000,public</Cache-Control><Expires>Wed, 18 May 2033 03:33:20 GMT</Expires><Age>29108684</Age><X-Amz-Cf-Id>nGIviGW8w8f8VUX_7wqwxBIgfzlvXD1Cql4MBPWFBcdaJ3AWXfdv8A==</X-Amz-Cf-Id><Via>1.0 55e7d5b8ebb3124d57a5c6542c42b88e.cloudfront.net:11180 (CloudFront), 1.0 0b5a53004df3247b04bccfea37864767.cloudfront.net (CloudFront)</Via><X-Cache>Hit from cloudfront</X-Cache></response></headers></item><item><type>favicon</type><url>http://www.amazon.com/favicon.ico</url><size>0</size><resp>null</resp><headers><response></response></headers></item></comps></results>
