<?xml version="1.0" encoding="UTF-8"?><results filename="23"><w>149303</w><o>96</o><u>http://www.linkedin.com/directory/people/p.html</u><r>9</r><i>sitespeed.io-1.3</i><lt>1674</lt><g><ynumreq><score>96</score><message>This page has 3 external Javascript scripts.  Try combining them into one.</message><components></components></ynumreq><yemptysrc><score>100</score><message></message><components></components></yemptysrc><ycompress><score>100</score><message></message><components></components></ycompress><ycsstop><score>100</score><message></message><components></components></ycsstop><yjsbottom><score>100</score><message></message><components></components></yjsbottom><yexpressions><score>100</score><message></message><components></components></yexpressions><yexternal><message>Only consider this if your property is a common user home page.</message><components><item>There is a total of 6 inline scripts</item></components></yexternal><ydns><score>85</score><message>The components are split over more than 4 domains</message><components><item>www.linkedin.com: 2 components, 33.0K (33.0K GZip)</item><item>static.licdn.com: 2 components, 49.8K (49.9K GZip)</item><item>www.google-analytics.com: 1 component, 37.3K (37.3K GZip)</item><item>b.scorecardresearch.com: 1 component, 1.9K (1.9K GZip)</item><item>edge.quantserve.com: 1 component, 5.6K (5.6K GZip)</item><item>static01.linkedin.com: 1 component, 20.6K (21.0K GZip)</item><item>static02.linkedin.com: 1 component, 0.2K (0.2K GZip)</item></components></ydns><yminify><score>90</score><message>There is 1 component that can be minified</message><components><item><![CDATA[inline &lt;script&gt; tag #4]]></item></components></yminify><yredirects><score>100</score><message></message><components></components></yredirects><ydupes><score>100</score><message></message><components></components></ydupes><yetags><score>100</score><message></message><components></components></yetags><yxhr><score>100</score><message></message><components></components></yxhr><yxhrmethod><score>100</score><message></message><components></components></yxhrmethod><ymindom><score>100</score><message></message><components></components></ymindom><yno404><score>100</score><message></message><components></components></yno404><ymincookie><score>100</score><message></message><components></components></ymincookie><ycookiefree><score>100</score><message></message><components></components></ycookiefree><ynofilter><score>100</score><message></message><components></components></ynofilter><yimgnoscale><score>100</score><message></message><components></components></yimgnoscale><_3po_asyncjs><score>79</score><message>The following 1 3rd party script not loaded asynchronously:</message><components><item>http://www.google-analytics.com/ga.js</item></components></_3po_asyncjs><_3po_jsonce><score>100</score><message></message><components></components></_3po_jsonce><cssprint><score>100</score><message></message><components></components></cssprint><cssinheaddomain><score>90</score><message>The following 1 css are loaded from a different domain inside head, causing DNS lookups before page is rendered. Unique DNS in head that decreases the score:1.</message><components><item><![CDATA[http://static.licdn.com/scds/concat/common/css?v=build-2000_1_21446-prod&f=scss%2Fbase%2Freset_en_US&f=scss%2Fbase%2Fbase_en_US&f=scss%2Fmodules%2Fghost_label_en_US&f=scss%2Fbase%2Fimages_en_US&f=scss%2Fmodules%2Falerts_en_US&f=scss%2Fmodules%2Flegal_notice_en_US&f=scss%2Fmodules%2Ftabs_en_US&f=scss%2Fmodules%2Fcheck_textarea_en_US&f=scss%2Fmodules%2Fshow_more_en_US&f=scss%2Fmodules%2Fchrome_lite_en_US&f=scss%2Fbase%2Fbuttons_en_US&f=scss%2Fmodules%2Fdirectory_en_US]]></item></components></cssinheaddomain><syncjsinhead><score>100</score><message></message><components></components></syncjsinhead><avoidfont><score>100</score><message></message><components></components></avoidfont><totalrequests><score>100</score><message></message></totalrequests><expiresmod><score>89</score><message>There is 1 static component without a far-future expiration date. There is 1 static component that are skipped from the score calculation:http://www.google-analytics.com/ga.js</message><components><item>http://edge.quantserve.com/quant.js</item></components></expiresmod><spof><score>90</score><message>The following 1 assets are loaded from a different domain inside head and could be a single point of failure. </message><components><item><![CDATA[http://static.licdn.com/scds/concat/common/css?v=build-2000_1_21446-prod&f=scss%2Fbase%2Freset_en_US&f=scss%2Fbase%2Fbase_en_US&f=scss%2Fmodules%2Fghost_label_en_US&f=scss%2Fbase%2Fimages_en_US&f=scss%2Fmodules%2Falerts_en_US&f=scss%2Fmodules%2Flegal_notice_en_US&f=scss%2Fmodules%2Ftabs_en_US&f=scss%2Fmodules%2Fcheck_textarea_en_US&f=scss%2Fmodules%2Fshow_more_en_US&f=scss%2Fmodules%2Fchrome_lite_en_US&f=scss%2Fbase%2Fbuttons_en_US&f=scss%2Fmodules%2Fdirectory_en_US]]></item></components></spof></g><w_c>33073</w_c><r_c>4</r_c><stats><doc><r>1</r><w>33073</w></doc><css><r>1</r><w>48920</w></css><js><r>3</r><w>44932</w></js><cssimage><r>2</r><w>21300</w></cssimage><image><r>1</r><w>1078</w></image><favicon><r>1</r><w>0</w></favicon></stats><stats_c><doc><r>1</r><w>33073</w></doc><js><r>2</r><w>0</w></js><favicon><r>1</r><w>0</w></favicon></stats_c><comps><item><type>doc</type><url>http://www.linkedin.com/directory/people/p.html</url><size>33073</size><resp>924</resp><gzip>33073</gzip><cr>72</cr><cs>72</cs><headers><request><User-Agent>Mozilla/5.0 (Macintosh; Intel Mac OS X) AppleWebKit/534.34 (KHTML, like Gecko) PhantomJS/1.7.0 Safari/534.34</User-Agent><Accept>text/html,application/xhtml+xml,application/xml;q=0.9,*/*;q=0.8</Accept></request><response><Server>Apache-Coyote/1.1</Server><Content-Type>text/html;charset=UTF-8</Content-Type><Content-Language>en-US</Content-Language><Vary>Accept-Encoding</Vary><Date>Wed, 14 Nov 2012 23:58:03 GMT</Date><X-Fs-Uuid>85bdb64c55273de2e0fe459214c4f895</X-Fs-Uuid><X-Li-Uuid>hb22TFUnPeLg/kWSFMT4lQ==</X-Li-Uuid><Age>1</Age><Connection>keep-alive</Connection><Content-Encoding>gzip</Content-Encoding><Set-Cookie><![CDATA[lang="v=2&lang=en-us"; Version=1; Domain=linkedin.com; Path=/
X-LI-IDC=C1]]></Set-Cookie></response></headers></item><item><type>css</type><url><![CDATA[http://static.licdn.com/scds/concat/common/css?v=build-2000_1_21446-prod&f=scss%2Fbase%2Freset_en_US&f=scss%2Fbase%2Fbase_en_US&f=scss%2Fmodules%2Fghost_label_en_US&f=scss%2Fbase%2Fimages_en_US&f=scss%2Fmodules%2Falerts_en_US&f=scss%2Fmodules%2Flegal_notice_en_US&f=scss%2Fmodules%2Ftabs_en_US&f=scss%2Fmodules%2Fcheck_textarea_en_US&f=scss%2Fmodules%2Fshow_more_en_US&f=scss%2Fmodules%2Fchrome_lite_en_US&f=scss%2Fbase%2Fbuttons_en_US&f=scss%2Fmodules%2Fdirectory_en_US]]></url><size>48852</size><resp>931</resp><gzip>48920</gzip><expires>2013/10/18</expires><headers><request><User-Agent>Mozilla/5.0 (Macintosh; Intel Mac OS X) AppleWebKit/534.34 (KHTML, like Gecko) PhantomJS/1.7.0 Safari/534.34</User-Agent><Accept>text/css,*/*;q=0.1</Accept><Referer>http://www.linkedin.com/directory/people/p.html</Referer></request><response><Server>Apache-Coyote/1.1</Server><Access-Control-Allow-Origin>http://www.linkedin.com</Access-Control-Allow-Origin><Last-Modified>Wed, 17 Oct 2012 23:09:52 GMT</Last-Modified><Content-Type>text/css</Content-Type><Vary>Accept-Encoding</Vary><Content-Encoding>gzip</Content-Encoding><Cache-Control>max-age=29179142</Cache-Control><Expires>Fri, 18 Oct 2013 17:17:06 GMT</Expires><Date>Wed, 14 Nov 2012 23:58:04 GMT</Date><Connection>keep-alive</Connection></response></headers></item><item><type>js</type><url>http://www.google-analytics.com/ga.js</url><size>37362</size><resp>1025</resp><gzip>37362</gzip><expires>2012/11/15</expires><headers><request><User-Agent>Mozilla/5.0 (Macintosh; Intel Mac OS X) AppleWebKit/534.34 (KHTML, like Gecko) PhantomJS/1.7.0 Safari/534.34</User-Agent><Accept>*/*</Accept><Referer>http://www.linkedin.com/directory/people/p.html</Referer></request><response><Content-Encoding>gzip</Content-Encoding><Last-Modified>Wed, 07 Nov 2012 22:33:51 GMT</Last-Modified><Date>Wed, 14 Nov 2012 20:31:40 GMT</Date><Expires>Thu, 15 Nov 2012 08:31:40 GMT</Expires><Content-Type>text/javascript</Content-Type><Vary>Accept-Encoding</Vary><X-Content-Type-Options>nosniff, nosniff</X-Content-Type-Options><Cache-Control>max-age=43200, public</Cache-Control><Age>12384</Age><Server>GFE/2.0</Server></response></headers></item><item><type>js</type><url>http://b.scorecardresearch.com/beacon.js</url><size>1900</size><resp>1078</resp><gzip>1900</gzip><expires>2012/11/29</expires><headers><request><User-Agent>Mozilla/5.0 (Macintosh; Intel Mac OS X) AppleWebKit/534.34 (KHTML, like Gecko) PhantomJS/1.7.0 Safari/534.34</User-Agent><Accept>*/*</Accept><Referer>http://www.linkedin.com/directory/people/p.html</Referer></request><response><Content-Type>application/x-javascript</Content-Type><Vary>Accept-Encoding</Vary><Content-Encoding>gzip</Content-Encoding><Expires>Wed, 28 Nov 2012 23:58:04 GMT</Expires><Date>Wed, 14 Nov 2012 23:58:04 GMT</Date><Connection>keep-alive</Connection><Cache-Control>private, no-transform, max-age=1209600</Cache-Control></response></headers></item><item><type>js</type><url>http://edge.quantserve.com/quant.js</url><size>5670</size><resp>1088</resp><gzip>5670</gzip><expires>2012/11/16</expires><headers><request><User-Agent>Mozilla/5.0 (Macintosh; Intel Mac OS X) AppleWebKit/534.34 (KHTML, like Gecko) PhantomJS/1.7.0 Safari/534.34</User-Agent><Accept>*/*</Accept><Referer>http://www.linkedin.com/directory/people/p.html</Referer></request><response><Server>Apache</Server><Last-Modified>Mon, 25 Jun 2012 19:57:36 GMT</Last-Modified><Accept-Ranges>bytes</Accept-Ranges><Content-Type>application/x-javascript</Content-Type><Vary>Accept-Encoding</Vary><Content-Encoding>gzip</Content-Encoding><Cache-Control>private, max-age=86400</Cache-Control><Expires>Thu, 15 Nov 2012 23:58:04 GMT</Expires><Date>Wed, 14 Nov 2012 23:58:04 GMT</Date><Connection>keep-alive</Connection></response></headers></item><item><type>cssimage</type><url>http://static01.linkedin.com/scds/common/u/img/sprite/sprite_global_v8.png</url><size>20664</size><resp>948</resp><gzip>21084</gzip><expires>2013/9/1</expires><headers><request><User-Agent>Mozilla/5.0 (Macintosh; Intel Mac OS X) AppleWebKit/534.34 (KHTML, like Gecko) PhantomJS/1.7.0 Safari/534.34</User-Agent><Referer>http://www.linkedin.com/directory/people/p.html</Referer><Accept>*/*</Accept></request><response><Server>Apache-Coyote/1.1</Server><Access-Control-Allow-Origin>http://www.linkedin.com</Access-Control-Allow-Origin><Last-Modified>Sat, 01 Sep 2012 00:58:09 GMT</Last-Modified><Content-Type>image/png</Content-Type><Vary>Accept-Encoding</Vary><Content-Encoding>gzip</Content-Encoding><Cache-Control>max-age=25060335</Cache-Control><Expires>Sun, 01 Sep 2013 01:10:19 GMT</Expires><Date>Wed, 14 Nov 2012 23:58:04 GMT</Date><Connection>keep-alive</Connection></response></headers></item><item><type>cssimage</type><url>http://static02.linkedin.com/scds/common/u/img/bg/bg_border_3x1.png</url><size>215</size><resp>946</resp><gzip>216</gzip><expires>2013/4/6</expires><headers><request><User-Agent>Mozilla/5.0 (Macintosh; Intel Mac OS X) AppleWebKit/534.34 (KHTML, like Gecko) PhantomJS/1.7.0 Safari/534.34</User-Agent><Referer>http://www.linkedin.com/directory/people/p.html</Referer><Accept>*/*</Accept></request><response><Server>Apache-Coyote/1.1</Server><Access-Control-Allow-Origin>http://www.linkedin.com</Access-Control-Allow-Origin><Content-Type>image/png</Content-Type><Content-Encoding>gzip</Content-Encoding><Vary>Accept-Encoding</Vary><Cache-Control>max-age=12328345</Cache-Control><Expires>Sat, 06 Apr 2013 16:30:29 GMT</Expires><Date>Wed, 14 Nov 2012 23:58:04 GMT</Date><Connection>keep-alive</Connection></response></headers></item><item><type>image</type><url>http://static.licdn.com/scds/common/u/img/logos/logo_linkedin_92x22.png</url><size>1045</size><resp>944</resp><gzip>1078</gzip><expires>2013/8/16</expires><headers><request><User-Agent>Mozilla/5.0 (Macintosh; Intel Mac OS X) AppleWebKit/534.34 (KHTML, like Gecko) PhantomJS/1.7.0 Safari/534.34</User-Agent><Referer>http://www.linkedin.com/directory/people/p.html</Referer><Accept>*/*</Accept></request><response><Server>Apache-Coyote/1.1</Server><Access-Control-Allow-Origin>http://www.linkedin.com</Access-Control-Allow-Origin><Last-Modified>Thu, 16 Aug 2012 01:24:37 GMT</Last-Modified><Content-Type>image/png</Content-Type><Vary>Accept-Encoding</Vary><Content-Encoding>gzip</Content-Encoding><Cache-Control>max-age=23732089</Cache-Control><Expires>Fri, 16 Aug 2013 16:12:53 GMT</Expires><Date>Wed, 14 Nov 2012 23:58:04 GMT</Date><Connection>keep-alive</Connection></response></headers></item><item><type>favicon</type><url>http://www.linkedin.com/img/favicon_v3.ico</url><size>0</size><resp>null</resp><headers><response></response></headers></item></comps><dictionary><w>size</w><o>overall score</o><u>url</u><r>total number of requests</r><s>space id of the page</s><i>id of the ruleset used</i><lt>page load time</lt><grades><![CDATA[100 >= A >= 90 > B >= 80 > C >= 70 > D >= 60 > E >= 50 > F >= 0 > N/A = -1]]></grades><g>scores of all rules in the ruleset</g><rules><ynumreq><name>Make fewer HTTP requests</name><info>Decreasing the number of components on a page reduces the number of HTTP requests required to render the page, resulting in faster page loads.  Some ways to reduce the number of components include:  combine files, combine multiple scripts into one script, combine multiple CSS files into one style sheet, and use CSS Sprites and image maps.</info><weight>8</weight></ynumreq><yemptysrc><name>Avoid empty src or href</name><info>You may expect a browser to do nothing when it encounters an empty image src.  However, it is not the case in most browsers. IE makes a request to the directory in which the page is located; Safari, Chrome, Firefox 3 and earlier make a request to the actual page itself. This behavior could possibly corrupt user data, waste server computing cycles generating a page that will never be viewed, and in the worst case, cripple your servers by sending a large amount of unexpected traffic.</info><weight>30</weight></yemptysrc><ycompress><name>Compress components with gzip</name><info>Compression reduces response times by reducing the size of the HTTP response.  Gzip is the most popular and effective compression method currently available and generally reduces the response size by about 70%.  Approximately 90% of today's Internet traffic travels through browsers that claim to support gzip.</info><weight>8</weight></ycompress><ycsstop><name>Put CSS at top</name><info>Moving style sheets to the document HEAD element helps pages appear to load quicker since this allows pages to render progressively.</info><weight>4</weight></ycsstop><yjsbottom><name>Put JavaScript at bottom</name><info>JavaScript scripts block parallel downloads; that is, when a script is downloading, the browser will not start any other downloads.  To help the page load faster, move scripts to the bottom of the page if they are deferrable.</info><weight>4</weight></yjsbottom><yexpressions><name>Avoid CSS expressions</name><info>CSS expressions (supported in IE beginning with Version 5) are a powerful, and dangerous, way to dynamically set CSS properties.  These expressions are evaluated frequently:  when the page is rendered and resized, when the page is scrolled, and even when the user moves the mouse over the page.  These frequent evaluations degrade the user experience.</info><weight>3</weight></yexpressions><yexternal><name>Make JavaScript and CSS external</name><info>Using external JavaScript and CSS files generally produces faster pages because the files are cached by the browser.  JavaScript and CSS that are inlined in HTML documents get downloaded each time the HTML document is requested.  This reduces the number of HTTP requests but increases the HTML document size.  On the other hand, if the JavaScript and CSS are in external files cached by the browser, the HTML document size is reduced without increasing the number of HTTP requests.</info><weight>4</weight></yexternal><ydns><name>Reduce DNS lookups</name><info>The Domain Name System (DNS) maps hostnames to IP addresses, just like phonebooks map people's names to their phone numbers.  When you type URL www.yahoo.com into the browser, the browser contacts a DNS resolver that returns the server's IP address.  DNS has a cost; typically it takes 20 to 120 milliseconds for it to look up the IP address for a hostname.  The browser cannot download anything from the host until the lookup completes.</info><weight>3</weight></ydns><yminify><name>Minify JavaScript and CSS</name><info>Minification removes unnecessary characters from a file to reduce its size, thereby improving load times.  When a file is minified, comments and unneeded white space characters (space, newline, and tab) are removed.  This improves response time since the size of the download files is reduced.</info><weight>4</weight></yminify><yredirects><name>Avoid URL redirects</name><info>URL redirects are made using HTTP status codes 301 and 302.  They tell the browser to go to another location.  Inserting a redirect between the user and the final HTML document delays everything on the page since nothing on the page can be rendered and no components can be downloaded until the HTML document arrives.</info><weight>4</weight></yredirects><ydupes><name>Remove duplicate JavaScript and CSS</name><info>Duplicate JavaScript and CSS files hurt performance by creating unnecessary HTTP requests (IE only) and wasted JavaScript execution (IE and Firefox).  In IE, if an external script is included twice and is not cacheable, it generates two HTTP requests during page loading.  Even if the script is cacheable, extra HTTP requests occur when the user reloads the page.  In both IE and Firefox, duplicate JavaScript scripts cause wasted time evaluating the same scripts more than once.  This redundant script execution happens regardless of whether the script is cacheable.</info><weight>4</weight></ydupes><yetags><name>Configure entity tags (ETags)</name><info>Entity tags (ETags) are a mechanism web servers and the browser use to determine whether a component in the browser's cache matches one on the origin server.  Since ETags are typically constructed using attributes that make them unique to a specific server hosting a site, the tags will not match when a browser gets the original component from one server and later tries to validate that component on a different server.</info><weight>2</weight></yetags><yxhr><name>Make AJAX cacheable</name><info>One of AJAX's benefits is it provides instantaneous feedback to the user because it requests information asynchronously from the backend web server.  However, using AJAX does not guarantee the user will not wait for the asynchronous JavaScript and XML responses to return.  Optimizing AJAX responses is important to improve performance, and making the responses cacheable is the best way to optimize them.</info><weight>4</weight></yxhr><yxhrmethod><name>Use GET for AJAX requests</name><info>When using the XMLHttpRequest object, the browser implements POST in two steps:  (1) send the headers, and (2) send the data.  It is better to use GET instead of POST since GET sends the headers and the data together (unless there are many cookies).  IE's maximum URL length is 2 KB, so if you are sending more than this amount of data you may not be able to use GET.</info><weight>3</weight></yxhrmethod><ymindom><name>Reduce the number of DOM elements</name><info>A complex page means more bytes to download, and it also means slower DOM access in JavaScript.  Reduce the number of DOM elements on the page to improve performance.</info><weight>3</weight></ymindom><yno404><name>Avoid HTTP 404 (Not Found) error</name><info>Making an HTTP request and receiving a 404 (Not Found) error is expensive and degrades the user experience.  Some sites have helpful 404 messages (for example, "Did you mean ...?"), which may assist the user, but server resources are still wasted.</info><weight>4</weight></yno404><ymincookie><name>Reduce cookie size</name><info>HTTP cookies are used for authentication, personalization, and other purposes.  Cookie information is exchanged in the HTTP headers between web servers and the browser, so keeping the cookie size small minimizes the impact on response time.</info><weight>3</weight></ymincookie><ycookiefree><name>Use cookie-free domains</name><info>When the browser requests a static image and sends cookies with the request, the server ignores the cookies.  These cookies are unnecessary network traffic.  To workaround this problem, make sure that static components are requested with cookie-free requests by creating a subdomain and hosting them there.</info><weight>3</weight></ycookiefree><ynofilter><name>Avoid AlphaImageLoader filter</name><info>The IE-proprietary AlphaImageLoader filter attempts to fix a problem with semi-transparent true color PNG files in IE versions less than Version 7.  However, this filter blocks rendering and freezes the browser while the image is being downloaded.  Additionally, it increases memory consumption.  The problem is further multiplied because it is applied per element, not per image.</info><weight>4</weight></ynofilter><yimgnoscale><name>Do not scale images in HTML</name><info>Web page designers sometimes set image dimensions by using the width and height attributes of the HTML image element.  Avoid doing this since it can result in images being larger than needed.  For example, if your page requires image myimg.jpg which has dimensions 240x720 but displays it with dimensions 120x360 using the width and height attributes, then the browser will download an image that is larger than necessary.</info><weight>3</weight></yimgnoscale><_3po_asyncjs><name>Load third party javascript asynchronously</name><info><![CDATA[Always load third party javascript asynchronously. Third parties that will be checked are twitter, facebook, google (api, analythics, ajax), linkedin, disqus, pinterest & jquery.]]></info><weight>10</weight></_3po_asyncjs><_3po_jsonce><name>Load the third party javascript only once</name><info>Make sure the third party javascripts are loaded only once.</info><weight>10</weight></_3po_jsonce><cssprint><name>Avoid loading specific css for print</name><info>Loading a specific stylesheet for print, can block rendering in your browser (depending on browser version) and will for almost all browsers, block the onload event to fire (even though the print stylesheet is not even used!).</info><weight>3</weight></cssprint><cssinheaddomain><name>Load CSS in head from document domain</name><info>CSS files inside of HEAD should be loaded from the same domain as the main document, in order to avoid DNS lookups, because you want to have the HEAD part of the page finished as fast as possible, for the browser to be abe to start render the page. This is extra important for mobile.</info><weight>8</weight></cssinheaddomain><syncjsinhead><name>Never load JS synchronously in head</name><info>Javascript files should never be loaded synchronously in HEAD, because it will block the rendering of the page.</info><weight>20</weight></syncjsinhead><avoidfont><name>Avoid use of web fonts</name><info>Avoid use of webfonts because they will decrease the performance of the page.</info><weight>1</weight></avoidfont><totalrequests><name>Reduce number of total requests</name><info>Avoid to have too many requests on your page. The more requests, the slower the page will be for the end user.</info><weight>10</weight></totalrequests><expiresmod><name>Have long expire headers for static components</name><info>By adding long HTTP expires headers to your static files, the files will be cached in the end users browser. This is the standard expires Yslow rule with the twist that you do not get penalized using Google Analythics or Gaug.es.</info><weight>10</weight></expiresmod><spof><name>Frontend single point of failure</name><info>A page can be stopped to be loaded in the browser, if a single script or css could not be fetched (the white screen of death), and that is something you really want to avoid. Never load 3rd party components inside of HEAD!</info><weight>5</weight></spof></rules><w_c>page weight with primed cache</w_c><r_c>number of requests with primed cache</r_c><stats>number of requests and weight grouped by component type</stats><stats_c>number of request and weight of components group by component type with primed cache</stats_c><comps>array of all the components found on the page</comps></dictionary></results>
